Workbook

Sheet Schedule
A1: Sr No. | B1: Vendor Code | C1: Erp Id | D1: Zone | E1: State | F1: Location | G1: Agency Type | H1: Vendor Name | I1: Owner/Partners/Director's Name | J1: Contact Person | K1: Address | L1: Office Phone # | M1: YBL collection contact | N1: Owner Phone # | O1: EMail ID | P1: Alternate Email Id | Q1: PAN No | R1: Service Tax No | S1: GST no | T1: ARN Number | U1: YBL A/c No | V1: BANK_NAME | W1: YBL A/c Status | X1: Category | Y1: Status | Z1: Agreement Date (DD/MM/YYYY) | AA1: ORM/BH Approval (DD/MM/YYYY) | AB1: Discontinued/ Termination Date (DD/MM/YYYY) | AC1: Discontinued/Termination Reason | AD1: Remarks | AE1: ERP ID | AF1: Vendor Name | AG1: JAN'26 | AH1: FEB'26 | AI1: MAR'26 | AJ1: Total | AK1: As per Repo Tracker | AL1: Eligible Reason | AM1: Eligible Status | AN1: Audit Firm | AO1: RCM Name | AP1: Audited address | AQ1: Status | AR1: Remarks | AS1: Console | AT1: Manager | AU1: Auditor Name | AV1: Auditor Cont. Number | AW1: Audit date | AX1: Vendor Name | AY1: Location | AZ1: State | BA1: CM ID | BB1: CM | BC1: RCM | BD1: Vendor Name | BE1: File Name | BF1: Collection Agency | BG1: Repo Agency
A2: 1 | B2: 66907 | C2: 66907 | D2: East | E2: Assam | F2: Guwahati | G2: Collection & Repossession Agency | H2: Aba | I2: Junti Bania | J2: Junti Bania | K2: House No -33, Rangmili Path, M T Road, Guwahati - 780124 | L2: 8638990389,7002339398 | M2: 8638990389,7002339398 | N2: 8638990389,7002339398 | O2: aba.guwahati002@gmail.com, northeast@abaguwahati.Co.in | P2: NA | Q2: AXUPB5259R | S2: 18AXUPB5259R1ZG | V2: YES BANK LIMITED | X2: Properitoryship | Y2: Active | Z2: 45197 | AA2: 45195 | AE2: 66907 | AF2: ABA | AG2: 244 | AH2: 267 | AI2: 279 | AJ2: 790 | AL2: Allocaton given by Collection agency | AM2: Eligible for audit | AN2: KGAC | AO2: Md Shabbir Alam | AP2: 3 Rd Florr House No 20 Hr Port Near Decora Marriage Hall Rgb Road Guwahati | AQ2: Audited | AR2: NA | AT2: Abdul Kayum | AU2: Pradeep | AV2: 8287823681 | AW2: 46130 | AX2: Kumar Gaurav Agarwal & company | AY2: Guwahati | AZ2: Assam | BA2: BKE6757902, GCE6775573 | BB2: Bikash Kalita, Gautam Chowdhury | BC2: Subhasis Banerjee, Md Shabbir Alam | BD2: Aba | BE2: Aba - Guwahati - Assam | BF2: Aba_Collection Agency_Guwahati_Assam
A3: 2 | B3: Z20583 | C3: 26018 | D3: East | E3: Assam | F3: Guwahati | G3: Collection & Repossession Agency | H3: Fairadvisory Legalservices | I3: Nidhi Prakash Yadav | J3: Nidhi Prakash Yadav | K3: H No .4 Dispur Gate Naharani Path Guwahati Assam 781038 | L3: 0657-2438714 | M3: 0657-2438714,8521158806,7677437282,7978942486,7504735768,9861236045,6901459251,9934824866,9864030986,7061093255, 8210106510, 8210106510, 7338703469, 8610129493, 8754312805, 9087498198, 9360441597, 9952066494, | N3: 9031040500 | O3: fairadvisory.jsr@gmail.com; collection@fairadvisory.net.in | P3: nidhi_kgdn@rediffmail.com | Q3: AAPPY5351B | S3: 20AAPPY5351B1ZS | V3: YES BANK LIMITED | X3: Properitoryship | Y3: Active | Z3: 43297 | AA3: 43297 | AD3: New email id registeration request received in Jul, Repo activity added in Dec | AE3: 26018 | AF3: Fairadvisory Legalservices | AG3: 1762 | AH3: 1483 | AI3: 1338 | AJ3: 4583 | AK3: 5 | AL3: Allocaton given by Collection & Repossession | AM3: Eligible for audit | AN3: KGAC | AO3: Biswarup Ghosh | AP3: NA | AQ3: Not Audited | AR3: Visited the agency but audit not done due to agency is working for Yes Bank from their another branch, Address : 454, Urao Basti, Old Sitaramdera, P.O - Agrico, Jamshedpur - 831009 | AS3: NA | AT3: NA | AU3: NA | AV3: NA | AW3: NA | AX3: NA | AY3: Guwahati | AZ3: Assam | BA3: PSE6778569, JSE6785583, PYE6778749, NKE6776587, SDE6778568, SSE6756265, NDE6765957, STE6769262, SBE5788018 | BB3: Pravesh Sharma, Jay Shukla, Pankaj Yadav, Nitumani Kalita, Suman Das, Santosh Sharmayanjyoti Deka, Santosh Thakur, Sachin Bharti | BC3: Biswarup Ghosh, Md Shabbir Alam | BD3: Fairadvisory Legalservices | BE3: NA | BF3: NA | BG3: NA
A4: 119 | B4: NA | C4: 185979 | D4: North | E4: Delhi | F4: Delhi | G4: Collection Agency | H4: Accurate Investigations | I4: Daya Nand Kaushik | J4: Daya Nand Kaushik | K4: A5- Shankar Garden Opp Metro Pillar No 618, Najafgarh Road Vikas Puri New Delhi 110018 | L4: 9873412356 , 7217773183 | M4: 9873412356 , 7217773183 | N4: 9873412356 , 7217773183 | O4: dayanand.kaushik1972@gmail.com ; veenu.1976@gmail.com ; recon@accurateinvestigations.in | P4: NA | Q4: ASZPK5551F | S4: 07ASZPK5551F1Z9 | X4: Properitoryship | Y4: Active | Z4: 45996 | AA4: 45996 | AD4: Supplementary done on 5th Dec 25 | AE4: 185979 | AF4: ACCURATE INVESTIGATIONS | AG4: 248 | AH4: 586 | AI4: 695 | AJ4: 1529 | AL4: Allocaton given by Collection agency | AM4: Eligible for audit | AN4: KGAC | AO4: NA | AP4: A5- Shankar Garden Opp Metro Pillar No 618, Najafgarh Road Vikas Puri New Delhi 110018 | AQ4: Audited | AR4: NA | AT4: Pravesh (9205533109) | AU4: Parteek Yadav | AV4: 7460008081 | AW4: 46120 | AX4: Kumar Gaurav Agarwal & company | AY4: Delhi | AZ4: Delhi | BA4: VGE6773224, SRE6782838, NKE6775741, JSE6785583, SBE6782270 | BB4: Vishal Gupta, Sidharth RaNitin Kumar, Jay Shukla, Subhajit Bhowmik | BC4: Na | BD4: Accurate Investigations | BE4: Accurate Investigations - Delhi | BF4: Accurate Investigations_Collection Agency_Delhi
A5: 179 | B5: NA | C5: 351028 | D5: North | E5: Uttar Pradesh | F5: Lucknow | G5: Repossession Agency | H5: Aarya Associates | I5: Vijender Singh | J5: Vijender Singh | K5: Flat No.210,Skyline-3 Sushant Golf City Ansal Api Lucknow Uttar Pradesh-226030 | L5: 7070007010 | M5: 7070007010 | N5: 7070007010 | O5: aarya.repo2014@gmail.com | P5: NA | Q5: CDEPS6081E | S5: 09CDEPS6081E1ZA | X5: Proprietorship | Y5: Active | Z5: 45835 | AA5: 45834 | AE5: 351028 | AF5: AARYA ASSOCIATES | AG5: NA | AH5: NA | AI5: NA | AJ5: NA | AK5: 10 | AL5: Allocaton given by Repo agency | AM5: Eligible for audit | AN5: KGAC | AO5: #N/A | AP5: Flat No.210,Skyline-3 Sushant Golf City Ansal Api Lucknow Uttar Pradesh-226030 | AQ5: Audited | AR5: NA | AT5: Aaditya Gupta : 8931845182 | AU5: Hariom Sharma | AV5: 9810670823 | AW5: 46125 | AX5: Kumar Gaurav Agarwal & company | AY5: Lucknow | AZ5: Uttar Pradesh | BA5: NA | BB5: Shyam Parkash, Rittin Arya, Vivek Shukla, Vivek Kumar Shukla | BC5: Sameer Dhar, Abhinav Lal, Sanjeev Kumar | BD5: Aarya Associates | BE5: Aarya Associates - Lucknow - Uttar Pradesh | BF5: Aarya Associates_Collection Agency_Lucknow_Uttar Pradesh | BG5: Aarya Associates_Repo Agency_Lucknow_Uttar Pradesh
A6: 84 | B6: Z15138 | C6: 26225 | D6: North | E6: Uttar Pradesh | F6: Kanpur | G6: Collection & Repossession Agency | H6: Agpo Management Services Pvt Ltd - Kanpur | I6: Gaurav Agrawal | J6: Gaurav Agrawal | K6: 2Nd Floor, 111/273 Harsh Nagar,Kanpur 208012 | L6: 0522-4958979,9839068693,0512-2540019,0562-4000125,0522-4622891 | M6: 0522-4958979,9839068693,0512-2540019,0562-4000125,8869880805,7080800310,7905710207,9335905751,9720123148,9198779911,9044015935,7800029105,9359051896,9161544560,9026110389,8588918415,7080329092,8868065575,0522-4622891 | N6: 0512-3016879 | O6: YESBANKAGPO@GMAIL.COM | P6: NA | Q6: AAECA4088K | S6: 09AAECA4088K1ZB | V6: ICICI BANK LIMITED | X6: PVT Ltd | Y6: Active | Z6: 43115 | AA6: 43066 | AE6: 26225 | AF6: Agpo Management Services Pvt Ltd | AG6: 1602 | AH6: 1715 | AI6: 2033 | AJ6: 5350 | AK6: 9 | AL6: Allocaton given by Collection & Repossession | AM6: Eligible for audit | AN6: KGAC | AO6: Abhinav Lal | AP6: 2Nd Floor, 111/273 Harsh Nagar,Kanpur 208012 | AQ6: Audited | AR6: Audited for Collection Only, as no activity of repossession are done from Kanpur branch | AT6: Md Imran | AU6: Chandan Sharma | AV6: 7753851136 | AW6: 46123 | AX6: Kumar Gaurav Agarwal & company | AY6: Kanpur | AZ6: Uttar Pradesh | BA6: VME6772902, SPE6785038, SCE6722048, SKE6774754, APE6750911, RSE6763776, NSE6773411, RHE6775503, HJE6739606, DAE6777331, VGE6786972, PKE6749748 | BB6: Vaibhav Mishra, Shashi Pratap Singh, Sachin Chauhan, Satendra Kumar, Amit Pandey, Ram Shankar, Nitin Srivastava, Rahul Harishankar, Harish Johar, Devendra AsthaVivek Gupta, Pawan Kumar | BC6: Sameer Dhar, Sanjeev Kumar, Abhinav Lal, Subhodip Mukherjee, Vineet Kumar | BD6: Agpo Management Services Pvt Ltd - Kanpur | BE6: Agpo Management Services Pvt Ltd - Kanpur - Uttar Pradesh | BF6: Agpo Management Services Pvt Ltd - Kanpur_Collection Agency_Uttar Pradesh
A7: 6 | B7: Z20543 | C7: 25557 | D7: East | E7: Assam | F7: Siliguri | G7: Collection & Repossession Agency | H7: Aim Corporate | I7: Sanjay Gupta | J7: Sanjay Gupta/Suresh Bisoi | K7: 102 Ramkrishna Raod,Ashrampara, Pin-734001,Word No-14, Siliguri,West Bengal | L7: 86480,30702,9007374460,9874289876,7595900524 | M7: 86480,30702,9007374460,9836763581,7044067822,9051761080,8697789378,8296720891,6290612984,8910991842,9804445016,9038223935,9874930018,9874289876,7980165338,9832055052,7001938434,7000482645,9098301963,8240590554,9002842557,8319378592,7718236167,8777381034,9977401420,9826122732,9062106927,7595900524,9830343106 | N7: 8697564337 | O7: collections5@aimcorporate.co | P7: NA | Q7: AVBPG1374M | S7: 19AVBPG1374M2ZD | V7: YES BANK LIMITED | X7: Properitoryship | Y7: Active | Z7: 43283 | AA7: 43281 | AD7: Repo activity added in Dec 21,Email id change req recd on 14th Jun. Supplementary agreement added for Jamshedpur Bhubaneshwar on 3rd Aug'22 | AE7: 25557 | AF7: Aim Corporate | AG7: 1287 | AH7: 1305 | AI7: 1328 | AJ7: 3920 | AK7: 16 | AL7: Allocaton given by Collection & Repossession | AM7: Eligible for audit | AN7: KGAC | AO7: Biswarup Ghosh | AP7: NA | AQ7: Not Audited | AR7: Visited the agency but audit not done due to agency is working for Yes Bank from their another branch, Address : 17/3 Sahapur Colony New Alipore, Kolkata-700053 | AS7: NA | AT7: NA | AU7: NA | AV7: NA | AW7: NA | AX7: NA | AY7: Siliguri | AZ7: Assam | BA7: KSE6767729, SME6784348, IEE6769906, PME6771779, RBE6757282, DSE6782069, SNE6610031, ASE6777499, TSE6288042, NKE6754736, RHE6158002, ABE6771337, OAE6762281, SGE6696032, MAE6785142, JME6788432 | BB7: Krishnendu Sarder, Saisab Mallick, Imran Elahi, Priyanka Mondal, Ritam Basak, Deepak Singh, Suryanarayan Nayak, Arindam Sarkar, Tarkeshwar Singh, Nishant Kumar, Rajkumar Hazra, Abhisek Bose, Ossam Aditya, Soumitra Ghosh, Monawwar Alam, Jayadev Mishra | BC7: Subhasis Banerjee, Biswarup Ghosh, Md Shabbir Alam | BD7: Aim Corporate | BE7: NA | BF7: NA | BG7: NA
A8: 86 | B8: Z15138 | C8: 26225 | D8: North | E8: Uttar Pradesh | F8: Lucknow | G8: Collection & Repossession Agency | H8: Agpo Management Services Pvt Ltd - Lucknow | I8: Gaurav Agrawal | J8: Gaurav Agrawal | K8: 2Nd Floor, Seth Sadan Compund, 20 Rana Pratap Marg, Lucknow, - 226001- | L8: 0522-4958979,9839068693,0512-2540019,0562-4000125,0522-4622891 | M8: 0522-4958979,9839068693,0512-2540019,0562-4000125,8869880805,7080800310,7905710207,9335905751,9720123148,9198779911,9044015935,7800029105,9359051896,9161544560,9026110389,8588918415,7080329092,8868065575,0522-4622891 | N8: 0512-3016879 | O8: YESBANKAGPO@GMAIL.COM | P8: NA | Q8: AAECA4088K | S8: 09AAECA4088K1ZB | V8: ICICI BANK LIMITED | X8: PVT Ltd | Y8: Active | Z8: 43115 | AA8: 43066 | AE8: 26225 | AF8: Agpo Management Services Pvt Ltd | AG8: 1602 | AH8: 1715 | AI8: 2033 | AJ8: 5350 | AK8: 9 | AL8: Allocaton given by Collection & Repossession | AM8: Eligible for audit | AN8: KGAC | AP8: 2Nd Floor, Seth Sadan Compund, 20 Rana Pratap Marg, Lucknow, - 226001- | AQ8: Audited | AR8: Audited for Collection Only, as no activity of repossession are done from Lucknow branch | AT8: Arvind Kumar Mishra : 7080800310 | AU8: Hariom Sharma | AV8: 9810670823 | AW8: 46126 | AX8: Kumar Gaurav Agarwal & company | AY8: Lucknow | AZ8: Uttar Pradesh | BA8: VME6772902, SPE6785038, SCE6722048, SKE6774754, APE6750911, RSE6763776, NSE6773411, RHE6775503, HJE6739606, DAE6777331, VGE6786972, PKE6749748 | BB8: Vaibhav Mishra, Shashi Pratap Singh, Sachin Chauhan, Satendra Kumar, Amit Pandey, Ram Shankar, Nitin Srivastava, Rahul Harishankar, Harish Johar, Devendra AsthaVivek Gupta, Pawan Kumar | BC8: Sameer Dhar, Sanjeev Kumar, Abhinav Lal, Subhodip Mukherjee, Vineet Kumar | BD8: Agpo Management Services Pvt Ltd - Lucknow | BE8: Agpo Management Services Pvt Ltd - Lucknow - Uttar Pradesh | BF8: Agpo Management Services Pvt Ltd - Lucknow_Collection Agency_Uttar Pradesh
A9: 37 | B9: NA | C9: 348998 | D9: North | E9: Delhi | F9: Delhi | G9: Collection & Repossession Agency | H9: Aim Associates | I9: Sanjay Sethi | J9: Sanjay Sethi | K9: 45-46 Balaji Complex, 2Nd Floor, Guru Nanak Nagar West Laxmi Nagar New Delhi 110092 | L9: 01146142871, 43702304 | M9: 01146142871, 43702304 | N9: 9811006913 | O9: ysethi@aimsanjay.com | P9: NA | Q9: ALJPS1500R | S9: 07ALJPS1500R1ZP | V9: ICICI BANK LIMITED | X9: Proprietorship | Y9: Active | Z9: 45838 | AA9: 45838 | AE9: 348998 | AF9: Aim Associates | AG9: 172 | AH9: 181 | AI9: 138 | AJ9: 491 | AL9: Allocaton given by Collection agency | AM9: Eligible for audit | AN9: KGAC | AO9: Sameer Dhar | AP9: 45-46 Balaji Complex, 2Nd Floor, Guru Nanak Nagar West Laxmi Nagar New Delhi 110092 | AQ9: Audited | AR9: NA | AT9: Sanjay Sethi /9811006913 | AU9: Abhinav Khurana | AV9: 9217935065 | AW9: 46123 | AX9: Kumar Gaurav Agarwal & company | AY9: Delhi | AZ9: Delhi | BA9: PGE6777921, NSE6771909 | BB9: Priyanka Guptarinder Singh | BC9: Sameer Dhar, Sanjeev Kumar | BD9: Aim Associates | BE9: Aim Associates - Delhi | BF9: Aim Associates_Collection Agency_Delhi
A10: 80 | B10: Z15138 | C10: 26225 | D10: North | E10: Uttar Pradesh | F10: Agra | G10: Collection & Repossession Agency | H10: Agpo Management Services Pvt Ltd - Agra | I10: Gaurav Agrawal | J10: Gaurav Agrawal | K10: Shop No 14, 2Nd Floor, Block No 1, Shoe Market, Sanjay Place, Agra - 282002- | L10: 0522-4958979,9839068693,0512-2540019,0562-4000125,0522-4622891 | M10: 0522-4958979,9839068693,0512-2540019,0562-4000125,8869880805,7080800310,7905710207,9335905751,9720123148,9198779911,9044015935,7800029105,9359051896,9161544560,9026110389,8588918415,7080329092,8868065575,0522-4622891 | N10: 0512-3016879 | O10: YESBANKAGPO@GMAIL.COM | P10: NA | Q10: AAECA4088K | S10: 09AAECA4088K1ZB | V10: ICICI BANK LIMITED | X10: PVT Ltd | Y10: Active | Z10: 43115 | AA10: 43066 | AE10: 26225 | AF10: Agpo Management Services Pvt Ltd | AG10: 1602 | AH10: 1715 | AI10: 2033 | AJ10: 5350 | AK10: 9 | AL10: Allocaton given by Collection & Repossession | AM10: Eligible for audit | AN10: KGAC | AP10: Shop No 14, 2Nd Floor, Block No 1, Shoe Market, Sanjay Place, Agra - 282002- | AQ10: Audited | AR10: NA | AT10: Ram Kumar | AU10: Chandan Sharma | AV10: 7753851136 | AW10: 46127 | AX10: Kumar Gaurav Agarwal & company | AY10: Agra | AZ10: Uttar Pradesh | BA10: VME6772902, SPE6785038, SCE6722048, SKE6774754, APE6750911, RSE6763776, NSE6773411, RHE6775503, HJE6739606, DAE6777331, VGE6786972, PKE6749748 | BB10: Vaibhav Mishra, Shashi Pratap Singh, Sachin Chauhan, Satendra Kumar, Amit Pandey, Ram Shankar, Nitin Srivastava, Rahul Harishankar, Harish Johar, Devendra AsthaVivek Gupta, Pawan Kumar | BC10: Sameer Dhar, Sanjeev Kumar, Abhinav Lal, Subhodip Mukherjee, Vineet Kumar | BD10: Agpo Management Services Pvt Ltd - Agra | BE10: Agpo Management Services Pvt Ltd - Agra - Uttar Pradesh | BF10: Agpo Management Services Pvt Ltd - Agra_Collection Agency_Uttar Pradesh | BG10: Agpo Management Services Pvt Ltd - Agra_Repo Agency_Uttar Pradesh
A11: 7 | B11: Z20543 | C11: 25557 | D11: East | E11: Bihar | F11: Patna | G11: Collection & Repossession Agency | H11: Aim Corporate - Patna | I11: Sanjay Gupta | J11: Sanjay Gupta/Suresh Bisoi | K11: A/56,Housing Colony Lohiyanagar,Kankarbagh Patna Bihar_800020 | L11: 86480,30702,9007374460,9874289876,7595900524 | M11: 86480,30702,9007374460,9836763581,7044067822,9051761080,8697789378,8296720891,6290612984,8910991842,9804445016,9038223935,9874930018,9874289876,7980165338,9832055052,7001938434,7000482645,9098301963,8240590554,9002842557,8319378592,7718236167,8777381034,9977401420,9826122732,9062106927,7595900524,9830343106 | N11: 8697564337 | O11: collections5@aimcorporate.co | P11: NA | Q11: AVBPG1374M | S11: 19AVBPG1374M2ZD | V11: YES BANK LIMITED | X11: Properitoryship | Y11: Active | Z11: 43283 | AA11: 43281 | AD11: Repo activity added in Dec 21,Email id change req recd on 14th Jun. Supplementary agreement added for Jamshedpur Bhubaneshwar on 3rd Aug'22 | AE11: 25557 | AF11: Aim Corporate | AG11: 1287 | AH11: 1305 | AI11: 1328 | AJ11: 3920 | AK11: 16 | AL11: Allocaton given by Collection & Repossession | AM11: Eligible for audit | AN11: KGAC | AO11: Biswarup Ghosh | AP11: A/56,Housing Colony Lohiyanagar,Kankarbagh Patna Bihar_800020 | AQ11: Audited | AR11: Audited for Collection Only, as no activity of repossession are done for the audit quarter | AT11: Manoj | AU11: Vikky Kumar | AV11: 9354241930 | AW11: 46134 | AX11: Kumar Gaurav Agarwal & company | AY11: Patna | AZ11: Bihar | BA11: KSE6767729, SME6784348, IEE6769906, PME6771779, RBE6757282, DSE6782069, SNE6610031, ASE6777499, TSE6288042, NKE6754736, RHE6158002, ABE6771337, OAE6762281, SGE6696032, MAE6785142, JME6788432 | BB11: Krishnendu Sarder, Saisab Mallick, Imran Elahi, Priyanka Mondal, Ritam Basak, Deepak Singh, Suryanarayan Nayak, Arindam Sarkar, Tarkeshwar Singh, Nishant Kumar, Rajkumar Hazra, Abhisek Bose, Ossam Aditya, Soumitra Ghosh, Monawwar Alam, Jayadev Mishra | BC11: Subhasis Banerjee, Biswarup Ghosh, Md Shabbir Alam | BD11: Aim Corporate - Patna | BE11: Aim Corporate - Patna - Bihar | BF11: Aim Corporate - Patna_Collection Agency_Bihar
A12: 10 | B12: Yblv1132 | C12: 307991 | D12: North | E12: Delhi | F12: Delhi | G12: Collection & Repossession Agency | H12: Ambitious Enterprises | I12: Rameshwar Jaiswal | J12: Rameshwar Jaiswal | K12: Rz-154A , Main Najafgarh Road, Uttam Nagar Delhi | L12: 7303036357 | M12: 7303036357 | N12: 7303036357 | O12: ambitiousenterprises5@gmail.com,ambitiousenterprises2@gmail.com | P12: NA | Q12: CHNPJ3651C | S12: 07CHNPJ3651C1ZG | V12: AU SMALL FINANCE BANK | X12: Properitoryship | Y12: Active | Z12: 45680 | AA12: 45679 | AE12: 307991 | AF12: AMBITIOUS ENTERPRISES | AG12: 140 | AH12: 78 | AI12: 121 | AJ12: 339 | AL12: Allocaton given by Collection agency | AM12: Eligible for audit | AN12: KGAC | AO12: Sameer Dhar | AP12: Rz-154A , Main Najafgarh Road, Uttam Nagar Delhi | AQ12: Audited | AR12: NA | AT12: Akhilesh Kumar Tripahi | AU12: Rahul Verma | AV12: 9354183359 | AW12: 46126 | AX12: Kumar Gaurav Agarwal & company | AY12: Delhi | AZ12: Delhi | BA12: NSE6771909, SKE5835012, MSE6236002, SRE6739824, NRE6746973 | BB12: Narinder Singh, Sushim Kumar, Manpreet Singh(Auto), Syed Razavdeep Rastogi | BC12: Sanjeev Kumar, Sameer Dhar | BD12: Ambitious Enterprises | BE12: Ambitious Enterprises - Delhi | BF12: Ambitious Enterprises_Collection Agency_Delhi
A13: 101 | B13: Z20543 | C13: 25557 | D13: East | E13: West Bengal | F13: Kolkata | G13: Collection & Repossession Agency | H13: Aim Corporate - Kolkata | I13: Sanjay Gupta | J13: Sanjay Gupta/Suresh Bisoi | K13: 17/3 Sahapur Colony New Alipore, Kolkata-700053 | L13: 86480,30702,9007374460,9874289876,7595900524 | M13: 86480,30702,9007374460,9836763581,7044067822,9051761080,8697789378,8296720891,6290612984,8910991842,9804445016,9038223935,9874930018,9874289876,7980165338,9832055052,7001938434,7000482645,9098301963,8240590554,9002842557,8319378592,7718236167,8777381034,9977401420,9826122732,9062106927,7595900524,9830343106 | N13: 8697564337 | O13: collections5@aimcorporate.co | P13: NA | Q13: AVBPG1374M | S13: 19AVBPG1374M2ZD | V13: YES BANK LIMITED | X13: Properitoryship | Y13: Active | Z13: 43283 | AA13: 43281 | AD13: Repo activity added in Dec 21,Email id change req recd on 14th Jun. Supplementary agreement added for Jamshedpur Bhubaneshwar on 3rd Aug'22 | AE13: 25557 | AF13: Aim Corporate | AG13: 1287 | AH13: 1305 | AI13: 1328 | AJ13: 3920 | AK13: 16 | AL13: Allocaton given by Collection & Repossession | AM13: Eligible for audit | AN13: KGAC | AO13: Biswarup Ghosh | AP13: 17/3 Sahapur Colony New Alipore, Kolkata-700053 Office Adders-34/ | AQ13: Audited | AR13: NA | AT13: Payal | AU13: Vikky Kumar | AV13: 9354241930 | AW13: 46121 | AX13: Kumar Gaurav Agarwal & company | AY13: Kolkata | AZ13: West Bengal | BA13: KSE6767729, SME6784348, IEE6769906, PME6771779, RBE6757282, DSE6782069, SNE6610031, ASE6777499, TSE6288042, NKE6754736, RHE6158002, ABE6771337, OAE6762281, SGE6696032, MAE6785142, JME6788432 | BB13: Krishnendu Sarder, Saisab Mallick, Imran Elahi, Priyanka Mondal, Ritam Basak, Deepak Singh, Suryanarayan Nayak, Arindam Sarkar, Tarkeshwar Singh, Nishant Kumar, Rajkumar Hazra, Abhisek Bose, Ossam Aditya, Soumitra Ghosh, Monawwar Alam, Jayadev Mishra | BC13: Subhasis Banerjee, Biswarup Ghosh, Md Shabbir Alam | BD13: Aim Corporate - Kolkata | BE13: Aim Corporate - Kolkata - West Bengal | BF13: Aim Corporate - Kolkata_Collection Agency_West Bengal | BG13: Aim Corporate - Kolkata_Repo Agency_West Bengal
A14: 181 | B14: NA | C14: 312995 | D14: North | E14: Uttar Pradesh | F14: Varanasi | G14: Repossession Agency | H14: Akhand Motors | I14: Akhand Ppratap Singh | J14: Akhand Ppratap Singh | K14: Vill Dalipur , Post - Mangari, Near Babatpur Airport Varanasi 221202 | L14: 8004555581 | M14: 8004555581 | N14: 8004555581 | O14: akhandmotors80@gmail.com | P14: NA | Q14: LYXPS0898G | S14: 09LYXPS0898G1Z2 | V14: HDFC BANK LTD | X14: Properitoryship | Y14: Active | Z14: 45670 | AA14: 45667 | AD14: New Repossession project | AE14: 312995 | AF14: AKHAND MOTORS | AG14: NA | AH14: NA | AI14: NA | AJ14: NA | AK14: 3 | AL14: Allocaton given by Repo agency | AM14: Eligible for audit | AN14: KGAC | AO14: #N/A | AP14: Vill Dalipur , Post - Mangari, Near Babatpur Airport Varanasi 221202 | AQ14: Audited | AR14: NA | AT14: Aditya Pratap Singh | AU14: Chandan Sharma | AV14: 7753851136 | AW14: 46120 | AX14: Kumar Gaurav Agarwal & company | AY14: Varanasi | AZ14: Uttar Pradesh | BA14: NA | BB14: Vivek Kumar Shukla, Sourabh Parihar, Punit Chhotelal Sharma | BC14: Dipak Mangaldas Dhandhukiya, Sanjeev Kumar | BD14: Akhand Motors | BE14: Akhand Motors - Varanasi - Uttar Pradesh | BF14: Akhand Motors_Collection Agency_Varanasi_Uttar Pradesh | BG14: Akhand Motors_Repo Agency_Varanasi_Uttar Pradesh
A15: 53 | B15: NA | C15: 313005 | D15: North | E15: Punjab | F15: Patiala | G15: Collection & Repossession Agency | H15: Ar Associates | I15: Anmol Kumar | J15: Anmol Kumar | K15: Sco 131 Chhoti Baradari, Patiala, Patiala | L15: 7355443003 | M15: 7355443003 | N15: 7355443003 | O15: ARassociate0786@gmail.com | P15: NA | Q15: GCIPK9297P | S15: 03GCIPK9297P1ZL | V15: STATE BANK OF INDIA | X15: Properitoryship | Y15: Active | Z15: 45685 | AA15: 45685 | AE15: 313005 | AF15: AR ASSOCIATES | AG15: 100 | AH15: 107 | AI15: 93 | AJ15: 300 | AL15: Allocaton given by Collection agency | AM15: Eligible for audit | AN15: KGAC | AO15: Ashutosh Gupta | AP15: Sethi Complex 2Nd Floor, Above Icici Bank Near Polo Ground, Patiala | AQ15: Audited | AR15: NA | AT15: Anmol Kumar | AU15: Aman Monga | AV15: 9990034588 | AW15: 46135 | AX15: Kumar Gaurav Agarwal & company | AY15: Patiala | AZ15: Punjab | BA15: MKE6407056 | BB15: Maninder Kumar | BC15: Ashutosh Gupta | BD15: Ar Associates | BE15: Ar Associates - Patiala - Punjab | BF15: Ar Associates_Collection Agency_Patiala_Punjab
A16: 24 | B16: NA | C16: 309009 | D16: North | E16: Uttar Pradesh | F16: Agra | G16: Collection & Repossession Agency | H16: Ansh Enterprises | I16: Rakesh Kumar | J16: Rakesh Kumar | K16: Shop No 5 , 1 St Floor Block 25 , Clothe Market Sanjay Palace Agra 283102 | L16: 9634815557 | M16: 9634815557 | N16: 9634815557 | O16: info@anshenterprise.co.in | P16: NA | Q16: CJSPD0387A | S16: 09CJSPD0387A2Z8 | V16: YES BANK LIMITED | X16: Properitoryship | Y16: Active | Z16: 45680 | AA16: 45679 | AD16: New Repossession project | AE16: 309009 | AF16: ANSH ENTERPRISES | AG16: 111 | AH16: 152 | AI16: 133 | AJ16: 396 | AK16: 2 | AL16: Allocaton given by Collection & Repossession | AM16: Eligible for audit | AN16: KGAC | AO16: NA | AP16: Shop No 5 , 1 St Floor Block 25 , Clothe Market Sanjay Palace Agra 283102 | AQ16: Audited | AR16: NA | AT16: Rakesh Chahat | AU16: Chandan Sharma | AV16: 7753851136 | AW16: 46128 | AX16: Kumar Gaurav Agarwal & company | AY16: Agra | AZ16: Uttar Pradesh | BA16: RSE6763776, GKE6543092 | BB16: Ram Shankar, Govind Kumar | BC16: Rohit Nijhawan | BD16: Ansh Enterprises | BE16: Ansh Enterprises - Agra - Uttar Pradesh | BF16: Ansh Enterprises_Collection Agency_Agra_Uttar Pradesh | BG16: Ansh Enterprises_Repo Agency_Agra_Uttar Pradesh
A17: 67 | B17: NA | C17: 365999 | D17: North | E17: Rajasthan | F17: Jaipur | G17: Collection & Repossession Agency | H17: Bank Bridge Solution | I17: Meena Devi | J17: Meena Devi | K17: Floor No. Part - B, Basement Floor, Plot No - 1179, Sakal Sumangal, Rani Sati Nagar, Nirman Nagar, Jaipur - 302019 | L17: 9828067001 | M17: 9828067001 | N17: 9828067001 | O17: Bankbridgesolution@gmail.com | P17: NA | Q17: FWFPD6079G | S17: 08FWFPD6079G1ZA | X17: Properitoryship | Y17: Active | Z17: 45965 | AA17: 45965 | AD17: Supplementary done on 4th Nov 25 | AE17: 365999 | AF17: BANK BRIDGE SOLUTION | AG17: 330 | AH17: 369 | AI17: 612 | AJ17: 1311 | AL17: Allocaton given by Collection agency | AM17: Eligible for audit | AN17: KGAC | AO17: NA | AP17: Floor No. Part - B, Basement Floor, Plot No - 1179, Sakal Sumangal, Rani Sati Nagar, Nirman Nagar, Jaipur - 302019 | AQ17: Audited | AR17: NA | AT17: Anil Swami / 7976225567 | AU17: Akash Sharma | AV17: 7688959606 | AW17: 46128 | AX17: Kumar Gaurav Agarwal & company | AY17: Jaipur | AZ17: Rajasthan | BA17: PSE6778569 | BB17: Pravesh Sharma | BC17: Na | BD17: Bank Bridge Solution | BE17: Bank Bridge Solution - Jaipur - Rajasthan | BF17: Bank Bridge Solution_Collection Agency_Jaipur_Rajasthan
A18: 8 | B18: NA | C18: 313004 | D18: East | E18: Chhattisgarh | F18: Raipur | G18: Collection & Repossession Agency | H18: Anurag Agency | I18: Anurag Rathi | J18: Anurag Rathi | K18: 3Rd Floor,Hanumanta Complex,Near Mansu Realty Ring Road No. 1 Agoraha Colony Raipura Raipur (492013) | L18: 9893023143 | M18: 9893023143 | N18: 9893023143 | O18: ANURAGRATHI1010@GMAIL.COM ; aa.y@anuragagency.com | P18: NA | Q18: AIJPR0004N | S18: 22AIJPR0004N2ZE | V18: YES BANK LIMITED | X18: Properitoryship | Y18: Active | Z18: 45621 | AA18: 45618 | AE18: 313004 | AF18: Anurag Agency | AG18: 635 | AH18: 615 | AI18: 608 | AJ18: 1858 | AL18: Allocaton given by Collection agency | AM18: Eligible for audit | AN18: KGAC | AO18: - | AP18: 3Rd Floor,Hanumanta Complex,Near Mansu Realty Ring Road No. 1 Agoraha Colony Raipura Raipur (492013) | AQ18: Audited | AR18: Audited for collection and Repossessoin, as agency have repo of assest in the audit quarter | AT18: Namarta Sharma / 8770534356 | AU18: Parteek Yadav | AV18: 7460008081 | AW18: 46125 | AX18: Kumar Gaurav Agarwal & company | AY18: Raipur | AZ18: Chhattisgarh | BA18: VUE6755300, RQE6781542, ASE6778431, SME6345002, MKE6775854, ADE6782782 | BB18: Vikram Upadhyay, Rizwan Quraishi, Avtar Singh, Sudarshan Maddu, Manoj Kumar, Anindh Dubey | BC18: Saurabh Chaturvedi, Biswarup Ghosh, Md Shabbir Alam, -, Saurabh Chaturvedi , Bikram Chakraborty | BD18: Anurag Agency | BE18: Anurag Agency - Raipur - Chhattisgarh | BF18: Anurag Agency_Collection Agency_Raipur_Chhattisgarh | BG18: Anurag Agency_Repo Agency_Raipur_Chhattisgarh
A19: 157 | B19: Z16312 | C19: 54034 | D19: North | E19: Rajasthan | F19: Jaipur | G19: Collection/Pickup/Repo Agency | H19: Choudhary Brothers Group - Jaipur | I19: Ashok Choudhary | J19: Ashok Choudhary | K19: Head Office Address : C 70 Kashyap Path, Janpath, Shyam Nagar Jaipur 302006 | L19: 9829295353,01414919039 | M19: 9829295353,01414919039,9610449872,9887603519,6375273571,8696397777,9529123413,9001811855,9024720814,9829221122 | N19: 9929295353 | O19: cbgroupjaipur01@gmail.com | P19: cbgalwar2018@gmail.com; cbgroup.alwar@gmail.com | Q19: AAIFC4465F | R19: ANPPC7352RSD001 | S19: 08AAIFC4465F1ZF | V19: HDFC BANK LTD | X19: Partnership | Y19: Active | Z19: 42877 | AA19: 42876 | AE19: 54034 | AF19: Choudhary Brothers Group | AG19: 781 | AH19: 692 | AI19: 685 | AJ19: 2158 | AL19: Allocaton given by Collection agency | AM19: Eligible for audit | AN19: KGAC | AO19: Ashutosh Gupta | AP19: Head Office Address : C 70 Kashyap Path, Janpath, Shyam Nagar Jaipur 302006 | AQ19: Audited | AR19: NA | AT19: Pushpendra Choudhary / 9829221122 | AU19: Akash Sharma | AV19: 7688959606 | AW19: 46132 | AX19: Kumar Gaurav Agarwal & company | AY19: Jaipur | AZ19: Rajasthan | BA19: SCE6758746, SKE6777255, RSE6771124, PSE6777607, T23418, SME5900019, KDE6778345, RSE6782005 | BB19: Sunil Choudhary, Sandeep Kumar, Ranjan Solanki, Pramod Sankhala, Nilesh Pednekar, Siddharth Maharishi, Kailash Devanda, Rajveer Singh | BC19: Ashutosh Gupta, Sanjeev Kumar, Sameer Dhar, Pawan Rana | BD19: Choudhary Brothers Group - Jaipur | BE19: Choudhary Brothers Group - Jaipur - Rajasthan | BF19: Choudhary Brothers Group - Jaipur_Collection Agency_Rajasthan
A20: 19 | B20: Z24482 | C20: 45704 | D20: North | E20: Delhi | F20: Delhi | G20: Collection & Repossession Agency | H20: Shree Balaji | I20: Jitender Dhaiya | J20: Jitender Dhaiya | K20: C - 2/395, 3Rd Floor Back Side, Janakpuri, Delhi 110058 | L20: 9999999276 | M20: 9899177177 | N20: 9999999276 | O20: info@shreebalaji276.in | P20: shreebalaji276@gmail.com | Q20: AKWPD7176N | S20: 07AKWPD7176N1Z9 | V20: YES BANK LIMITED | X20: Properitoryship | Y20: Active | Z20: 44183 | AA20: 44183 | AD20: Add change req recd in May22 | AE20: 45704 | AF20: Shree Balaji | AG20: 531 | AH20: 624 | AI20: 352 | AJ20: 1507 | AK20: 7 | AL20: Allocaton given by Collection & Repossession | AM20: Eligible for audit | AN20: KGAC | AO20: Amit Sharma | AP20: NA | AQ20: Not Audited | AR20: Audit Failed due to non cooperation. | AS20: NA | AT20: NA | AU20: NA | AV20: NA | AW20: NA | AX20: NA | AY20: Delhi | AZ20: Delhi | BA20: ASE6770928, SKE6779366, RSE6776115, SKE5835012, MKE5878004, SSE6776468, VGE6773224, RAE6783127, SPE6776273, NKE6775741, KKE6777919 | BB20: Aanchal Singh, Sumit Kumar, Rahul Sharma, Sushim Kumar, Manish Kumar, Subhash Sharma, Vishal Gupta, Rittin Arya, Sushant Parashar, Nitin Kumar, Kamal Kumar | BC20: Sanjeev Kumar, Amit Sharma | BD20: Shree Balaji | BE20: NA | BF20: NA | BG20: NA
A21: 48 | B21: NA | C21: 190972 | D21: North | E21: Punjab | F21: Chandigarh | G21: Collection & Repossession Agency | H21: Citi Enterprises | I21: Dinesh Midha | J21: Dinesh Midha | K21: Sco-87, 1St Floor, , Sector-40C, , Chandigarh -160036 | L21: 9815009116 | M21: 9815009116 | N21: 9815009116 | O21: Dinesh.midha@citibesteam.com | P21: NA | Q21: ACBPM4580E | S21: 04ACBPM4580E1ZX | V21: YES BANK LIMITED | X21: Properitoryship | Y21: Active | Z21: 45538 | AA21: 45537 | AD21: Supplementary agreement done in Sept'24,Supplementary agreement done in March'25 | AE21: 190972 | AF21: CITI ENTERPRISES | AG21: 1339 | AH21: 1073 | AI21: 1206 | AJ21: 3618 | AL21: Allocaton given by Collection agency | AM21: Eligible for audit | AN21: KGAC | AO21: NA | AP21: Sco-87, 1St Floor, , Sector-40C, , Chandigarh -160036 | AQ21: Audited | AR21: NA | AT21: Radhika | AU21: Rahul Verma | AV21: 9354183359 | AW21: 46132 | AX21: Kumar Gaurav Agarwal & company | AY21: Chandigarh | AZ21: Punjab | BA21: SSE6775469, VKE6782576, SRE6782838, SSE6748795 | BB21: Sukhwinder Singh, Vikash Kumar, Sidharth RaSukhwant Singh | BC21: Na | BD21: Citi Enterprises | BE21: Citi Enterprises - Chandigarh - Punjab | BF21: Citi Enterprises_Collection Agency_Chandigarh_Punjab
A22: 147 | B22: NA | C22: 165960 | D22: East | E22: West Bengal | F22: Kolkata | G22: Collection Agency | H22: Credit Solution | I22: Prasanta Saha | J22: Prasanta Saha | K22: 20/1, Plot, 100 Sahapur Colony, New Alipore, Kolkata- 700053 | L22: 9836363123 , 7449756305 | M22: 9836363123 , 7449756305 | N22: 9836363123 , 7449756305 | O22: CREDITSOLUTIONKOLKATA@GMAIL.COM ; debtreco@cesolution.co.in | P22: NA | Q22: AXAPS5363D | S22: 19AXAPS5363D2ZC | X22: Properitoryship | Y22: Active | Z22: 45559 | AA22: 45559 | AD22: Supplementary agreement done in Sept'24 // Addition of Bkt 3&4 for PL,BL | AE22: 165960 | AF22: Credit Solution | AG22: 235 | AH22: 256 | AI22: 395 | AJ22: 886 | AL22: Allocaton given by Collection agency | AM22: Eligible for audit | AN22: KGAC | AO22: Ashutosh Gupta | AP22: 20/1, Plot, 100 Sahapur Colony, New Alipore, Kolkata- 700053 | AQ22: Audited | AR22: NA | AT22: Manish Kunar Barick | AU22: Vikky Kumar | AV22: 9354241930 | AW22: 46121 | AX22: Kumar Gaurav Agarwal & company | AY22: Kolkata | AZ22: West Bengal | BA22: KSE6767729, SDE6781658 | BB22: Krishnendu Sarder, Sujoy Das | BC22: Ashutosh Gupta | BD22: Credit Solution | BE22: Credit Solution - Kolkata - West Bengal | BF22: Credit Solution_Collection Agency_Kolkata_West Bengal
A23: 64 | B23: Z27683 | C23: 51542 | D23: North | E23: Rajasthan | F23: Bikaner | G23: Collection & Repossession Agency | H23: D S Associates | I23: Dhnshree Swami | J23: Om Prakash Swami | K23: Shop No. 7, Near Vishvkarma Gate, Near Shree Ram Mandir, Bikaner - 334001 | L23: 9983965443 | M23: 9983965443 | N23: 9214419806 | O23: dsassociates2016@gmail.com | P23: NA | Q23: GPMPS2855J | R23: NA | S23: 08GPMPS2855J1Z2 | X23: Properitoryship | Y23: Active | Z23: 44890 | AA23: 44890 | AE23: 51542 | AF23: D S Associates | AG23: 289 | AH23: 286 | AI23: 297 | AJ23: 872 | AL23: Allocaton given by Collection agency | AM23: Eligible for audit | AN23: KGAC | AO23: - | AP23: Shop No. 7, Near Vishvkarma Gate, Near Shree Ram Mandir, Bikaner - 334001 | AQ23: Audited | AR23: NA | AT23: Mukul Ramawat / 8209758199 | AU23: Akash Sharma | AV23: 7688959606 | AW23: 46119 | AX23: Kumar Gaurav Agarwal & company | AY23: Bikaner | AZ23: Rajasthan | BA23: MCE6212008, SSE6776468, DKE6771022, ATE6773431, LCE6760405, PKE6777451 | BB23: Mahendra Chouhan, Subhash Sharma, Dinesh Kumar, Ashish Tiwari, Lal Chand Chimpa, Pawan Kumar | BC23: Ashutosh Gupta, Kalpesh Raval, Sameer Dhar, Sanjeev Kumar, Pawan RaVivek Joshi, - | BD23: D S Associates | BE23: D S Associates - Bikaner - Rajasthan | BF23: D S Associates_Collection Agency_Bikaner_Rajasthan
A24: 34 | B24: NA | C24: 310986 | D24: East | E24: Jharkhand | F24: Ranchi | G24: Collection & Repossession Agency | H24: Definate Solutions | I24: Nisha | J24: Nisha | K24: Dubey Colony,Tetri Toli,Nakmkum, Ranchi,834010,Jharkhand, Dubey Colony,Tetri Toli,Nakmkum, Ranchi,834010,Jharkhand, Dubey Colony,Tetri Toli,Nakmkum, Ranchi,834010,Jhar | L24: 8083983999 | M24: 8083983999 | N24: 8083983999 | O24: definatesolutions.rnc@gmail.com ; dsy.rnc@gmail.com | P24: NA | Q24: AUSPD7846D | S24: 20AUSPD7846D1ZP | V24: PUNJAB NATIONAL BANK | X24: Properitoryship | Y24: Active | Z24: 45668 | AA24: 45665 | AD24: New Repossession project | AE24: 310986 | AF24: DEFINATE SOLUTIONS | AG24: 99 | AH24: 99 | AI24: 102 | AJ24: 300 | AL24: Allocaton given by Collection agency | AM24: Eligible for audit | AN24: KGAC | AO24: Subhasis Banerjee | AP24: Dubey Colony,Tetri Toli,Nakmkum, Ranchi,834010,Jharkhand, Dubey Colony,Tetri Toli,Nakmkum, Ranchi,834010,Jharkhand, Dubey Colony,Tetri Toli,Nakmkum, Ranchi,834010,Jhar | AQ24: Audited | AR24: NA | AT24: Nisha | AU24: Vikky Kumar | AV24: 9354241930 | AW24: 46130 | AX24: Kumar Gaurav Agarwal & company | AY24: Ranchi | AZ24: Jharkhand | BA24: RME6754808 | BB24: Rabi Mishra | BC24: Subhasis Banerjee | BD24: Definate Solutions | BE24: Definate Solutions - Ranchi - Jharkhand | BF24: Definate Solutions_Collection Agency_Ranchi_Jharkhand
A25: 82 | B25: NA | C25: 347001 | D25: North | E25: Uttar Pradesh | F25: Ayodhya | G25: Collection & Repossession Agency | H25: Awadhesh Kumar Dubey | I25: Awadhesh Kumar Dubey | J25: Awadhesh Kumar Dubey | K25: Chandpur Harvansh Purbi, Chandpur Harbanshpur Po Dabha Semar Disct.Ayodhya Up 224133 | L25: 9450916368 | M25: 9450916368 | N25: 9450916368 | O25: dubey_awadhesh@rediffmail.com | P25: NA | Q25: AHAPD1739N | S25: 09AHAPD1739N1Z9 | X25: Proprietorship | Y25: Active | Z25: 45840 | AA25: 45838 | AE25: 347001 | AF25: AWADHESH KUMAR DUBEY | AG25: NA | AH25: NA | AI25: NA | AJ25: NA | AK25: 1 | AL25: Allocaton given by Repo agency | AM25: Eligible for audit | AN25: KGAC | AO25: #N/A | AP25: Chandpur Harvansh Purbi, Chandpur Harbanshpur Po Dabha Semar Disct.Ayodhya Up 224133 | AQ25: Audited | AR25: NA | AT25: Vijay Dube | AU25: Chandan Sharma | AV25: 7753851136 | AW25: 46119 | AX25: Kumar Gaurav Agarwal & company | AY25: Ayodhya | AZ25: Uttar Pradesh | BA25: NA | BB25: Shyam Parkash, Vivek Kumar Shukla | BC25: Abhinav Lal | BD25: Awadhesh Kumar Dubey | BE25: Awadhesh Kumar Dubey - Ayodhya - Uttar Pradesh | BF25: Awadhesh Kumar Dubey_Collection Agency_Ayodhya_Uttar Pradesh | BG25: Awadhesh Kumar Dubey_Repo Agency_Ayodhya_Uttar Pradesh
A26: 12 | B26: Z25246 | C26: 26364 | D26: North | E26: Delhi | F26: Delhi | G26: Collection & Repossession Agency | H26: Earth Services | I26: Subhash Chand | J26: Subhash Chand | K26: Wz-12 Kh No2882/738 1St , Floor Kailash Park, Nd-15 | L26: 01149148479 | M26: 01149148479,7303542742,9210171819,9911632358,9717706206,9871666049,9560827618,9953547789 | N26: 9711567008 | O26: earth4@earthservices.in | P26: earthservices17@gmail.com | Q26: AEGPC6483B | R26: 07AEGPC6483BSD001 | S26: 07AEGPC6483B2ZR | V26: YES BANK LIMITED | X26: Proprietorship | Y26: Active | Z26: 44391 | AA26: 44392 | AD26: Repo activity added in May22 | AE26: 26364 | AF26: Earth Services | AG26: 2128 | AH26: 2131 | AI26: 1953 | AJ26: 6212 | AL26: Allocaton given by Collection agency | AM26: Eligible for audit | AN26: KGAC | AO26: Ashutosh Gupta | AP26: Wz-12 Kh No2882/738 1St , Floor Kailash Park, Nd-15 | AQ26: Audited | AR26: NA | AT26: Mithlesh Kumar | AU26: Pawan Kumar | AV26: 9582917652 | AW26: 46134 | AX26: Kumar Gaurav Agarwal & company | AY26: Delhi | AZ26: Delhi | BA26: NKE6775741, AKE6778416, SRE6782838, RSE6776475, VKE6782576, SSE6775469, MME6755196, VGE6773224, SSE6748795 | BB26: Nitin Kumar, Amit Kumar, Sidharth RaRupesh Singh, Vikash Kumar, Sukhwinder Singh, Mritunjay MunVishal Gupta, Sukhwant Singh | BC26: Ashutosh Gupta | BD26: Earth Services | BE26: Earth Services - Delhi | BF26: Earth Services_Collection Agency_Delhi
A27: 26 | B27: NA | C27: 315002 | D27: North | E27: Haryana | F27: Hisar | G27: Collection & Repossession Agency | H27: Port Care Consultancy | I27: Neeraj Kumar | J27: Neeraj Kumar | K27: Sco No.-153, , 3Rd Floor, Red Square Market,Hisar,Haryana-125001 | L27: 9355511114 | M27: 9355511114 | N27: 9355511114 | O27: khyalia.vinod@gmail.com | P27: NA | Q27: AWNPK8831A | S27: 06AWNPK8831A2ZJ | V27: YES BANK LIMITED | X27: Properitoryship | Y27: Active | Z27: 45698 | AA27: 45695 | AE27: 315002 | AF27: PORT CARE CONSULTANCY | AG27: 3 | AH27: 0 | AI27: 0 | AJ27: 3 | AL27: Allocaton given by Collection agency | AM27: Eligible for audit | AN27: KGAC | AO27: Sanjeev Kumar | AP27: NA | AQ27: Not Audited | AR27: Low allocation in January and no allocation afterwards | AS27: NA | AT27: NA | AU27: NA | AV27: NA | AW27: NA | AX27: NA | AY27: Hisar | AZ27: Haryana | BA27: ANE5784049 | BB27: Anil Kumar Nandal | BC27: Sanjeev Kumar | BD27: Port Care Consultancy | BE27: NA | BF27: NA | BG27: NA
A28: 40 | B28: NA | C28: 347002 | D28: East | E28: Odisha | F28: Cuttack | G28: Collection & Repossession Agency | H28: B K Associates | I28: Basanta Kumar Swain,Sasmita Swain,Bibhu Sundar Jena | J28: Basanta Kumar Swain,Sasmita Swain,Bibhu Sundar Jena | K28: At Rajesndranagar,Temple Side Lane Near Mangala Mandir,Madhupatna,Cuttack,Odisha,753010 | L28: 9937173611 | M28: 9937173611 | N28: 9937173611 | O28: bkassociates3611@gmail.com, bkcollection2018@gmail.com | P28: NA | Q28: AAMFB1648R | S28: 21AAMFB1648R2Z3 | X28: Patnership | Y28: Active | Z28: 45840 | AA28: 45836 | AE28: 347002 | AF28: B K Associates | AG28: NA | AH28: NA | AI28: NA | AJ28: NA | AK28: 2 | AL28: Allocaton given by Repo agency | AM28: Eligible for audit | AN28: KGAC | AO28: #N/A | AP28: At Rajesndranagar,Temple Side Lane Near Mangala Mandir,Madhupatna,Cuttack,Odisha,753010 | AQ28: Audited | AR28: NA | AT28: Bibhusundar Jena | AU28: Vikky Kumar | AV28: 9354241930 | AW28: 46125 | AX28: Kumar Gaurav Agarwal & company | AY28: Cuttack | AZ28: Odisha | BA28: NA | BB28: Santosh Sharma, Suryanarayan Nayak | BC28: Biswarup Ghosh | BD28: B K Associates | BE28: B K Associates - Cuttack - Odisha | BF28: B K Associates_Collection Agency_Cuttack_Odisha | BG28: B K Associates_Repo Agency_Cuttack_Odisha
A29: 28 | B29: Z22853 | C29: 26490 | D29: North | E29: Haryana | F29: Panipat | G29: Collection & Repossession Agency | H29: G.D.M. Management Services Pvt Ltd - Panipat | I29: Rajesh Kumar/Naresh Kumar | J29: Rajesh Kumar/Naresh Kumar | K29: Prince Guest House, Room No.2-B,Near Axis Bank, G T Road, Panipat-132103 | L29: 011,40919715,9354909242,9315045873,7678326675,7827410614,8882896148,8595955476,8882818651,9315131930,8178036157,8851243856,7827429289,76783918128076508276,8882899467,8595956472,7678321553,7678308077,7678396018,8920038807,8368999916,8810592365,9315748638,7678324044,8882403961,8595954459,8076608859,8076534454,8920963073,8920038738 | M29: 011,40919715,9354909242,9315045873,7678326675,7827410614,8882896148,8595955476,8882818651,9315131930,8178036157,8851243856,7827429289,76783918128076508276,8882899467,8595956472,7678321553,7678308077,7678396018,8920038807,8368999916,8810592365,9315748638,7678324044,8882403961,8595954459,8076608859,8076534454,8920963073,8920038738,7292030107,9999098611,9891999980,7017538011,9810205430,9958686165,9266697828,9817875090,9671775656,9992202126,9050604254,9667169442,8851473697,7065315053,7065954659,7065963209,7065640923,8750131886,8750773816,8750273692,8750967594,8750172809,8750973013,8750537906,8750957629,8750900871,8588893713,8588842445,8588847253,8750177170,8750094542,7065502925,7065494502,7065936794,7065784203,7065675119,7065680813,7065334058,7065610331,8588845250,8588875903,8588891770,8588858236,8588876523,8588846304,7669627101,7669794829,7669591561,7669898316,7669794921,7669201607,7669818304,7669836846,7669803373,7669201593,7669614273,7669764163,7669794879,7669646432,7669516059,7669595815,7669616520,7669988972,7669886976,7669614267,7669573471,7669196176,7669827710,7669675347,7669614262,8929665273,8929110705,8929988714,8929447921,8929727441,8929925517,8929843241 | N29: 9896400088,9354909242 | O29: goodwill_naresh@outlook.com ; gdmdebtmanagement@outlook.com | P29: NA | Q29: AAHCG6535C | S29: 06AAHCG6535C1ZT | V29: ICICI BANK LIMITED | X29: PVT Ltd | Y29: Active | Z29: 43724 | AA29: 43704 | AD29: Addition address req received in Sept, Supplementary agreement done on 18th Sep'23 | AE29: 26490 | AF29: G.D.M. Management Services PVT LTD | AG29: 2186 | AH29: 2355 | AI29: 2014 | AJ29: 6555 | AK29: 2 | AL29: Allocaton given by Collection & Repossession | AM29: Eligible for audit | AN29: KGAC | AO29: Ashutosh Gupta | AP29: NA | AQ29: Not Audited | AR29: Visited the agency but audit not done due to agency is working for Yes Bank from their another branch, Address : A-1 1st floor , shastri nagar , new delhi -110034 | AS29: NA | AT29: NA | AU29: NA | AV29: NA | AW29: NA | AX29: NA | AY29: Panipat | AZ29: Haryana | BA29: NRE6746973, SRE6739824, RSE6763776, SRE6782838, RCE6775867, BRE6281007, ANE5784049, ERE6776646, PKE6779360, VME6772902, KSE6769063, MRE6786842 | BB29: Navdeep Rastogi, Syed Raza, Ram Shankar, Sidharth RaRitesh Chourasia, Bhavna Rajput, Anil Kumar Nandal, Ekta Rani, Pawan Kumar, Vaibhav Mishra, Kushpal Singh, Mohit Rathore | BC29: Sameer Dhar, Kunal Malhotra, Sanjeev Kumar, Ashutosh Gupta, Upanshu Bajaj | BD29: G.D.M. Management Services Pvt Ltd - Panipat | BE29: NA | BF29: NA | BG29: NA
A30: 85 | B30: Z26519 | C30: 12290 | D30: North | E30: Uttar Pradesh | F30: Kanpur | G30: Collection & Repossession Agency | H30: Baiswara Associates | I30: Mr Sanjeev Singh | J30: Mr Sanjeev Singh | K30: H-775 Mig World Bank Petrol Line Barra Kanpur -208027 | L30: 9839214520; 7007800000 | M30: 9839214520,9682214520 | O30: baiswaraassociates_2009@rediffmail.com; baiswara@baiswaragroup.com | P30: baiswaraassociates@gmail.com | Q30: AXDPS6196H | R30: 09AXDPS6196H1ZU | S30: 09AXDPS6196H1ZU | V30: CENTRAL BANK OF INDIA | X30: Properitoryship | Y30: Active | Z30: 44609 | AA30: 44603 | AD30: Coolection activity added in Dec22 | AE30: 12290 | AF30: Baiswara Associates | AG30: 41 | AH30: 36 | AI30: 35 | AJ30: 112 | AL30: Allocaton given by Collection agency | AM30: Eligible for audit | AN30: KGAC | AO30: Abhinav Lal | AP30: H-775 Mig World Bank Petrol Line Barra Kanpur -208027 | AQ30: Audited | AR30: Audited for collection and Repossessoin, as agency have repo of assest in the audit quarter | AT30: Himanshu Awashti | AU30: Chandan Sharma | AV30: 7753851136 | AW30: 46123 | AX30: Kumar Gaurav Agarwal & company | AY30: Kanpur | AZ30: Uttar Pradesh | BA30: VGE6786972, NSE6633007 | BB30: Vivek Gupta, Nitin Kumar Singh | BC30: Abhinav Lal | BD30: Baiswara Associates | BE30: Baiswara Associates - Kanpur - Uttar Pradesh | BF30: Baiswara Associates_Collection Agency_Kanpur_Uttar Pradesh | BG30: Baiswara Associates_Repo Agency_Kanpur_Uttar Pradesh
A31: 160 | B31: Z16682 | C31: 25732 | D31: East | E31: West Bengal | F31: Kolkata | G31: Collection/Pickup/Repo Agency | H31: Esolve Solutions Pvt Ltd | I31: Rajesh Gupta | J31: Rajesh Gupta | K31: 1/1 Meredith St, 2Nd Floor, Kolkata - 700072 | L31: 9830006161 | M31: 9830006161,9830553705,7003487878,7003048731, 9674081075 , 6291926035 | N31: 9830006161 | O31: collections.yesbank@e-solvesolutions.com | P31: NA | Q31: AABCE8294Q | S31: 19AABCE8294Q1ZP | V31: YES BANK LIMITED | X31: PVT Ltd | Y31: Active | Z31: 44659 | AA31: 44659 | AD31: Repo activity added | AE31: 25732 | AF31: Esolve solutions PVT LTD | AG31: 1204 | AH31: 1174 | AI31: 1138 | AJ31: 3516 | AL31: Allocaton given by Collection agency | AM31: Eligible for audit | AN31: KGAC | AO31: Ashutosh Gupta | AP31: 1/1 Meredith St, 2Nd Floor, Kolkata - 700072 | AQ31: Audited | AR31: NA | AT31: Somnath Dey | AU31: Pradeep | AV31: 8287823681 | AW31: 46132 | AX31: Kumar Gaurav Agarwal & company | AY31: Kolkata | AZ31: West Bengal | BA31: SDE6778568, MSE6778149, AME6761288, SME6781177, TSE6288042, DSE6782069 | BB31: Suman Das, Md Sarfarazuddin, Md Azharuddin, Sudip ManTarkeshwar Singh, Deepak Singh | BC31: Ashutosh Gupta, Biswarup Ghosh | BD31: Esolve Solutions Pvt Ltd | BE31: Esolve Solutions Pvt Ltd - Kolkata - West Bengal | BF31: Esolve Solutions Pvt Ltd_Collection Agency_Kolkata_West Bengal
A32: 97 | B32: Z28071 | C32: 54117 | D32: North | E32: Uttarakhand | F32: Dehradun | G32: Collection & Repossession Agency | H32: Evergreen Solution | I32: Anand Ballabh Pandey | J32: Anand Ballabh Pandey | K32: B-228 Nehru Colony Dehradun-248001 | L32: 7895100604 | M32: 7895100604 | N32: 9358950033 | O32: evergreen.solution@rediffmail.com; anand.pandey@evergreensolution.org.in | P32: evergreensolutionybl@gmail.com | Q32: BAKPP7912B | S32: 05BAKPP7912B1ZU | V32: YES BANK LIMITED | X32: Properitoryship | Y32: Active | Z32: 44971 | AA32: 44965 | AE32: 54117 | AF32: Evergreen Solution | AG32: 216 | AH32: 207 | AI32: 210 | AJ32: 633 | AL32: Allocaton given by Collection agency | AM32: Eligible for audit | AN32: KGAC | AO32: Abhinav Lal | AP32: B-228 Nehru Colony Dehradun-248001 | AQ32: Audited | AR32: NA | AT32: Aknsha Kumari / 9548597076 | AU32: Akshay Notiyal | AV32: 9149204613 | AW32: 46133 | AX32: Kumar Gaurav Agarwal & company | AY32: Dehradun | AZ32: Uttarakhand | BA32: JSE6775853, HKE6745350, RAE6783127, STE5844128 | BB32: Jeetmani Silswal, Hayat Kathayat, Rittin Arya, Sandeep Tyagi | BC32: Ashutosh Gupta, Sanjeev Kumar, Abhinav Lal, Sameer Dhar | BD32: Evergreen Solution | BE32: Evergreen Solution - Dehradun - Uttarakhand | BF32: Evergreen Solution_Collection Agency_Dehradun_Uttarakhand
A33: 45 | B33: Z15099 | C33: 26517 | D33: North | E33: Punjab | F33: Amritsar | G33: Collection & Repossession Agency | H33: Excel Agencies - Amritsar | I33: Pawandeep Singh | J33: Pawandeep Singh / Pardeep Kumar/Prince Aneja/Sukhdev Chabbra/Tarandeep Singh | K33: Shop No 20, Ssss Complex, Batala Road, Randhwa, Amritsar - 143001 | L33: 0172-4605355,4605245,0181-4608882,0161-4648632 | M33: 0172-4605355,4605245,0181-4608882,0161-4648632,9914141900,6280449688,9872074864,9646689689,7087344321,7986600380,6239609030,9779282827,7888714695,0172-5090526 | N33: 9914141900,9988210298,9317575751 | O33: ;excelbat@yahoo.co.in; excelyes9@gmail.com;exceljal.yesbank@gmail.com;excel.yesbankchd@gmail.com ; excel.yesbank56@gmail.com; excel2019@excelagencies.com | P33: NA | Q33: ANDPS3022N | S33: 03ANDPS3022N1Z2 | V33: YES BANK LIMITED | X33: Properitoryship | Y33: Active | Z33: 43579 | AA33: 43579 | AD33: Address addition details received on 16th Aug,Mohal add change req reced in Oct21. | AE33: 26517 | AF33: Excel Agencies | AG33: 1051 | AH33: 1002 | AI33: 925 | AJ33: 2978 | AL33: Allocaton given by Collection agency | AM33: Eligible for audit | AN33: KGAC | AO33: Ashutosh Gupta | AP33: Shop No 20, Ssss Complex, Batala Road, Randhwa, Amritsar - 143001 | AQ33: Audited | AR33: NA | AT33: Pooja Gupta/8837665745 | AU33: Pawan Kumar | AV33: 9582917652 | AW33: 46125 | AX33: Kumar Gaurav Agarwal & company | AY33: Amritsar | AZ33: Punjab | BA33: PSE6777607, JBE6662016, SGE6771981, SKE6776527, JSE6784665, KDE6778345, SCE6758746 | BB33: Pramod Sankhala, Jaspreet Bhathal, Sahil Gorsi, Sunil Kumar , Jagmohan Singh, Kailash Devanda, Sunil Choudhary | BC33: Ashutosh Gupta | BD33: Excel Agencies - Amritsar | BE33: Excel Agencies - Amritsar - Punjab | BF33: Excel Agencies - Amritsar_Collection Agency_Punjab
A34: 33 | B34: NA | C34: 67899 | D34: East | E34: Jharkhand | F34: Jamshedpur | G34: Collection & Repossession Agency | H34: Sai Enterprises | I34: Bharat Kumar | J34: Bharat Kumar | K34: H No - 06, Vidyapati Nagar, Main Road Baridih, Jamshedpur - 831017 // | L34: 9110166707 | M34: 9110166707 ; 8291720550 | N34: 9110166707 | O34: saienterprisesyb@saient.co.in | P34: NA | Q34: CRXPK1279H | R34: 0 | S34: #N/A | T34: 0 | U34: 0 | V34: YES BANK LIMITED | W34: 0 | X34: Properitoryship | Y34: Active | Z34: 45133 | AA34: 45131 | AB34: 0 | AC34: 0 | AD34: 0 | AE34: 67899 | AF34: Sai Enterprises | AG34: 449 | AH34: 443 | AI34: 439 | AJ34: 1331 | AL34: Allocaton given by Collection agency | AM34: Eligible for audit | AN34: KGAC | AO34: Ashutosh Gupta | AP34: NA | AQ34: Not Audited | AR34: Audited on another address : B/111 subhash road, baagun nagar baridih near AIWC high school po baridih east singhbhum jamshedpur 831017. | AS34: NA | AT34: NA | AU34: NA | AV34: NA | AW34: NA | AX34: NA | AY34: Jamshedpur | AZ34: Jharkhand | BA34: PYE6778749, PKE6762328, STE6769262, CRE6787981 | BB34: Pankaj Yadav, Prabhakar Kumar, Santosh Thakur, Chandan Rishabh | BC34: Ashutosh Gupta, Md Shabbir Alam | BD34: Sai Enterprises | BE34: NA | BF34: NA | BG34: NA
A35: 56 | B35: Z15099 | C35: 26517 | D35: North | E35: Punjab | F35: Ludhiana | G35: Collection & Repossession Agency | H35: Excel Agencies - Ludhiana | I35: Pawandeep Singh | J35: Pawandeep Singh / Pardeep Kumar/Prince Aneja/Sukhdev Chabbra/Tarandeep Singh | K35: Office No. 2, 2Nd Floor, Novelty Plaza, Opp. Park Plaza, Bhai Wala Chowk, Ludhiana - 141001 | L35: 0172-4605355,4605245,0181-4608882,0161-4648632 | M35: 0172-4605355,4605245,0181-4608882,0161-4648632,9914141900,6280449688,9872074864,9646689689,7087344321,7986600380,6239609030,9779282827,7888714695,0172-5090526 | N35: 9914141900,9988210298,9317575751 | O35: ;excelbat@yahoo.co.in; excelyes9@gmail.com;exceljal.yesbank@gmail.com;excel.yesbankchd@gmail.com ; excel.yesbank56@gmail.com; excel2019@excelagencies.com | P35: NA | Q35: ANDPS3022N | S35: 03ANDPS3022N1Z2 | V35: YES BANK LIMITED | X35: Properitoryship | Y35: Active | Z35: 43579 | AA35: 43579 | AD35: Address addition details received on 16th Aug,Mohal add change req reced in Oct21. | AE35: 26517 | AF35: Excel Agencies | AG35: 1051 | AH35: 1002 | AI35: 925 | AJ35: 2978 | AL35: Allocaton given by Collection agency | AM35: Eligible for audit | AN35: KGAC | AO35: Ashutosh Gupta | AP35: Office No. 2, 2Nd Floor, Novelty Plaza, Opp. Park Plaza, Bhai Wala Chowk, Ludhiana - 141001 | AQ35: Audited | AR35: NA | AT35: Sukhdev/9317575751 | AU35: Pawan Kumar | AV35: 9582917652 | AW35: 46127 | AX35: Kumar Gaurav Agarwal & company | AY35: Ludhiana | AZ35: Punjab | BA35: PSE6777607, JBE6662016, SGE6771981, SKE6776527, JSE6784665, KDE6778345, SCE6758746 | BB35: Pramod Sankhala, Jaspreet Bhathal, Sahil Gorsi, Sunil Kumar , Jagmohan Singh, Kailash Devanda, Sunil Choudhary | BC35: Ashutosh Gupta | BD35: Excel Agencies - Ludhiana | BE35: Excel Agencies - Ludhiana - Punjab | BF35: Excel Agencies - Ludhiana_Collection Agency_Punjab
A36: 61 | B36: Z15099 | C36: 26517 | D36: North | E36: Punjab | F36: Mohali | G36: Collection & Repossession Agency | H36: Excel Agencies - Mohali | I36: Pawandeep Singh | J36: Pawandeep Singh / Pardeep Kumar/Prince Aneja/Sukhdev Chabbra/Tarandeep Singh | K36: Plot No 259,Phase Viii B,Industrial Focal Point,Sas Nagar, Mohali - 160062 | L36: 0172-4605355,4605245,0181-4608882,0161-4648632 | M36: 0172-4605355,4605245,0181-4608882,0161-4648632,9914141900,6280449688,9872074864,9646689689,7087344321,7986600380,6239609030,9779282827,7888714695,0172-5090526 | N36: 9914141900,9988210298,9317575751 | O36: ;excelbat@yahoo.co.in; excelyes9@gmail.com;exceljal.yesbank@gmail.com;excel.yesbankchd@gmail.com ; excel.yesbank56@gmail.com; excel2019@excelagencies.com | P36: NA | Q36: ANDPS3022N | S36: 03ANDPS3022N1Z2 | V36: YES BANK LIMITED | X36: Properitoryship | Y36: Active | Z36: 43579 | AA36: 43579 | AD36: Address addition details received on 16th Aug,Mohal add change req reced in Oct21. | AE36: 26517 | AF36: Excel Agencies | AG36: 1051 | AH36: 1002 | AI36: 925 | AJ36: 2978 | AL36: Allocaton given by Collection agency | AM36: Eligible for audit | AN36: KGAC | AO36: Ashutosh Gupta | AP36: Plot No 259,Phase Viii B,Industrial Focal Point,Sas Nagar, Mohali - 160062 | AQ36: Audited | AR36: NA | AT36: Dimple | AU36: Pawan Kumar | AV36: 9582917652 | AW36: 46123 | AX36: Kumar Gaurav Agarwal & company | AY36: Mohali | AZ36: Punjab | BA36: PSE6777607, JBE6662016, SGE6771981, SKE6776527, JSE6784665, KDE6778345, SCE6758746 | BB36: Pramod Sankhala, Jaspreet Bhathal, Sahil Gorsi, Sunil Kumar , Jagmohan Singh, Kailash Devanda, Sunil Choudhary | BC36: Ashutosh Gupta | BD36: Excel Agencies - Mohali | BE36: Excel Agencies - Mohali - Punjab | BF36: Excel Agencies - Mohali_Collection Agency_Punjab
A37: 183 | B37: Z16131 | C37: 25788 | D37: East | E37: West Bengal | F37: Kolkata | G37: Repossession Agency | H37: Bharat Repossession Unit | I37: Biswajit Dey | J37: Biswajit Dey | K37: 11, Bandhab Nagar, P.O + P.S – Belgharia, West Bengal, Kolkata - 700056 | L37: 9836671180 | M37: 9836671180,8981066924 | N37: 8961166923 | O37: biswajitdeyrepo@gmail.com; Brubd2000@yahoo.com | P37: NA | Q37: AKJPD5143L | R37: AKJPD5143LSD001 | S37: 19AKJPD5143L1ZY | U37: 076085800000011 | V37: YES BANK LIMITED | W37: OPENED | X37: Properitoryship | Y37: Active | Z37: 42588 | AA37: 42576 | AE37: 25788 | AF37: Bharat Repossession Unit | AG37: NA | AH37: NA | AI37: NA | AJ37: NA | AK37: 4 | AL37: Allocaton given by Repo agency | AM37: Eligible for audit | AN37: KGAC | AO37: #N/A | AP37: 11, Bandhab Nagar, P.O + P.S – Belgharia, West Bengal, Kolkata - 700056 | AQ37: Audited | AR37: NA | AT37: Sanjeev Chakraborty | AU37: Vikky Kumar | AV37: 9354241930 | AW37: 46119 | AX37: Kumar Gaurav Agarwal & company | AY37: Kolkata | AZ37: West Bengal | BA37: NA | BB37: Arindam Sarkar, Priyanka Mondal, Deepak Singh, Imran Elahi, Sachin Bharti, Sudip ManAmit Ranjan Singh, Suryakanta Jena | BC37: Subhasis Banerjee, Biswarup Ghosh | BD37: Bharat Repossession Unit | BE37: Bharat Repossession Unit - Kolkata - West Bengal | BF37: Bharat Repossession Unit_Collection Agency_Kolkata_West Bengal | BG37: Bharat Repossession Unit_Repo Agency_Kolkata_West Bengal
A38: 155 | B38: Z16778 | C38: 25428 | D38: North | E38: Rajasthan | F38: Ajmer | G38: Collection/Pickup/Repo Agency | H38: F K Associates | I38: Farid Khan | J38: Farid Khan | K38: 1St Floor Swami Complex, India Motor Circle Ajmer | L38: 0145-2427748 | M38: 0145-2427748,7725943164,9928754482,8078644514,9829070500 | N38: 9829070500,John,Bill,maker-,9772888871 | O38: fkassociate@yahoo.co.in; farid.khan.vendor@yesbank.in | P38: fkassociate788@gmail.com | Q38: AFDPK6193C | R38: ST/AJM/AJM/301/BAS/2005 | S38: 08AFDPK6193C1ZI | V38: YES BANK LIMITED | X38: Properitoryship | Y38: Active | Z38: 42147 | AA38: 42875 | AE38: 25428 | AF38: F K Associates | AG38: 432 | AH38: 409 | AI38: 393 | AJ38: 1234 | AL38: Allocaton given by Collection & Repossession | AM38: Eligible for audit | AN38: KGAC | AO38: Ashutosh Gupta | AP38: 1St Floor Swami Complex, India Motor Circle Ajmer | AQ38: Audited | AR38: Audited for Collection Only, as no activity of repossession are done for the audit quarter | AT38: Akash Kushwah / 7725943164 | AU38: Akash Sharma | AV38: 7688959606 | AW38: 46123 | AX38: Kumar Gaurav Agarwal & company | AY38: Ajmer | AZ38: Rajasthan | BA38: YME6753113, AHE6782821, PSE6777607, RSE6771124, SCE6758746, MSE6781974 | BB38: Yasin Mohammed, Akram Hussain, Pramod Sankhala, Ranjan Solanki, Sunil Choudhary, Manish Shukla | BC38: Ashutosh Gupta , Kalpesh Raval, Saurabh Saroch | BD38: F K Associates | BE38: F K Associates - Ajmer - Rajasthan | BF38: F K Associates_Collection Agency_Ajmer_Rajasthan
A39: 38 | B39: NA | C39: 348998 | D39: North | E39: Delhi | F39: Delhi | G39: Collection & Repossession Agency | H39: Aim Associates | I39: Sanjay Sethi | J39: Sanjay Sethi | K39: 3E/6 Jhandewaln Extn New Delhi 110055 | L39: 01146142871, 43702304 | M39: 01146142871, 43702304 | N39: 9811006913 | O39: ysethi@aimsanjay.com | P39: NA | Q39: ALJPS1500R | R39: 0 | S39: 07ALJPS1500R1ZP | T39: 0 | U39: 0 | V39: ICICI BANK LIMITED | W39: 0 | X39: Proprietorship | Y39: Active | Z39: 45838 | AA39: 45838 | AB39: 0 | AC39: 0 | AD39: 0 | AE39: 348998 | AF39: Aim Associates | AG39: 172 | AH39: 181 | AI39: 138 | AJ39: 491 | AL39: Allocaton given by Collection agency | AM39: Eligible for audit | AN39: KGAC | AO39: Sameer Dhar | AP39: NA | AQ39: Not Audited | AR39: Audited on another address : 45 46 , 2nd floor , west guru angad nagar , laxmi nagar -110092 | AS39: NA | AT39: NA | AU39: NA | AV39: NA | AW39: NA | AX39: NA | AY39: Delhi | AZ39: Delhi | BA39: PGE6777921, NSE6771909 | BB39: Priyanka Guptarinder Singh | BC39: Sameer Dhar, Sanjeev Kumar | BD39: Aim Associates | BE39: NA | BF39: NA | BG39: NA
A40: 111 | B40: NA | C40: 351036 | D40: East | E40: West Bengal | F40: Nadia | G40: Collection & Repossession Agency | H40: Boundless Grow Up Private Limited | I40: Mithun Halder/Suparna Jana | J40: Mithun Halder/Suparna Jana | K40: New Kalipur, Bhatjangla, Ps-Kotwali, Krishnanagar, Nadia, Pin-741102. | L40: 9609095019 / 7872433133 | M40: 9609095019 / 7872433133 | N40: 9609095019 / 7872433133 | O40: Boundlessgrowuppvtltd@gmail.com | P40: NA | Q40: AAKCB8919J | S40: 19AAKCB8919J1Z1 | X40: Partnership | Y40: Active | Z40: 45875 | AA40: 45875 | AE40: 351036 | AF40: Boundless Grow UP PRIVATE LIMITED | AG40: NA | AH40: NA | AI40: NA | AJ40: NA | AK40: 2 | AL40: Allocaton given by Repo agency | AM40: Eligible for audit | AN40: KGAC | AO40: #N/A | AP40: New Kalipur, Bhatjangla, Ps-Kotwali, Krishnanagar, Nadia, Pin-741102. | AQ40: Audited | AR40: NA | AT40: Subir Sikdar | AU40: Pradeep | AV40: 8287823681 | AW40: 46120 | AX40: Kumar Gaurav Agarwal & company | AY40: Nadia | AZ40: West Bengal | BA40: NA | BB40: Priyanka Mondal, Sourabh Parihar | BC40: Subhasis Banerjee, Biswarup Ghosh | BD40: Boundless Grow Up Private Limited | BE40: Boundless Grow Up Private Limited - Nadia - West Bengal | BF40: Boundless Grow Up Private Limited_Collection Agency_Nadia_West Bengal | BG40: Boundless Grow Up Private Limited_Repo Agency_Nadia_West Bengal
A41: 102 | B41: 83886 | C41: 83886 | D41: East | E41: West Bengal | F41: Kolkata | G41: Collection & Repossession Agency | H41: Chandan Saha | I41: Chandan Saha | J41: Chandan Saha | K41: 180/1/B, Roy Bahadur Road, Kolkata - 700034 | L41: 9748631964,9830252232 | M41: 9748631964,9830252232,8420986890,8585836534 | N41: 9748631964,9830252232 | O41: mcs@chandansaha.com | P41: NA | Q41: BMGPS0314G | S41: 19BMGPS0314G2Z4 | V41: YES BANK LIMITED | X41: Properitoryship | Y41: Active | Z41: 45188 | AA41: 45182 | AE41: 83886 | AF41: CHANDAN SAHA | AG41: 834 | AH41: 823 | AI41: 818 | AJ41: 2475 | AK41: 2 | AL41: Allocaton given by Collection & Repossession | AM41: Eligible for audit | AN41: KGAC | AO41: Ashutosh Gupta | AP41: 180/1/B, Roy Bahadur Road, Kolkata - 700034 | AQ41: Audited | AR41: NA | AT41: Tarun Kumar Kundu | AU41: Vikky Kumar | AV41: 9354241930 | AW41: 46120 | AX41: Kumar Gaurav Agarwal & company | AY41: Kolkata | AZ41: West Bengal | BA41: SME6784348, PME6771779, AME6761288, SPE6770640, ASE6777499, IEE6769906, DSE6782069, TSE6288042, RBE6757282, MBE6782720, SGE6696032, MAE6785142, SPE6753711 | BB41: Saisab Mallick, Priyanka Mondal, Md Azharuddin, Souvik Pramanik, Arindam Sarkar, Imran Elahi, Deepak Singh, Tarkeshwar Singh, Ritam Basak, Manish Bhagat, Soumitra Ghosh, Monawwar Alam, Subhakanta Panda | BC41: Subhasis Banerjee, Ashutosh Gupta, Biswarup Ghosh, Md Shabbir Alam | BD41: Chandan Saha | BE41: Chandan Saha - Kolkata - West Bengal | BF41: Chandan Saha_Collection Agency_Kolkata_West Bengal | BG41: Chandan Saha_Repo Agency_Kolkata_West Bengal
A42: 149 | B42: Z16683 | C42: 24898 | D42: East | E42: West Bengal | F42: Kolkata | G42: Collection Agency | H42: Fusion Financier | I42: Sanjoy Chakraborty | J42: Sanjoy Chakraborty | K42: 8\38, Fern Road, Kolkata - 700019 | L42: 9831011333,9830764627 | M42: 9831011333,9830764627 | N42: 9831011333,9830764627 | O42: fusion_financier@yahoo.com | P42: NA | Q42: ACNPC6685N | S42: NA | X42: Properitoryship | Y42: Active | Z42: 45372 | AA42: 45370 | AD42: Supplementary agreement done in Mar'24 | AE42: 24898 | AF42: FUSION FINANCIER | AG42: 157 | AH42: 183 | AI42: 130 | AJ42: 470 | AL42: Allocaton given by Collection agency | AM42: Eligible for audit | AN42: KGAC | AO42: Ashutosh Gupta | AP42: 8\38, Fern Road, Kolkata - 700019 | AQ42: Audited | AR42: NA | AT42: Sandeep Kumar Gosh | AU42: Vikky Kumar | AV42: 9354241930 | AW42: 46120 | AX42: Kumar Gaurav Agarwal & company | AY42: Kolkata | AZ42: West Bengal | BA42: SDE6781658 | BB42: Sujoy Das | BC42: Ashutosh Gupta | BD42: Fusion Financier | BE42: Fusion Financier - Kolkata - West Bengal | BF42: Fusion Financier_Collection Agency_Kolkata_West Bengal
A43: 36 | B43: NA | C43: 346995 | D43: North | E43: Delhi | F43: Delhi | G43: Collection & Repossession Agency | H43: Chaudhary Associates | I43: Amit Singh | J43: Amit Singh | K43: 165, Gali No 5 Village Jagatpur, New Delhi North East Delh-110084 | L43: NA | M43: NA | N43: NA | O43: NA | P43: NA | Q43: NA | R43: NA | S43: NA | T43: NA | U43: NA | V43: NA | W43: NA | X43: NA | Y43: NA | Z43: NA | AA43: NA | AB43: NA | AC43: NA | AD43: NA | AE43: 346995 | AF43: CHAUDHARY ASSOCIATES | AG43: NA | AH43: NA | AI43: NA | AJ43: NA | AL43: Allocaton given by Repo agency | AM43: Eligible for audit | AN43: KGAC | AO43: #N/A | AP43: 165, Gali No 5 Village Jagatpur, New Delhi North East Delh-110084 | AQ43: Audited | AR43: NA | AT43: Amit Singh | AU43: Rahul Verma | AV43: 9354183359 | AW43: 46130 | AX43: Kumar Gaurav Agarwal & company | AY43: Delhi | AZ43: Delhi | BA43: NA | BB43: Sourabh Parihar, Vivek Kumar Shukla | BC43: Abhinav Lal | BD43: Chaudhary Associates | BE43: Chaudhary Associates - Delhi | BF43: Chaudhary Associates_Collection Agency_Delhi | BG43: Chaudhary Associates_Repo Agency_Delhi
A44: 137 | B44: Z25522 | C44: 12568 | D44: North | E44: Uttar Pradesh | F44: Agra | G44: Collection Agency | H44: Global Financial Consultant | I44: Dhiraj Kumar Jain | J44: Dhiraj Kumar Jain | K44: Wing B-1, 7Th Florr, Shree Vrindavan Tower, Opp. Shoe Market, Sanjay Place, Agra 282002 | L44: 0562-4000668 | M44: 0562-4000668,9758966661,9837103889,9568425247 | N44: 9837349502 | O44: GLOBALAGRA@GMAIL.COM | P44: DHK_AGRA@YAHOO.COM | Q44: ADAPJ0616J | R44: 09ADAPJ0616J1ZT | S44: 09ADAPJ0616J1ZT | T44: SERVICE PROVIDER | U44: UTTAR PREDESH 09 | X44: Proprietorship | Y44: Active | Z44: 44429 | AA44: 44413 | AE44: 12568 | AF44: Global Financial Consultant | AG44: 59 | AH44: 60 | AI44: 0 | AJ44: 119 | AL44: Allocaton given by Collection agency | AM44: Eligible for audit | AN44: KGAC | AO44: NA | AP44: Wing B-1, 7Th Florr, Shree Vrindavan Tower, Opp. Shoe Market, Sanjay Place, Agra 282002 | AQ44: Audited | AR44: NA | AT44: Shansank Agarwal | AU44: Chandan Sharma | AV44: 7753851136 | AW44: 46127 | AX44: Kumar Gaurav Agarwal & company | AY44: Agra | AZ44: Uttar Pradesh | BA44: RSE6763776 | BB44: Ram Shankar | BC44: Na | BD44: Global Financial Consultant | BE44: Global Financial Consultant - Agra - Uttar Pradesh | BF44: Global Financial Consultant_Collection Agency_Agra_Uttar Pradesh
A45: 44 | B45: Z20583 | C45: 26018 | D45: East | E45: Odisha | F45: Bhubaneshwar | G45: Collection & Repossession Agency | H45: Fairadvisory Legalservices | I45: Nidhi Prakash Yadav | J45: Nidhi Prakash Yadav | K45: C-3, Hall 5, 3Rd Floor, Plot No. A/410, Metro House, Saheed Nagar, Bhubaneshwar - 751007- | L45: 0657-2438714 | M45: 0657-2438714,8521158806,7677437282,7978942486,7504735768,9861236045,6901459251,9934824866,9864030986,7061093255, 8210106510, 8210106510, 7338703469, 8610129493, 8754312805, 9087498198, 9360441597, 9952066494, | N45: 9031040500 | O45: fairadvisory.jsr@gmail.com; collection@fairadvisory.net.in | P45: nidhi_kgdn@rediffmail.com | Q45: AAPPY5351B | S45: 20AAPPY5351B1ZS | V45: YES BANK LIMITED | X45: Properitoryship | Y45: Active | Z45: 43297 | AA45: 43297 | AD45: New email id registeration request received in Jul, Repo activity added in Dec | AE45: 26018 | AF45: Fairadvisory Legalservices | AG45: 1762 | AH45: 1483 | AI45: 1338 | AJ45: 4583 | AK45: 5 | AL45: Allocaton given by Collection & Repossession | AM45: Eligible for audit | AN45: KGAC | AO45: Biswarup Ghosh | AP45: NA | AQ45: Not Audited | AR45: Visited the agency but audit not done due to agency is working for Yes Bank from their another branch, Address : 454, Urao Basti, Old Sitaramdera, P.O - Agrico, Jamshedpur - 831009 | AS45: NA | AT45: NA | AU45: NA | AV45: NA | AW45: NA | AX45: NA | AY45: Bhubaneshwar | AZ45: Odisha | BA45: PSE6778569, JSE6785583, PYE6778749, NKE6776587, SDE6778568, SSE6756265, NDE6765957, STE6769262, SBE5788018 | BB45: Pravesh Sharma, Jay Shukla, Pankaj Yadav, Nitumani Kalita, Suman Das, Santosh Sharmayanjyoti Deka, Santosh Thakur, Sachin Bharti | BC45: Biswarup Ghosh, Md Shabbir Alam | BD45: Fairadvisory Legalservices | BE45: NA | BF45: NA | BG45: NA
A46: 112 | B46: Z21422 | C46: 26219 | D46: East | E46: Bihar | F46: Patna | G46: Collection Agency | H46: Global Management - Patna | I46: Rishikesh Mishra | J46: Rishikesh Mishra | K46: O. P. Complex, Opp Hdfc Bank, P & M Mall Road, Kurji, Patna 800010 | L46: 8809666397 | M46: 8809666397,8084225146,9305522921,6001956075,7002050742 , 9122499181 , | N46: 9920726030 | O46: prabhakar.globalmanagement@gmail.com; rishikesh.mishra@globalmanagement.in ; collection2@globalmanagement.ind.in | P46: ninad.global@gmail.com;collection.globalmanagement@gmail.com;rishi.globalmanagement@gmail.com | Q46: BNMPM5304D | S46: 27BNMPM5304D2Z3 | X46: Properitoryship | Y46: Active | Z46: 43432 | AA46: 43430 | AE46: 26219 | AF46: Global Management | AG46: 1784 | AH46: 1635 | AI46: 1588 | AJ46: 5007 | AL46: Allocaton given by Collection agency | AM46: Eligible for audit | AN46: KGAC | AO46: NA | AP46: O. P. Complex, Opp Hdfc Bank, P & M Mall Road, Kurji, Patna 800010 | AQ46: Audited | AR46: NA | AT46: Pankaj Kumar | AU46: Vikky Kumar | AV46: 9354241930 | AW46: 46133 | AX46: Kumar Gaurav Agarwal & company | AY46: Patna | AZ46: Bihar | BA46: NKE6776587, AGE6739903, DNE6774673, MME6529036, MKE6768979, RSE6776475, GSE6778012, MME6755196E6771064, AKE6769375, SBE6771663, AKE6777646, SCE6766134, NDE6765957, SSE6762160, KPE6762069 | BB46: Nitumani Kalita, Arjun Gudewar, Divya Nagda, Manoj Mishra, Manibhushan Kumar, Rupesh Singh, Gaurav Singh, Mritunjay Munnageshwar A, Abhishek Kumar, Swapnil Bhat, Ashit Kumar, Shailendra Chauhanyanjyoti Deka, Sushant Singh, Ketan Pol | BC46: Abhijeet Kashid, Subhasis Banerjee, Ashutosh Gupta, Kunal Malhotra | BD46: Global Management - Patna | BE46: Global Management - Patna - Bihar | BF46: Global Management - Patna_Collection Agency_Bihar
A47: 46 | B47: NA | C47: 351001 | D47: North | E47: Punjab | F47: Amritsar | G47: Collection & Repossession Agency | H47: Qadir Enterprises | I47: Ashwani Kumar | J47: Ashwani Kumar | K47: Sco. 18 Thrid Floor, Nehru Shopping Complex Lawrance Road, Amritsar Punjab | L47: 9876123500 | M47: 9876123500 | N47: 9876123500 | O47: Qadirenterprieses@gmail.com | P47: NA | Q47: ASBPK1360J | S47: 03ASBPK1360J1Z5 | V47: INDUSIND BANK LIMITED | X47: Proprietorship | Y47: Active | Z47: 45839 | AA47: 45839 | AE47: 351001 | AF47: QADIR ENTERPRISES | AG47: NA | AH47: NA | AI47: NA | AJ47: NA | AL47: Allocaton given by Repo agency | AM47: Eligible for audit | AN47: KGAC | AO47: #N/A | AP47: NA | AQ47: Not Audited | AR47: No repo or collection cases available with Agency in Jan to March 2026 | AS47: NA | AT47: NA | AU47: NA | AV47: NA | AW47: NA | AX47: NA | AY47: Amritsar | AZ47: Punjab | BA47: NA | BB47: NA | BC47: NA | BD47: Qadir Enterprises | BE47: NA | BF47: NA | BG47: NA
A48: 11 | B48: Z23039 | C48: 26323 | D48: North | E48: Delhi | F48: Delhi | G48: Collection & Repossession Agency | H48: Delta Services | I48: Anil Sharma | J48: Anil Sharma / Paramjeet Singh | K48: Wz-20, Possangipur, Janakpuri, New Delhi – 110058 | L48: 9971153647,9810396799 | M48: 9971153647,8506080708,8802044516,7011216498,9210620005,8178669564,9896254268,9810396799,8287593410,9891919811,7303421524,9910937893,01143685208 | N48: 9810396799,8506080708 | O48: himanshudeltaservices@gmail.com ; anilsharmaojas1@gmail.com | P48: NA | Q48: BAUPS1949D | S48: 07BAUPS1949D2Z7 | V48: YES BANK LIMITED | X48: Properitoryship | Y48: Active | Z48: 43829 | AA48: 43829 | AE48: 26323 | AF48: Delta Services | AG48: 573 | AH48: 542 | AI48: 489 | AJ48: 1604 | AK48: 43 | AL48: Allocaton given by Collection & Repossession | AM48: Eligible for audit | AN48: KGAC | AO48: NA | AP48: Wz-20, Possangipur, Janakpuri, New Delhi – 110058 | AQ48: Audited | AR48: NA | AT48: Anil Sharma | AU48: Pawan Kumar | AV48: 9582917652 | AW48: 46134 | AX48: Kumar Gaurav Agarwal & company | AY48: Delhi | AZ48: Delhi | BA48: RAE6783127, KSE6769063, SKE5835012, SSE6775469, RSE6763776, STE5844128, PKE6779360, MKE6780549 | BB48: Rittin Arya, Kushpal Singh, Sushim Kumar, Sukhwinder Singh, Ram Shankar, Sandeep Tyagi, Pawan Kumar, Milind Kumbhar | BC48: Sanjeev Kumar, Rajnish Dwivedi | BD48: Delta Services | BE48: Delta Services - Delhi | BF48: Delta Services_Collection Agency_Delhi | BG48: Delta Services_Repo Agency_Delhi
A49: 81 | B49: NA | C49: 282016 | D49: North | E49: Uttar Pradesh | F49: Allahabad | G49: Collection & Repossession Agency | H49: Global Services - Allahabad | I49: Sandeep Kumar Singh | J49: Sandeep Kumar Singh | K49: 15 24 , Stainley Road , Civil Lines Allahabad-211001 | L49: 9889577777 | M49: 9889577777 | N49: 9889577777 | O49: globalservices.ald@gmail.com | P49: NA | Q49: DGHPS4102K | S49: 09DGHPS4102K1Z5 | V49: YES BANK LIMITED | X49: Properitoryship | Y49: Active | Z49: 45555 | AA49: 45554 | AE49: 282016 | AF49: GLOBAL SERVICES | AG49: 104 | AH49: 262 | AI49: 201 | AJ49: 567 | AL49: Allocaton given by Collection agency | AM49: Eligible for audit | AN49: KGAC | AO49: Kunal Malhotra | AP49: 15 24 , Stainley Road , Civil Lines Allahabad-211001 | AQ49: Audited | AR49: NA | AT49: Sandip Singh | AU49: Chandan Sharma | AV49: 7753851136 | AW49: 46122 | AX49: Kumar Gaurav Agarwal & company | AY49: Allahabad | AZ49: Uttar Pradesh | BA49: RSE6762728, DSE6786366, MKE6467020, VME6772902, KKE6776767 | BB49: Ravi Singh, Dheerendra Singh, Manoj Kumar, Vaibhav Mishra, Kunwar Kumar Singh | BC49: Kunal Malhotra, Upanshu Bajaj | BD49: Global Services - Allahabad | BE49: Global Services - Allahabad - Uttar Pradesh | BF49: Global Services - Allahabad_Collection Agency_Uttar Pradesh
A50: 14 | B50: NA | C50: 282016 | D50: North | E50: Delhi | F50: Delhi | G50: Collection & Repossession Agency | H50: Global Services - Delhi | I50: Sandeep Kumar Singh | J50: Sandeep Kumar Singh | K50: C-128/2, Village- Mohdpur New Delhi- 110067 | L50: 9889577777 | M50: 9889577777 | N50: 9889577777 | O50: globalservices.ald@gmail.com | P50: NA | Q50: DGHPS4102K | R50: 0 | S50: #N/A | T50: 0 | U50: 0 | V50: YES BANK LIMITED | W50: 0 | X50: Properitoryship | Y50: Active | Z50: 45555 | AA50: 45554 | AB50: 0 | AC50: 0 | AD50: 0 | AE50: 282016 | AF50: GLOBAL SERVICES | AG50: 104 | AH50: 262 | AI50: 201 | AJ50: 567 | AL50: Allocaton given by Collection agency | AM50: Eligible for audit | AN50: KGAC | AO50: Kunal Malhotra | AP50: C-128/2, Village- Mohdpur New Delhi- 110067 | AQ50: Audited | AR50: NA | AT50: Neha (8851441735) | AU50: Akshay Notiyal | AV50: 9149204613 | AW50: 46135 | AX50: Kumar Gaurav Agarwal & company | AY50: Delhi | AZ50: Delhi | BA50: RSE6762728, DSE6786366, MKE6467020, VME6772902, KKE6776767 | BB50: Ravi Singh, Dheerendra Singh, Manoj Kumar, Vaibhav Mishra, Kunwar Kumar Singh | BC50: Kunal Malhotra, Upanshu Bajaj | BD50: Global Services - Delhi | BE50: Global Services - Delhi - Delhi | BF50: Global Services - Delhi_Collection Agency_Delhi
A51: 167 | B51: NA | C51: 220977 | D51: North | E51: Haryana | F51: Gurgoan | G51: Repossession Agency | H51: Golden Hawk Debt Management And Legal Services Pvt. Ltd | I51: Ajay Singh Boken | J51: Ajay Singh Boken | K51: 2315/32 Gali No 1 , Near Atul Katariya Chowk , Gurgaon Haryana 122001 | L51: 9811981900 | M51: 9811981900 | N51: 9811981900 | O51: ajay.singh@goldenhawk.co.in | P51: NA | Q51: AADCG6578M | S51: 06AADCG6578M2Z0 | V51: YES BANK LIMITED | X51: Company | Y51: Active | Z51: 45703 | AA51: 45702 | AE51: 220977 | AF51: Golden hawk debt management and legal services pvt. Ltd | AG51: 15 | AH51: 13 | AI51: 0 | AJ51: 28 | AL51: Allocaton given by Collection agency | AM51: Eligible for audit | AN51: KGAC | AO51: NA | AP51: 2315/32 Gali No 1 , Near Atul Katariya Chowk , Gurgaon Haryana 122001 | AQ51: Audited | AR51: NA | AT51: Mithilesh Kumar | AU51: Pradeep | AV51: 8287823681 | AW51: 46136 | AX51: Kumar Gaurav Agarwal & company | AY51: Gurgoan | AZ51: Haryana | BA51: NA | BB51: NA | BC51: Sumit Narang | BD51: Golden Hawk Debt Management And Legal Services Pvt. Ltd | BE51: Golden Hawk Debt Management And Legal Services Pvt. Ltd - Gurgoan - Haryana | BF51: Golden Hawk Debt Management And Legal Services Pvt. Ltd_Collection Agency_Gurgoan_Haryana
A52: 99 | B52: Z25979 | C52: 12552 | D52: North | E52: Uttar Pradesh | F52: Saharanpur | G52: Collection & Repossession Agency | H52: Goldline Solutions Pvt Ltd | I52: Sandeep Saini & Girish Kher | J52: Kamal Kishore | K52: 7/98, 99 Gau Shala Road, Mubarak Shah, Near Punjabi Gurudwara, Saharanpur(Uttar Pradesh) Pin:- 247001 | L52: 9719790000 | M52: 9719790000,6398431149,8394088088,7088564465 | N52: 9719560009 | O52: GLS.YESBANK@GOLDLINE.NET.IN ; gls.help@goldline.net.in | P52: GLS.OWNERS@GOLDLINE.NET.IN | Q52: AAGCG8454P | S52: 09AAGCG8454P1ZR | V52: PUNJAB NATIONAL BANK | X52: PVT Ltd | Y52: Active | Z52: 44561 | AA52: 44560 | AE52: 12552 | AF52: Goldline Solutions pvt ltd | AG52: 282 | AH52: 296 | AI52: 308 | AJ52: 886 | AL52: Allocaton given by Collection agency | AM52: Eligible for audit | AN52: KGAC | AO52: Abhinav Lal | AP52: 7/98, 99 Gau Shala Road, Mubarak Shah, Near Punjabi Gurudwara, Saharanpur(Uttar Pradesh) Pin:- 247001 | AQ52: Audited | AR52: NA | AT52: Sandeep Saini / 9719790000 | AU52: Akshay Notiyal | AV52: 9149204613 | AW52: 46130 | AX52: Kumar Gaurav Agarwal & company | AY52: Saharanpur | AZ52: Uttar Pradesh | BA52: NKE6775741, HKE6745350, SKE6779366, RAE6783127 | BB52: Nitin Kumar, Hayat Kathayat, Sumit Kumar, Rittin Arya | BC52: Sanjeev Kumar, Abhinav Lal, Sameer Dhar, Rohit Nijhawan | BD52: Goldline Solutions Pvt Ltd | BE52: Goldline Solutions Pvt Ltd - Saharanpur - Uttar Pradesh | BF52: Goldline Solutions Pvt Ltd_Collection Agency_Saharanpur_Uttar Pradesh
A53: 95 | B53: NA | C53: 345011 | D53: North | E53: Uttar Pradesh | F53: Varanasi | G53: Collection & Repossession Agency | H53: Dhiraj Singh Agency | I53: Dhiraj Singh | J53: Dhiraj Singh | K53: L3 Awadh Paradise Haruha Airport Road Haruha Varansi Up-221001 | L53: 9935735100 , 9936735100 | M53: 9935735100 , 9936735100 | N53: 9935735100 , 9936735100 | O53: Dheerajsinghagency@gmail.com | P53: dheeraj7200@gmail.com | Q53: EOZPS1593R | S53: 09EOZPS1593F1ZA | V53: AXIS BANK LTD | X53: Properitoryship | Y53: Active | Z53: 45834 | AA53: 45834 | AE53: 345011 | AF53: Dhiraj Singh Agency | AG53: NA | AH53: NA | AI53: NA | AJ53: NA | AK53: 1 | AL53: Allocaton given by Repo agency | AM53: Eligible for audit | AN53: KGAC | AO53: #N/A | AP53: L3 Awadh Paradise Haruha Airport Road Haruha Varansi Up-221001 | AQ53: Audited | AR53: NA | AT53: Piyush Singh | AU53: Chandan Sharma | AV53: 7753851136 | AW53: 46120 | AX53: Kumar Gaurav Agarwal & company | AY53: Varanasi | AZ53: Uttar Pradesh | BA53: NA | BB53: Kushpal Singh, Vivek Kumar Shukla, Vivek Shukla, Manibhushan Kumar, Ankit Bambhaniya. | BC53: Abhinav Lal, Subhasis Banerjee | BD53: Dhiraj Singh Agency | BE53: Dhiraj Singh Agency - Varanasi - Uttar Pradesh | BF53: Dhiraj Singh Agency_Collection Agency_Varanasi_Uttar Pradesh | BG53: Dhiraj Singh Agency_Repo Agency_Varanasi_Uttar Pradesh
A54: 114 | B54: Z23170 | C54: 26111 | D54: North | E54: Delhi | F54: Delhi | G54: Collection Agency | H54: Gurman Industries - Nirman Vihar | I54: Sukhpreet Singh | J54: Sukhpreet Singh / Harpreet Singh / Umesh Sharma / Naveen Dua | K54: Mb-1/E, Madhuban Road, Vikas Marg, Shakarpur, New Delhi,East Delhi, Delhi India -110092 | L54: 9999997206,8711888990,9650031357,9716677887 | M54: 9999997206,8711888990,9650031357,9716677887,9811104946,9717899267,9716364866,7065571204 | N54: 9999997206 | O54: gurman.industry.srt@gmail.com ; sukhpreetsinghmalhotra@yahoo.com ; gurmanind@outlook.com | P54: NA | Q54: AIFPM1682B | R54: 0 | S54: 07AIFPM1682B2ZI | T54: 0 | U54: 0 | V54: 0 | W54: 0 | X54: Properitoryship | Y54: Active | Z54: 43788 | AA54: 40131 | AB54: 0 | AC54: 0 | AD54: New Address for Autoloan product request received in Oct. | AE54: 26111 | AF54: Gurman Industries | AG54: 371 | AH54: 421 | AI54: 529 | AJ54: 1321 | AL54: Allocaton given by Collection agency | AM54: Eligible for audit | AN54: KGAC | AO54: Rohit Nijhawan | AP54: Mb-1/E, Madhuban Road, Vikas Marg, Shakarpur, New Delhi,East Delhi, Delhi India -110092 | AQ54: Audited | AR54: NA | AT54: Gauri Shankar Sharma/7011373173 | AU54: Abhinav Khurana | AV54: 9217935065 | AW54: 46135 | AX54: Kumar Gaurav Agarwal & company | AY54: Delhi | AZ54: Delhi | BA54: VPE6766232, CME6702019, MKE6467020 | BB54: Vivek Pandey, Chander Miglani, Manoj Kumar | BC54: Rohit Nijhawan | BD54: Gurman Industries - Nirman Vihar | BE54: Gurman Industries - Nirman Vihar - Delhi | BF54: Gurman Industries - Nirman Vihar_Collection Agency_Delhi
A55: 115 | B55: Z23170 | C55: 26111 | D55: North | E55: Delhi | F55: Delhi | G55: Collection Agency | H55: Gurman Industries - Shubhash Nagar | I55: Sukhpreet Singh | J55: Sukhpreet Singh / Harpreet Singh / Umesh Sharma / Naveen Dua | K55: Plot No.5 Top Floor Near Marry Zone Banquet , Subhash Nagar Metro Station , Gate No.2 Tilak Nagar , Industrial Area , New Delhi-110019 | L55: 9999997206,8711888990,9650031357,9716677887 | M55: 9999997206,8711888990,9650031357,9716677887,9811104946,9717899267,9716364866,7065571204 | N55: 9999997206 | O55: gurman.industry.srt@gmail.com ; sukhpreetsinghmalhotra@yahoo.com ; gurmanind@outlook.com | P55: NA | Q55: AIFPM1682B | S55: 07AIFPM1682B2ZI | X55: Properitoryship | Y55: Active | Z55: 43788 | AA55: 40131 | AD55: New Address for Autoloan product request received in Oct. | AE55: 26111 | AF55: Gurman Industries | AG55: 371 | AH55: 421 | AI55: 529 | AJ55: 1321 | AL55: Allocaton given by Collection agency | AM55: Eligible for audit | AN55: KGAC | AO55: Rohit Nijhawan | AP55: Plot No.5 Top Floor Near Marry Zone Banquet , Subhash Nagar Metro Station , Gate No.2 Tilak Nagar , Industrial Area , New Delhi-110019 | AQ55: Audited | AR55: NA | AT55: Arif / 8742950251 | AU55: Abhinav Khurana | AV55: 9217935065 | AW55: 46134 | AX55: Kumar Gaurav Agarwal & company | AY55: Delhi | AZ55: Delhi | BA55: VPE6766232, CME6702019, MKE6467020 | BB55: Vivek Pandey, Chander Miglani, Manoj Kumar | BC55: Rohit Nijhawan | BD55: Gurman Industries - Shubhash Nagar | BE55: Gurman Industries - Shubhash Nagar - Delhi | BF55: Gurman Industries - Shubhash Nagar_Collection Agency_Delhi
A56: 55 | B56: Z25738 | C56: 24712 | D56: North | E56: Punjab | F56: Jalandhar | G56: Collection & Repossession Agency | H56: Resolution Achievers | I56: Puneet Kumar | J56: Puneet Kumar | K56: # 7-8 Nehru Garden Road, Opp. Bocki Industries, Jalandhar-I, Jalandhar, 144001 | L56: 0181-5012803,0181-5092369 | M56: 0181-5012803,0181-3564888,0181-5092369 | N56: 9888277220 | O56: ib@resolutionachievers.com | P56: puneet.kumar9972@gmail.com | Q56: AKPPK6137M | R56: NA | S56: 03AKPPK6137M1ZS | V56: YES BANK LIMITED | X56: Proprietorship | Y56: Active | Z56: 44482 | AA56: 44480 | AE56: 24712 | AF56: Resolution Achievers | AG56: 751 | AH56: 744 | AI56: 652 | AJ56: 2147 | AL56: Allocaton given by Collection agency | AM56: Eligible for audit | AN56: KGAC | AO56: Ashutosh Gupta | AP56: NA | AQ56: Not Audited | AR56: Audited on another address : 49-A, New Jawahar Nagar, ( Opp Apj School, Bmc Chowk ) Jalandhar City, Jalandhar-144001 | AS56: NA | AT56: NA | AU56: NA | AV56: NA | AW56: NA | AX56: NA | AY56: Jalandhar | AZ56: Punjab | BA56: KSE6769063, SSE6775469, SKE6776527, VKE6782576, VKE6600027, Mse6761857, SSE6748795 | BB56: Kushpal Singh, Sukhwinder Singh, Sunil Kumar , Vikash Kumar, Vivek Kumar Kaushal, Manmohan Singh, Sukhwant Singh | BC56: Ashutosh Gupta, Sameer Dhar | BD56: Resolution Achievers | BE56: NA | BF56: NA | BG56: NA
A57: 3 | B57: Yblv1123 | C57: 306987 | D57: East | E57: Assam | F57: Guwahati | G57: Collection & Repossession Agency | H57: Gurseerat Legal Management Service | I57: Harvinder Singh Upp | J57: Harvinder Singh Upp | K57: Kachari Basti Road, House No. 1, Holding No. 246 Of Gmc Ulubari, Guwahati, Kamrup, Assam-781007. | L57: 9650501568 | M57: 9650501568 | N57: 9650501568 | O57: Gurseerat.yesbank@gmail.com | P57: NA | Q57: CBMPS3176E | S57: 07CBMPS3176E1ZC | X57: Proprietorship | Y57: Active | Z57: 45659 | AA57: 45656 | AD57: New Repossession project | AE57: 306987 | AF57: GURSEERAT LEGAL MANAGEMENT SERVICE | AG57: 1292 | AH57: 1292 | AI57: 1145 | AJ57: 3729 | AL57: Allocaton given by Collection agency | AM57: Eligible for audit | AN57: KGAC | AO57: NA | AP57: Kachari Basti Road, House No. 1, Holding No. 246 Of Gmc Ulubari, Guwahati, Kamrup, Assam-781007. | AQ57: Audited | AR57: NA | AT57: Rakesh | AU57: Pradeep | AV57: 8287823681 | AW57: 46129 | AX57: Kumar Gaurav Agarwal & company | AY57: Guwahati | AZ57: Assam | BA57: NKE6776587, SBE6782270, VME6772902, SRE6782838, RSE6776475, NDE6765957 | BB57: Nitumani Kalita, Subhajit Bhowmik, Vaibhav Mishra, Sidharth RaRupesh Singhyanjyoti Deka | BC57: Na | BD57: Gurseerat Legal Management Service | BE57: Gurseerat Legal Management Service - Guwahati - Assam | BF57: Gurseerat Legal Management Service_Collection Agency_Guwahati_Assam
A58: 57 | B58: NA | C58: 12611 | D58: North | E58: Punjab | F58: Ludhiana | G58: Collection & Repossession Agency | H58: Royal Finance Associates | I58: Charanjit Singh | J58: Charanjit Singh | K58: Sco -21 2Nd Floor Cabin No.-206, Feroz Gandhi Market, Ludhiana 141001 | L58: 9914500602 | M58: 9914500602 | N58: 9914500602 | O58: royalfinanceassociates@gmail.com | P58: NA | Q58: GQSPS8565N | S58: 03GQSPS8565N1ZL | V58: BANDHAN BANK | X58: Properitoryship | Y58: Active | Z58: 45722 | AA58: 45722 | AD58: Renewal done on 10th sep 25 | AE58: 12611 | AF58: Royal Finance Associates | AG58: 0 | AH58: 2 | AI58: 0 | AJ58: 2 | AL58: Allocaton given by Collection agency | AM58: Eligible for audit | AN58: KGAC | AO58: TBH | AP58: NA | AQ58: Not Audited | AR58: As discussed with Shiraz sir, Royal Finance Associates to be marked as not audited as agency having less than 10 collection cases in Jan to March 2026 | AS58: NA | AT58: NA | AU58: NA | AV58: NA | AW58: NA | AX58: NA | AY58: Ludhiana | AZ58: Punjab | BA58: SKE6777255 | BB58: Sandeep Kumar | BD58: Royal Finance Associates | BE58: NA | BF58: NA | BG58: NA
A59: 103 | B59: Z18015 | C59: 25877 | D59: East | E59: West Bengal | F59: Kolkata | G59: Collection & Repossession Agency | H59: Easyway Advisory | I59: Sumita Das | J59: Sumita Das | K59: 28 (264/1) Dum Dum C Road, Kolkata - 700074 | L59: 9830224152 | M59: 9830224152,9804510702,9830345491,9836271214,7596929716,7890353325,8820602853,9804719393,8910300654,8272952761,7003778911,6291038887,7003354014,7384681593,7686026660,9804759569,9432708868,9874571598,9674292668,6291076359,8945967695,7890763153,9123764710,9123787772,033-2560-4434,086-9700-5532,083-3499-2690 | N59: 9830224152 | O59: easywayneworg@gmail.com; collection.ybkol@easyway.in.net | P59: NA | Q59: ALVPD1996J | R59: ALVPD1996JSD001 | S59: 19ALVPD1996J1ZB | V59: YES BANK LIMITED | X59: Properitoryship | Y59: Active | Z59: 42993 | AA59: 42990 | AE59: 25877 | AF59: Easyway Advisory | AG59: 616 | AH59: 625 | AI59: 608 | AJ59: 1849 | AK59: 2 | AL59: Allocaton given by Collection & Repossession | AM59: Eligible for audit | AN59: KGAC | AO59: NA | AP59: 28 (264/1) Dum Dum C Road, Kolkata - 700074 | AQ59: Audited | AR59: NA | AT59: Suradip Mondal | AU59: Vikky Kumar | AV59: 9354241930 | AW59: 46119 | AX59: Kumar Gaurav Agarwal & company | AY59: Kolkata | AZ59: West Bengal | BA59: KSE6767729, JSE6781036 | BB59: Krishnendu Sarder, Joy Saha | BC59: Na | BD59: Easyway Advisory | BE59: Easyway Advisory - Kolkata - West Bengal | BF59: Easyway Advisory_Collection Agency_Kolkata_West Bengal | BG59: Easyway Advisory_Repo Agency_Kolkata_West Bengal
A60: 96 | B60: NA | C60: 323996 | D60: North | E60: Uttarakhand | F60: Dehradun | G60: Collection & Repossession Agency | H60: Elite Debt Associates | I60: Padmadutt Pandey | J60: Padmadutt Pandey | K60: 3Rd Floor, B-228 Nehru, Colony | L60: 7895100604 | M60: 7895100604 | N60: 7895100604 | O60: ELITEDEBT.ASSOCIATES@REDIFFMAIL.COM | P60: NA | Q60: BAKPP7909J | S60: 05BAKPP7909J2Z7 | V60: YES BANK LIMITED | X60: Properitoryship | Y60: Active | Z60: 45791 | AA60: 45786 | AD60: Supplementary agreement done on 15th April '25 | AE60: 323996 | AF60: Elite Debt associates | AG60: NA | AH60: NA | AI60: NA | AJ60: NA | AL60: Allocaton given by Repo agency | AM60: Eligible for audit | AN60: KGAC | AO60: #N/A | AP60: 3Rd Floor, B-228 Nehru, Colony | AQ60: Audited | AR60: NA | AT60: Ankit (9675445974) | AU60: Akshay Notiyal | AV60: 9149204613 | AW60: 46133 | AX60: Kumar Gaurav Agarwal & company | AY60: Dehradun | AZ60: Uttarakhand | BA60: NA | BB60: Rittin Arya | BC60: NA | BD60: Elite Debt Associates | BE60: Elite Debt Associates - Dehradun - Uttarakhand | BF60: Elite Debt Associates_Collection Agency_Dehradun_Uttarakhand | BG60: Elite Debt Associates_Repo Agency_Dehradun_Uttarakhand
A61: 30 | B61: Z20583 | C61: 26018 | D61: East | E61: Jharkhand | F61: Jamshedpur | G61: Collection & Repossession Agency | H61: Fairadvisory Legalservices | I61: Nidhi Prakash Yadav | J61: Nidhi Prakash Yadav | K61: 454, Urao Basti, Old Sitaramdera, P.O - Agrico, Jamshedpur - 831009 | L61: 0657-2438714 | M61: 0657-2438714,8521158806,7677437282,7978942486,7504735768,9861236045,6901459251,9934824866,9864030986,7061093255, 8210106510, 8210106510, 7338703469, 8610129493, 8754312805, 9087498198, 9360441597, 9952066494, | N61: 9031040500 | O61: fairadvisory.jsr@gmail.com; collection@fairadvisory.net.in | P61: nidhi_kgdn@rediffmail.com | Q61: AAPPY5351B | S61: 20AAPPY5351B1ZS | V61: YES BANK LIMITED | X61: Properitoryship | Y61: Active | Z61: 43297 | AA61: 43297 | AD61: New email id registeration request received in Jul, Repo activity added in Dec | AE61: 26018 | AF61: Fairadvisory Legalservices | AG61: 1762 | AH61: 1483 | AI61: 1338 | AJ61: 4583 | AK61: 5 | AL61: Allocaton given by Collection & Repossession | AM61: Eligible for audit | AN61: KGAC | AO61: Biswarup Ghosh | AP61: 454, Urao Basti, Old Sitaramdera, P.O - Agrico, Jamshedpur - 831009 | AQ61: Audited | AR61: NA | AT61: Puja Das | AU61: Vikky Kumar | AV61: 9354241930 | AW61: 46128 | AX61: Kumar Gaurav Agarwal & company | AY61: Jamshedpur | AZ61: Jharkhand | BA61: PSE6778569, JSE6785583, PYE6778749, NKE6776587, SDE6778568, SSE6756265, NDE6765957, STE6769262, SBE5788018 | BB61: Pravesh Sharma, Jay Shukla, Pankaj Yadav, Nitumani Kalita, Suman Das, Santosh Sharmayanjyoti Deka, Santosh Thakur, Sachin Bharti | BC61: Biswarup Ghosh, Md Shabbir Alam | BD61: Fairadvisory Legalservices | BE61: Fairadvisory Legalservices - Jamshedpur - Jharkhand | BF61: Fairadvisory Legalservices_Collection Agency_Jamshedpur_Jharkhand | BG61: Fairadvisory Legalservices_Repo Agency_Jamshedpur_Jharkhand
A62: 136 | B62: Z26560 | C62: 12488 | D62: North | E62: Rajasthan | F62: Udaipur | G62: Collection Agency | H62: Ishaan Associates | I62: Mayank Mohale | J62: Mayank Mohale | K62: 17- Pushpa Vihar , Jeevantara, Goverdhan Vilas , Dewali, Udaipur -313001, Rajasthan | L62: 9950460462 | M62: 9828606335,9950460462 | N62: 9950460462 | O62: ishaanassociates2@gmail.com | P62: mayankmohale@gmail.com | Q62: ANVPM4297R | S62: 08ANVPM4297R1ZL | X62: Properitoryship | Y62: Active | Z62: 44659 | AA62: 44652 | AE62: 12488 | AF62: Ishaan Associates | AG62: 49 | AH62: 48 | AI62: 48 | AJ62: 145 | AL62: Allocaton given by Collection agency | AM62: Eligible for audit | AN62: KGAC | AO62: Kalpesh Raval | AP62: 17- Pushpa Vihar , Jeevantara, Goverdhan Vilas , Dewali, Udaipur -313001, Rajasthan | AQ62: Audited | AR62: NA | AT62: Mayank | AU62: Chandan Sharma | AV62: 7753851136 | AW62: 46132 | AX62: Kumar Gaurav Agarwal & company | AY62: Udaipur | AZ62: Rajasthan | BA62: DRE6759196, RCE6775150 | BB62: Devi Rathore, Ram Choudhary | BC62: Saurabh Saroch, Kalpesh Raval | BD62: Ishaan Associates | BE62: Ishaan Associates - Udaipur - Rajasthan | BF62: Ishaan Associates_Collection Agency_Udaipur_Rajasthan
A63: 169 | B63: NA | C63: 309992 | D63: East | E63: Jharkhand | F63: Ranchi | G63: Repossession Agency | H63: G S Services | I63: Anup Kumar | J63: Anup Kumar | K63: New Mahaveer Colny , Tetri Toli, Namkum,Ranchi 834010, New Mahaveer Colny , Tetri Toli, Namkum,Ranchi 834010, New Mahaveer Colny , Tetri Toli, Namkum,Ranchi 834010 | L63: 7549171717 | M63: 7549171717 | N63: 7549171717 | O63: gsservices8879@gmail.com | P63: NA | Q63: CSVPD1337A | S63: 20CSVPD1337A1ZC | V63: KOTAK MAHINDRA BANK LIMITED | X63: Properitoryship | Y63: Active | Z63: 45636 | AA63: 45631 | AD63: New Repossession project | AE63: 309992 | AF63: G S SERVICES | AG63: NA | AH63: NA | AI63: NA | AJ63: NA | AK63: 2 | AL63: Allocaton given by Repo agency | AM63: Eligible for audit | AN63: KGAC | AO63: #N/A | AP63: New Mahaveer Colny , Tetri Toli, Namkum,Ranchi 834010, New Mahaveer Colny , Tetri Toli, Namkum,Ranchi 834010, New Mahaveer Colny , Tetri Toli, Namkum,Ranchi 834010 | AQ63: Audited | AR63: NA | AT63: Rakesh Ji | AU63: Vikky Kumar | AV63: 9354241930 | AW63: 46130 | AX63: Kumar Gaurav Agarwal & company | AY63: Ranchi | AZ63: Jharkhand | BA63: NA | BB63: Santosh Kumar Thakur, Amit Ranjan Singh, Sachin Bharti, Sankerbalaji N, Santosh Kumar Sharma, Pritam Khastagir | BC63: Subhasis Banerjee, Biswarup Ghosh | BD63: G S Services | BE63: G S Services - Ranchi - Jharkhand | BF63: G S Services_Collection Agency_Ranchi_Jharkhand | BG63: G S Services_Repo Agency_Ranchi_Jharkhand
A64: 63 | B64: Z21689 | C64: 26539 | D64: North | E64: Rajasthan | F64: Alwar | G64: Collection & Repossession Agency | H64: A R Group - Alwar | I64: Babita Choudhary | J64: Babita Choudhary / Satyander Choudhary | K64: Room No.9, 1St Floor, Jat Boarding, Station Road, Alwar-301001- | L64: 0144-2702001 | M64: 0144-2702001,7412999557,7230020762 | N64: 9828559459 | O64: argroupalwar@gmail.com | P64: NA | Q64: AMAPC4791J | S64: 08AMAPC4791J1ZZ | V64: YES BANK LIMITED | X64: Properitoryship | Y64: Active | Z64: 43615 | AA64: 43613 | AD64: Panipat Location added on 27th Nov'23// Renewal agreement done 16th mar 26. | AE64: 26539 | AF64: A R Group | AG64: 595 | AH64: 685 | AI64: 753 | AJ64: 2033 | AK64: 1 | AL64: Allocaton given by Collection & Repossession | AM64: Eligible for audit | AN64: KGAC | AO64: Ashutosh Gupta | AP64: NA | AQ64: Not Audited | AR64: On 24th April 2026, our auditor Mr. Chandan Sharma visited the agency to conduct the audit. However, the audit could not be completed due to deliberate non-cooperation and obstructive behaviour by the agency staff. After presenting the authorized letter and ID card to agency person, the audit could not be completed due to deliberate non-cooperation , Abusing, harsh/rude behaviour and threaten to beat Auditor by the agency person. Agency person have collected auditor’s phone by forcefully and deleted all the evidence captured by the auditor. and agency person asked who have been authorised you to audit my agency and asked him to leave the agency or he will beat auditor. Due to these, hostile behaviour, and lack of cooperation, the audit could not be conducted and all the evidence deleted by agency person. | AS64: NA | AT64: NA | AU64: NA | AV64: NA | AW64: NA | AX64: NA | AY64: Alwar | AZ64: Rajasthan | BA64: PSE6778569, KDE6778345, SME5900019, KRE6769463, MCE6787677 | BB64: Pravesh Sharma, Kailash Devanda, Siddharth Maharishi, Kuldeep Rathore, Maya Choudhary | BC64: Ashutosh Gupta, Sameer Dhar | BD64: A R Group - Alwar | BE64: NA | BF64: NA | BG64: NA
A65: 120 | B65: NA | C65: 71934 | D65: North | E65: Delhi | F65: Delhi | G65: Collection Agency | H65: Jai Ambey Associates | I65: Ajay Kumar Trivedi | J65: Ajay Kumar Trivedi | K65: A30 Pillar No 538 2Nd Floor Tilak Nagar Near Janalpuri East Metro Station New Delhi 110018 | L65: 9389213520 | M65: 9389213520 | N65: 9389213520 | O65: JAIAMBEASSOCIATE@GMAIL.COM | P65: NA | Q65: ACYPT6677J | S65: 09ACYPT6677J2Z7 | X65: Properitoryship | Y65: Active | Z65: 45965 | AA65: 45965 | AD65: Supplementary done on 4th nov 25 | AE65: 71934 | AF65: JAI AMBEY ASSOCIATES | AG65: 0 | AH65: 269 | AI65: 97 | AJ65: 366 | AL65: Allocaton given by Collection agency | AM65: Eligible for audit | AN65: KGAC | AO65: NA | AP65: A30 Pillar No 538 2Nd Floor Tilak Nagar Near Janalpuri East Metro Station New Delhi 110018 | AQ65: Audited | AR65: NA | AT65: Piyush Chouhan / 7014621268 | AU65: Abhinav Khurana | AV65: 9217935065 | AW65: 46119 | AX65: Kumar Gaurav Agarwal & company | AY65: Delhi | AZ65: Delhi | BA65: JSE6785583 | BB65: Jay Shukla | BC65: Na | BD65: Jai Ambey Associates | BE65: Jai Ambey Associates - Delhi | BF65: Jai Ambey Associates_Collection Agency_Delhi
A66: 13 | B66: Z22853 | C66: 26490 | D66: North | E66: Delhi | F66: Delhi | G66: Collection & Repossession Agency | H66: G.D.M. Management Services Pvt Ltd - Delhi | I66: Rajesh Kumar/Naresh Kumar | J66: Rajesh Kumar/Naresh Kumar | K66: A-1 1St Floor , Shastri Nagar , New Delhi -110034 | L66: 011,40919715,9354909242,9315045873,7678326675,7827410614,8882896148,8595955476,8882818651,9315131930,8178036157,8851243856,7827429289,76783918128076508276,8882899467,8595956472,7678321553,7678308077,7678396018,8920038807,8368999916,8810592365,9315748638,7678324044,8882403961,8595954459,8076608859,8076534454,8920963073,8920038738 | M66: 011,40919715,9354909242,9315045873,7678326675,7827410614,8882896148,8595955476,8882818651,9315131930,8178036157,8851243856,7827429289,76783918128076508276,8882899467,8595956472,7678321553,7678308077,7678396018,8920038807,8368999916,8810592365,9315748638,7678324044,8882403961,8595954459,8076608859,8076534454,8920963073,8920038738,7292030107,9999098611,9891999980,7017538011,9810205430,9958686165,9266697828,9817875090,9671775656,9992202126,9050604254,9667169442,8851473697,7065315053,7065954659,7065963209,7065640923,8750131886,8750773816,8750273692,8750967594,8750172809,8750973013,8750537906,8750957629,8750900871,8588893713,8588842445,8588847253,8750177170,8750094542,7065502925,7065494502,7065936794,7065784203,7065675119,7065680813,7065334058,7065610331,8588845250,8588875903,8588891770,8588858236,8588876523,8588846304,7669627101,7669794829,7669591561,7669898316,7669794921,7669201607,7669818304,7669836846,7669803373,7669201593,7669614273,7669764163,7669794879,7669646432,7669516059,7669595815,7669616520,7669988972,7669886976,7669614267,7669573471,7669196176,7669827710,7669675347,7669614262,8929665273,8929110705,8929988714,8929447921,8929727441,8929925517,8929843241 | N66: 9896400088,9354909242 | O66: goodwill_naresh@outlook.com ; gdmdebtmanagement@outlook.com | P66: NA | Q66: AAHCG6535C | R66: 0 | S66: 06AAHCG6535C1ZT | T66: 0 | U66: 0 | V66: ICICI BANK LIMITED | W66: 0 | X66: PVT Ltd | Y66: Active | Z66: 43724 | AA66: 43704 | AB66: 0 | AC66: 0 | AD66: Addition address req received in Sept, Supplementary agreement done on 18th Sep'23 | AE66: 26490 | AF66: G.D.M. Management Services PVT LTD | AG66: 2186 | AH66: 2355 | AI66: 2014 | AJ66: 6555 | AK66: 2 | AL66: Allocaton given by Collection & Repossession | AM66: Eligible for audit | AN66: KGAC | AO66: Ashutosh Gupta | AP66: A-1 1St Floor , Shastri Nagar , New Delhi -110034 | AQ66: Audited | AR66: NA | AT66: Rupali Singh/8539940963 | AU66: Abhinav Khurana | AV66: 9217935065 | AW66: 46132 | AX66: Kumar Gaurav Agarwal & company | AY66: Delhi | AZ66: Delhi | BA66: NRE6746973, SRE6739824, RSE6763776, SRE6782838, RCE6775867, BRE6281007, ANE5784049, ERE6776646, PKE6779360, VME6772902, KSE6769063, MRE6786842 | BB66: Navdeep Rastogi, Syed Raza, Ram Shankar, Sidharth RaRitesh Chourasia, Bhavna Rajput, Anil Kumar Nandal, Ekta Rani, Pawan Kumar, Vaibhav Mishra, Kushpal Singh, Mohit Rathore | BC66: Sameer Dhar, Kunal Malhotra, Sanjeev Kumar, Ashutosh Gupta, Upanshu Bajaj | BD66: G.D.M. Management Services Pvt Ltd - Delhi | BE66: G.D.M. Management Services Pvt Ltd - Delhi - Delhi | BF66: G.D.M. Management Services Pvt Ltd - Delhi_Collection Agency_Delhi | BG66: G.D.M. Management Services Pvt Ltd - Delhi_Repo Agency_Delhi
A67: 66 | B67: Z21689 | C67: 26539 | D67: North | E67: Rajasthan | F67: Jaipur | G67: Collection & Repossession Agency | H67: A R Group - Jaipur | I67: Babita Choudhary | J67: Babita Choudhary / Satyander Choudhary | K67: 2Nd Floor, Saara Tower, Near Nursery Circle, Vaishali Nagar Jaipur - 302021 | L67: 0144-2702001 | M67: 0144-2702001,7412999557,7230020762 | N67: 9828559459 | O67: argroupalwar@gmail.com | P67: NA | Q67: AMAPC4791J | R67: 0 | S67: 08AMAPC4791J1ZZ | T67: 0 | U67: 0 | V67: YES BANK LIMITED | W67: 0 | X67: Properitoryship | Y67: Active | Z67: 43615 | AA67: 43613 | AB67: 0 | AC67: 0 | AD67: Panipat Location added on 27th Nov'23// Renewal agreement done 16th mar 26. | AE67: 26539 | AF67: A R Group | AG67: 595 | AH67: 685 | AI67: 753 | AJ67: 2033 | AK67: 1 | AL67: Allocaton given by Collection & Repossession | AM67: Eligible for audit | AN67: KGAC | AO67: Ashutosh Gupta | AP67: NA | AQ67: Not Audited | AR67: Visited the agency but audit not done due to agency is working for Yes Bank from their another branch, Address : 2nd floor, Saara Tower, Near Nursery Circle, Vaishali Nagar Jaipur - 302021 | AS67: NA | AT67: NA | AU67: NA | AV67: NA | AW67: NA | AX67: NA | AY67: Jaipur | AZ67: Rajasthan | BA67: PSE6778569, KDE6778345, SME5900019, KRE6769463, MCE6787677 | BB67: Pravesh Sharma, Kailash Devanda, Siddharth Maharishi, Kuldeep Rathore, Maya Choudhary | BC67: Ashutosh Gupta, Sameer Dhar | BD67: A R Group - Jaipur | BE67: NA | BF67: NA | BG67: NA
A68: 138 | B68: NA | C68: 189971 | D68: North | E68: Uttar Pradesh | F68: Agra | G68: Collection Agency | H68: Jmd Associates | I68: Arun Kumar Gupta | J68: Arun Kumar Gupta | K68: Flat No -705 , Prateek Center , Sanjay Palace Above Chai Sutta Bar Agra 282002 | L68: 7017936633 | M68: 7017936633 | N68: 7017936633 | O68: arun.gupta22041983@gmail.com | P68: NA | Q68: AQSPG4215B | S68: 09AQSPG4215B1Z1 | X68: Properitoryship | Y68: Active | Z68: 45448 | AA68: 45443 | AE68: 189971 | AF68: Jmd Associates | AG68: 47 | AH68: 45 | AI68: 292 | AJ68: 384 | AL68: Allocaton given by Collection agency | AM68: Eligible for audit | AN68: KGAC | AO68: NA | AP68: Flat No -705 , Prateek Center , Sanjay Palace Above Chai Sutta Bar Agra 282002 | AQ68: Audited | AR68: NA | AT68: Sarvesh Shukla | AU68: Chandan Sharma | AV68: 7753851136 | AW68: 46128 | AX68: Kumar Gaurav Agarwal & company | AY68: Agra | AZ68: Uttar Pradesh | BA68: RSE6763776, MRE6786842 | BB68: Ram Shankar, Mohit Rathore | BC68: Na | BD68: Jmd Associates | BE68: Jmd Associates - Agra - Uttar Pradesh | BF68: Jmd Associates_Collection Agency_Agra_Uttar Pradesh
A69: 166 | B69: NA | C69: 313994 | D69: North | E69: Uttar Pradesh | F69: Mainpuri | G69: Repossession Agency | H69: Gattu Brothers | I69: Bhupendra Singh | J69: Bhupendra Singh | K69: S/O Tilak Singh,Village, Mahuhar , Bhogaon Mainpuri,Up-205001 | L69: 9536352000 | M69: 9536352000 | N69: 9536352000 | O69: BHUPENDRAYADAV.522@GMAIL.COM | P69: NA | Q69: GSZPS9749M | S69: 09GSZPS9749M1ZW | V69: YES BANK LIMITED | X69: Properitoryship | Y69: Active | Z69: 45680 | AA69: 45679 | AD69: New Repossession project | AE69: 313994 | AF69: GATTU BROTHERS | AG69: NA | AH69: NA | AI69: NA | AJ69: NA | AK69: 2 | AL69: Allocaton given by Repo agency | AM69: Eligible for audit | AN69: KGAC | AO69: #N/A | AP69: S/O Tilak Singh,Village, Mahuhar , Bhogaon Mainpuri,Up-205001 | AQ69: Audited | AR69: NA | AT69: Pankaj Yadav | AU69: Chandan Sharma | AV69: 7753851136 | AW69: 46126 | AX69: Kumar Gaurav Agarwal & company | AY69: Mainpuri | AZ69: Uttar Pradesh | BA69: NA | BB69: Shyam Parkash, Vivek Kumar Shukla, Vivek Shukla, Sourabh Parihar, Sushim Kumar | BC69: Abhinav Lal, Sagar Pritishwar Choudhari, Sanjeev Kumar | BD69: Gattu Brothers | BE69: Gattu Brothers - Mainpuri - Uttar Pradesh | BF69: Gattu Brothers_Collection Agency_Mainpuri_Uttar Pradesh | BG69: Gattu Brothers_Repo Agency_Mainpuri_Uttar Pradesh
A70: 49 | B70: Z27277 | C70: 53931 | D70: North | E70: Punjab | F70: Chandigarh | G70: Collection & Repossession Agency | H70: Goodluck Associate | I70: Tararnpreet Kaur | J70: Tararnpreet Kaur | K70: Hig 43 Sec 48 C ,Mohali , Sco-122-123,1St Flor Phase 11 Mohali, Pin Code 160062 , Good Luck Associate Through Proprietor Taranveer Kaur ( Uid - 3775 2898 9758 ) W/O Amarjit Singh R/O Hig - 43 Sector - 48-C , Chandhigarh - 160062 | L70: 0172-3580181 | M70: 0172-3580181 | N70: 9041545500 | O70: GOODLUCK65D@GMAIL.COM | P70: GOODLUCK65D@GMAIL.COM | Q70: AUMPK5191L | R70: NA | S70: 03AUMPK5191L2Z8 | V70: HDFC BANK LTD | X70: Properitoryship | Y70: Active | Z70: 44811 | AA70: 44809 | AE70: 53931 | AF70: Goodluck Associate | AG70: 715 | AH70: 753 | AI70: 807 | AJ70: 2275 | AK70: 1 | AL70: Allocaton given by Collection & Repossession | AM70: Eligible for audit | AN70: KGAC | AO70: Ashutosh Gupta | AP70: Hig 43 Sec 48 C ,Mohali , Sco-122-123,1St Flor Phase 11 Mohali, Pin Code 160062 | AQ70: Audited | AR70: NA | AT70: Vartika Sharma | AU70: Aman Monga | AV70: 9990034588 | AW70: 46123 | AX70: Kumar Gaurav Agarwal & company | AY70: Chandigarh | AZ70: Punjab | BA70: SKE6777255, JBE6662016, PKE6446010, VKE6782576, JSE6784665, RRE6766563 | BB70: Sandeep Kumar, Jaspreet Bhathal, Parveen Kumar, Vikash Kumar, Jagmohan Singh, Rishu Raghuvanshi | BC70: Ashutosh Gupta, Sanjeev Kumar, Sameer Dhar, Pawan Rana | BD70: Goodluck Associate | BE70: Goodluck Associate - Chandigarh - Punjab | BF70: Goodluck Associate_Collection Agency_Chandigarh_Punjab | BG70: Goodluck Associate_Repo Agency_Chandigarh_Punjab
A71: 141 | B71: Yblv1129 | C71: 310994 | D71: North | E71: Delhi | F71: Delhi | G71: Collection Agency | H71: Jsr Consultant | I71: Jyoti Dhyani | J71: Jyoti Dhyani | K71: S-674 B Side F/F School Block Shakarpur Delhi-110092 | L71: 9899429228 | M71: 9899429228 | N71: 9899429228 | O71: Sohanlal@jsrconsultant.com; jsrconsultanty@gmail.com | P71: NA | Q71: BYGPD4089K | S71: 07BYGPD4089K1Z4 | X71: Properitoryship | Y71: Active | Z71: 45681 | AA71: 45679 | AE71: 310994 | AF71: JSR CONSULTANT | AG71: 452 | AH71: 361 | AI71: 573 | AJ71: 1386 | AL71: Allocaton given by Collection agency | AM71: Eligible for audit | AN71: KGAC | AO71: NA | AP71: S-674 B Side F/F School Block Shakarpur Delhi-110092 | AQ71: Audited | AR71: NA | AT71: Sohan / 9899429228 | AU71: Abhinav Khurana | AV71: 9217935065 | AW71: 46119 | AX71: Kumar Gaurav Agarwal & company | AY71: Delhi | AZ71: Delhi | BA71: SBE6782270, SPE6776273, SKE6774754, STE5844128, SKE6779366, RSE6776115, RAE6783127 | BB71: Subhajit Bhowmik, Sushant Parashar, Satendra Kumar, Sandeep Tyagi, Sumit Kumar, Rahul Sharma, Rittin Arya | BC71: NA | BD71: Jsr Consultant | BE71: Jsr Consultant - Delhi | BF71: Jsr Consultant_Collection Agency_Delhi
A72: 78 | B72: NA | C72: 318996 | D72: North | E72: Rajasthan | F72: Sikar | G72: Collection & Repossession Agency | H72: Govind Singh Gora | I72: Govind Singh Gora | J72: Govind Singh Gora | K72: First Floor Plot No 12 Near Manav City Jaipur Road, Opposite Sri Ram Transport Company Gokulpura Tiraha Sikar, Sikar, Rajasthan-332021 | L72: 9414037234 | M72: 9414037234 | N72: 9414037234 | O72: govindgora09@gmail.com | P72: NA | Q72: AFFPG1479P | S72: 08AFFPG1479P1ZY | V72: YES BANK LIMITED | X72: Properitoryship | Y72: Active | Z72: 45719 | AA72: 45715 | AE72: 318996 | AF72: Govind Singh Gora | AG72: NA | AH72: NA | AI72: NA | AJ72: NA | AK72: 4 | AL72: Allocaton given by Repo agency | AM72: Eligible for audit | AN72: KGAC | AO72: #N/A | AP72: First Floor Plot No 12 Near Manav City Jaipur Road, Opposite Sri Ram Transport Company Gokulpura Tiraha Sikar, Sikar, Rajasthan-332021 | AQ72: Audited | AR72: NA | AT72: Ashok Bagaria / 8005544510 | AU72: Akash Sharma | AV72: 7688959606 | AW72: 46118 | AX72: Kumar Gaurav Agarwal & company | AY72: Sikar | AZ72: Rajasthan | BA72: NA | BB72: Ashok Bagaria, Manpreet Singh, Shyam Parkash, Pushpendra Jangid | BC72: Vivek Joshi, Praveen Kumar Kurra, Sameer Dhar, Sanjeev Kumar | BD72: Govind Singh Gora | BE72: Govind Singh Gora - Sikar - Rajasthan | BF72: Govind Singh Gora_Collection Agency_Sikar_Rajasthan | BG72: Govind Singh Gora_Repo Agency_Sikar_Rajasthan
A73: 62 | B73: NA | C73: 310988 | D73: North | E73: Rajasthan | F73: Ajmer | G73: Collection & Repossession Agency | H73: Harshita Associates | I73: Ranveer Singh Rathore | J73: Ranveer Singh Rathore | K73: 112/10 Govind Bhawan, Opp. Savitri Girls School, Civil Lines Ajmer 305001 | L73: 9829383528 | M73: 9829383528 | N73: 9829383528 | O73: hassociates123@gmail.com | P73: NA | Q73: AAFFH4869P | S73: 08AAFFH4869P1ZK | V73: YES BANK LIMITED | X73: Partnership | Y73: Active | Z73: 45688 | AA73: 45685 | AD73: Addition for collection product on 22 Jan 26 | AE73: 310988 | AF73: Harshita Associates | AG73: 0 | AH73: 16 | AI73: 17 | AJ73: 33 | AK73: 2 | AL73: Allocaton given by Collection & Repossession | AM73: Eligible for audit | AN73: KGAC | AO73: Vivek Joshi | AP73: 112/10 Govind Bhawan, Opp. Savitri Girls School, Civil Lines Ajmer 305001 | AQ73: Audited | AR73: NA | AT73: Ranveer Singh Rathore / 9829383528 | AU73: Akash Sharma | AV73: 7688959606 | AW73: 46123 | AX73: Kumar Gaurav Agarwal & company | AY73: Ajmer | AZ73: Rajasthan | BA73: ATE6773431 | BB73: Ashish Tiwari | BC73: Vivek Joshi | BD73: Harshita Associates | BE73: Harshita Associates - Ajmer - Rajasthan | BF73: Harshita Associates_Collection Agency_Ajmer_Rajasthan | BG73: Harshita Associates_Repo Agency_Ajmer_Rajasthan
A74: 106 | B74: Z21820 | C74: 26212 | D74: East | E74: West Bengal | F74: Kolkata | G74: Collection & Repossession Agency | H74: Kalyani Associate - Kolkata | I74: Partha Sarthy Chatterjee | J74: Partha Sarthy Chatterjee / Satish Kumar | K74: Saltee Plaza,Room No 504,1 No Jessore Road,Gol Park, Kamar Danga,North Damdam West Bengal, Kolkata 700080 | L74: 8405900000,9204628789 | M74: 7903493400 6205830880 | N74: 7491016471 | O74: kalyaniassociates.jsr@gmail.com ; shubhankar.kalyaniassociates@gmail.com; kalyani.billing@gmail.com; kalyani.ybwoff@gmail.com; kalyaniassociates.jsr20@gmail.com; kalyani.ybmore@gmail.com; | P74: kalyaniyesbank.patna@gmail.com | Q74: ACMPC9882G | S74: 20ACMPC9882G2ZI | V74: HDFC BANK LTD | X74: Properitoryship | Y74: Active | Z74: 43489 | AA74: 43455 | AE74: 26212 | AF74: Kalyani Associate | AG74: 1392 | AH74: 1312 | AI74: 1130 | AJ74: 3834 | AK74: 2 | AL74: Allocaton given by Collection & Repossession | AM74: Eligible for audit | AN74: KGAC | AO74: Ashutosh Gupta | AP74: Saltee Plaza,Room No 504,1 No Jessore Road,Gol Park, Kamar Danga,North Damdam West Bengal, Kolkata 700080 | AQ74: Audited | AR74: Audited for Collection Only, as no activity of repossession are done from Kolkata branch | AT74: Rajib Halder | AU74: Vikky Kumar | AV74: 9354241930 | AW74: 46122 | AX74: Kumar Gaurav Agarwal & company | AY74: Kolkata | AZ74: West Bengal | BA74: AKE6777646, SDE6781658, SPE6753711, KBE6776090, ASE6778477, AME6761288, AME6777270, PKE6762328, PYE6778749, CJE6782046, KME6780756, ASE6777499, STE6769262, PME6771779, ASE5641009 | BB74: Ashit Kumar, Sujoy Das, Subhakanta Panda, Kalpataru Baishakh, Amit Singh, Md Azharuddin, Avdesh Mishra, Prabhakar Kumar, Pankaj Yadav, Choudhury JeKiran Mohapatra, Arindam Sarkar, Santosh Thakur, Priyanka Mondal | BC74: Ashutosh Gupta, Subhasis Banerjee | BD74: Kalyani Associate - Kolkata | BE74: Kalyani Associate - Kolkata - West Bengal | BF74: Kalyani Associate - Kolkata_Collection Agency_West Bengal
A75: 87 | B75: Z27852 | C75: 53909 | D75: North | E75: Uttar Pradesh | F75: Lucknow | G75: Collection & Repossession Agency | H75: Kk Associates | I75: Kaushal Kumar Verma | J75: Kaushal Kumar Verma | K75: Durgma Tower, 2Nd Floor, 125/06 , Queenton Road, Lalbagh , Lucknow Uttar Pradesh- 226001 | L75: 9838693930 | M75: 9838693930 | N75: 9838693930 | O75: KKVERMA2008@GMAIL.COM; kkassociate2002@gmail.com | P75: NA | Q75: ACEPV6796J | S75: 09ACPPV6796J1ZM | V75: HDFC BANK LTD | X75: Properitoryship | Y75: Active | Z75: 44905 | AA75: 44904 | AE75: 53909 | AF75: KK Associates | AG75: 273 | AH75: 238 | AI75: 196 | AJ75: 707 | AL75: Allocaton given by Collection & Repossession | AM75: Eligible for audit | AN75: KGAC | AO75: Abhinav Lal | AP75: Durgma Tower, 2Nd Floor, 125/06 , Queenton Road, Lalbagh , Lucknow Uttar Pradesh- 226001 | AQ75: Audited | AR75: Audited for Collection Only, as no activity of repossession are done for the audit quarter | AT75: Divyansh Verma - 9559897603 | AU75: Hariom Sharma | AV75: 9810670823 | AW75: 46127 | AX75: Kumar Gaurav Agarwal & company | AY75: Lucknow | AZ75: Uttar Pradesh | BA75: DSE6786366, SCE6722048, ASE5322056, DAE6777331 | BB75: Dheerendra Singh, Sachin Chauhan, Ashish Kumar Shukla, Devendra Asthana | BC75: Abhinav Lal | BD75: Kk Associates | BE75: Kk Associates - Lucknow - Uttar Pradesh | BF75: Kk Associates_Collection Agency_Lucknow_Uttar Pradesh
A76: 154 | B76: Z14993 | C76: 24908 | D76: North | E76: Haryana | F76: Karnal | G76: Collection/Pickup/Repo Agency | H76: I Care Securities | I76: Tarun Madan & Ivneet Kaur | J76: Tarun Madan & Ivneet Kaur | K76: Sco-18/181, Gokul Market, Civil Hospital Chowk, Karnal - 132001 | L76: 9053100002,7404380000,0184-4031900 | M76: 9053100002,7404380000,0184-4031900,9221321000,8574321000,9215921000 | N76: 9215921000 | O76: icare@icsk.co.in | P76: icaresecurities54@gmail.com | Q76: AAEFI6927L | S76: 06AJUPM7978A1ZN | U76: 16885800001770 | V76: YES BANK LIMITED | W76: OPENED | X76: Partnership | Y76: Active | Z76: 42782 | AA76: 42762 | AE76: 24908 | AF76: I Care Securities | AG76: 876 | AH76: 802 | AI76: 740 | AJ76: 2418 | AK76: 13 | AL76: Allocaton given by Collection & Repossession | AM76: Eligible for audit | AN76: KGAC | AO76: NA | AP76: Sco-18/181, Gokul Market, Civil Hospital Chowk, Karnal - 132001 | AQ76: Audited | AR76: NA | AT76: Savita | AU76: Aman Monga | AV76: 9990034588 | AW76: 46130 | AX76: Kumar Gaurav Agarwal & company | AY76: Karnal | AZ76: Haryana | BA76: KSE6769063, SSE6775469, VKE6782576, ANE5784049, PKE6779360, SRE6782838, RKE6218030, SSE6748795, KKE6765046 | BB76: Kushpal Singh, Sukhwinder Singh, Vikash Kumar, Anil Kumar Nandal, Pawan Kumar, Sidharth RaRavi Kant, Sukhwant Singh, Kapil Kumar | BC76: Sameer Dhar, Sanjeev Kumar, Pawan RaVineet Kumar | BD76: I Care Securities | BE76: I Care Securities - Karnal - Haryana | BF76: I Care Securities_Collection Agency_Karnal_Haryana | BG76: I Care Securities_Repo Agency_Karnal_Haryana
A77: 116 | B77: Z24041 | C77: 26478 | D77: North | E77: Delhi | F77: Delhi | G77: Collection Agency | H77: Krishnapriya Credit Management Services (P) Ltd | I77: Arneb Debashish Nanad / Sandeep Singh Negi | J77: Sandeep Singh Negi | K77: 301,302,305,306,Guru Arjun Dev Bhawan,Ranjeet Nagar,Commerccial Complex,Shadipur-110008 | L77: 1143012829,9711772121 | M77: 1143012829,9711772121,8800234205,8799786652,8527237397,8586975614,9560665401,8802098998 , 7303919511 | N77: 9711772121,8010982083 | O77: Rahul.arora@kpcmservices.com; kpcmservicesyes@gmail.com | P77: NA | Q77: AABCD5960C | S77: AABCD5960CST001 | X77: PVT Ltd | Y77: Active | Z77: 44033 | AA77: 44022 | AD77: Mail id change req rec in Nov21 ,address change req received in 7th Dec 21. | AE77: 26478 | AF77: KRISHNAPRIYA CREDIT MANAGEMENT SERVICES (P) LTD | AG77: 838 | AH77: 811 | AI77: 770 | AJ77: 2419 | AL77: Allocaton given by Collection agency | AM77: Eligible for audit | AN77: KGAC | AO77: Kunal Malhotra | AP77: 301,302,305,306,Guru Arjun Dev Bhawan,Ranjeet Nagar,Commerccial Complex,Shadipur-110008 | AQ77: Audited | AR77: NA | AT77: Rahul Arora | AU77: Rahul Verma | AV77: 9354183359 | AW77: 45763 | AX77: Kumar Gaurav Agarwal & company | AY77: Delhi | AZ77: Delhi | BA77: HBE6784419, RSE6778024, ASE6749478, VJE6777344, NTE6776994, RPE6777552 | BB77: Hemant Bajaj, Rinki Sharma, Ashvini Sharma, Vikashbhai Joshi, Neelesh Tiwari, Robin Pachchigar | BC77: Kunal Malhotra, Rajnish Dwivedi, Upanshu Bajaj | BD77: Krishnapriya Credit Management Services (P) Ltd | BE77: Krishnapriya Credit Management Services (P) Ltd - Delhi | BF77: Krishnapriya Credit Management Services (P) Ltd_Collection Agency_Delhi
A78: 128 | B78: Z24038 | C78: 26177 | D78: East | E78: Jharkhand | F78: Ranchi | G78: Collection Agency | H78: Kuber Consultants | I78: Uday Kumar Batter | J78: Uday Kumar Batter/Aman Nagpal | K78: 1St Floor , Quarter No-48/C , Road No 1 , Ashok Nagar , Doranda , Ranchi , Jharkhand- 834002 | L78: 9.71121399311493E+29 | M78: 9.711214e+89 | N78: 9711213993,1149385012 | O78: udaybhatter@kuberconsultants.com;aman.nagpal@kuberconsultants.com | P78: NA | Q78: AEQPB4106A | S78: 07AEQPB4106A2Z4 | X78: Properitoryship | Y78: Active | Z78: 44025 | AA78: 44025 | AE78: 26177 | AF78: Kuber Consultants | AG78: 187 | AH78: 398 | AI78: 395 | AJ78: 980 | AL78: Allocaton given by Collection agency | AM78: Eligible for audit | AN78: KGAC | AO78: Ashutosh Gupta | AP78: 1St Floor , Quarter No-48/C , Road No 1 , Ashok Nagar , Doranda , Ranchi , Jharkhand- 834002 | AQ78: Audited | AR78: NA | AT78: Rohit | AU78: Vikky Kumar | AV78: 9354241930 | AW78: 46130 | AX78: Kumar Gaurav Agarwal & company | AY78: Ranchi | AZ78: Jharkhand | BA78: STE6769262, AKE6777646, PYE6778749, CJE6782046, AME6777270 | BB78: Santosh Thakur, Ashit Kumar, Pankaj Yadav, Choudhury JeAvdesh Mishra | BC78: Ashutosh Gupta | BD78: Kuber Consultants | BE78: Kuber Consultants - Ranchi - Jharkhand | BF78: Kuber Consultants_Collection Agency_Ranchi_Jharkhand
A79: 9 | B79: Z23173 | C79: 26489 | D79: East | E79: Chhattisgarh | F79: Raipur | G79: Collection & Repossession Agency | H79: Infinity Services | I79: Ayesha Begam | J79: Varsha Vani/ Imran Charania / Mohd. Israr | K79: Hig/C-21, Sector - 1, Devendra Nagar, Raipur (C.G.) 492001. | L79: 0771-6750525 | M79: 0771-6750525,9755513130,6263682918,9630294540,8839566523,9516003738 | N79: 8370066666,9755513130,8517992526,9669940300 | O79: infinityservices@infiserve.com | P79: NA | Q79: AUWPB2567M | S79: 22AUWPB2567M2Z7 | V79: UNION BANK OF INDIA | X79: Properitoryship | Y79: Active | Z79: 43829 | AA79: 43829 | AD79: Mail change req recd on Sept 21 | AE79: 26489 | AF79: Infinity Services | AG79: 1155 | AH79: 1095 | AI79: 1128 | AJ79: 3378 | AK79: 6 | AL79: Allocaton given by Collection & Repossession | AM79: Eligible for audit | AN79: KGAC | AO79: Abhijeet Kashid | AP79: Hig/C-21, Sector - 1, Devendra Nagar, Raipur (C.G.) 492001. | AQ79: Audited | AR79: NA | AT79: Mohammed Rizwan (7509634823) | AU79: Parteek Yadav | AV79: 7460008081 | AW79: 46126 | AX79: Kumar Gaurav Agarwal & company | AY79: Raipur | AZ79: Chhattisgarh | BA79: VUE6755300, LVE6783252, ASE6778431, MKE6775854, SME6345002, RQE6781542, MKE6467020, NME6765631 | BB79: Vikram Upadhyay, Lokesh Vadaskar, Avtar Singh, Manoj Kumar, Sudarshan Maddu, Rizwan Quraishi, Nikunj Mohod | BC79: Amar Gupte, Abhijeet Kashid, Subhasis Banerjee, Biswarup Ghosh, Saurabh Chaturvedi, Md Shabbir Alam, Ashutosh Gupta | BD79: Infinity Services | BE79: Infinity Services - Raipur - Chhattisgarh | BF79: Infinity Services_Collection Agency_Raipur_Chhattisgarh | BG79: Infinity Services_Repo Agency_Raipur_Chhattisgarh
A80: 41 | B80: NA | C80: 351020 | D80: East | E80: Odisha | F80: Cuttack | G80: Collection & Repossession Agency | H80: M C Associate | I80: Rinarani Mohanty | J80: Rinarani Mohanty | K80: Plot No-244, Atnuapada, Po/Ps – Madhupatna, Cuttack, 753010 | L80: 9861023511 | M80: 9861023511 | N80: 9861023511 | O80: rinaranimohanty1@gmail.com | P80: NA | Q80: EXWPM4699Q | S80: 21EXWPM4699Q1Z4 | X80: Properitoryship | Y80: Active | Z80: 45867 | AA80: 45866 | AE80: 351020 | AF80: M C ASSOCIATE | AG80: 490 | AH80: 564 | AI80: 596 | AJ80: 1650 | AL80: Allocaton given by Collection agency | AM80: Eligible for audit | AN80: KGAC | AO80: Ashutosh Gupta | AP80: Plot No-244, Atnuapada, Po/Ps – Madhupatna, Cuttack, 753010 | AQ80: Audited | AR80: NA | AT80: Bhagyalaxmi | AU80: Vikky Kumar | AV80: 9354241930 | AW80: 46125 | AX80: Kumar Gaurav Agarwal & company | AY80: Cuttack | AZ80: Odisha | BA80: KBE6776090, KME6780756, AME6777270, CJE6782046 | BB80: Kalpataru Baishakh, Kiran Mohapatra, Avdesh Mishra, Choudhury Jena | BC80: Ashutosh Gupta | BD80: M C Associate | BE80: M C Associate - Cuttack - Odisha | BF80: M C Associate_Collection Agency_Cuttack_Odisha
A81: 65 | B81: Z15421 | C81: 25659 | D81: North | E81: Rajasthan | F81: Bikaner | G81: Collection & Repossession Agency | H81: Maa Bhawani Auto Enterprises | I81: Lokendar Bhatti | J81: Lokendar Bhatti | K81: A 9 Near Sbbj Bank Ignp Colony Bikaner Rajasthan | L81: 0151-2250356 | M81: 0151-2250356,9772043342 | N81: 9950002150 | O81: maabhawaniautoenterprises@gmail.com | P81: NA | Q81: ATJPB6991K | R81: ANPPC7352RSD001 | S81: 08ATJPB6991K1Z5 | U81: 052961900001494 | V81: YES BANK LIMITED | W81: OPENED | X81: Properitoryship | Y81: Active | Z81: 42877 | AA81: 42875 | AD81: Supplimental agreement done for Repo activity on Mar22. | AE81: 25659 | AF81: Maa Bhawani Auto Enterprises | AG81: 315 | AH81: 328 | AI81: 334 | AJ81: 977 | AL81: Allocaton given by Collection agency | AM81: Eligible for audit | AN81: KGAC | AO81: NA | AP81: A 9 Near Sbbj Bank Ignp Colony Bikaner Rajasthan | AQ81: Audited | AR81: NA | AT81: Jai Kumar Sharma / 9694906891 | AU81: Akash Sharma | AV81: 7688959606 | AW81: 46119 | AX81: Kumar Gaurav Agarwal & company | AY81: Bikaner | AZ81: Rajasthan | BA81: DBE6783560 | BB81: Dilip Bhati | BC81: Na | BD81: Maa Bhawani Auto Enterprises | BE81: Maa Bhawani Auto Enterprises - Bikaner - Rajasthan | BF81: Maa Bhawani Auto Enterprises_Collection Agency_Bikaner_Rajasthan
A82: 15 | B82: Z14974 | C82: 26166 | D82: North | E82: Delhi | F82: Delhi | G82: Collection & Repossession Agency | H82: Management Services | I82: Sunil Diwan | J82: Sunil Diwan | K82: B-138.3Rd Floor Navakar Building, Mohammad Pur New Delhi 110066 | L82: 35123776,35123772,66158639,40,3512786 | M82: 35123776,35123772,66158639,40-3512786,9899360123,9718723789,9871879487,9582230927,9350190024,9953755991,9818240991,9312064006,9654740745,9811580172,8920176622,9899093934,9268423754,9266616666,9315587290,8851340325,9717176805,9319141157,9717116496,9718562973,9873387576,7217757411,8130371073,9210040404,9560038050 | N82: 9811434904 | O82: Manav@managementser.com; hr@mser.co.in | P82: Manav@managementser.com; hr@mser.co.in | Q82: AAHPD9211D | R82: AAHPD9211DST001 | S82: 07AAHPD9211D2Z5 | U82: 033885800000130 | V82: BANK OF BARODA | W82: OPENED | X82: Properitoryship | Y82: Active | Z82: 42619 | AA82: 42608 | AD82: Mail id change req recd in Jul/Repo activity added in May22. | AE82: 26166 | AF82: Management Services | AG82: 1760 | AH82: 1707 | AI82: 1552 | AJ82: 5019 | AL82: Allocaton given by Collection agency | AM82: Eligible for audit | AN82: KGAC | AO82: Abhinav Lal | AP82: B-138.3Rd Floor Navakar Building, Mohammad Pur New Delhi 110066 | AQ82: Audited | AR82: NA | AT82: Rajesh Rohil : 9873954912 | AU82: Hariom Sharma | AV82: 9810670823 | AW82: 46134 | AX82: Kumar Gaurav Agarwal & company | AY82: Delhi | AZ82: Delhi | BA82: GME6718001, NKE6775741, KKE6776767, SKE6779366, PGE6777921, DSE6786366, RPE6784768, RSE6776115, GKE6784579, STE5844128, MFE6778570, VGE6773224, RAE6783127, SPE6776273 | BB82: Gaurav Mishra, Nitin Kumar, Kunwar Kumar Singh, Sumit Kumar, Priyanka Gupta, Dheerendra Singh, Ravi Parkash, Rahul Sharma, Gopal Khatri, Sandeep Tyagi, Md Faizullah, Vishal Gupta, Rittin Arya, Sushant Parashar | BC82: Sameer Dhar, Abhinav Lal | BD82: Management Services | BE82: Management Services - Delhi | BF82: Management Services_Collection Agency_Delhi
A83: 105 | B83: Yblv1117 | C83: 303020 | D83: East | E83: West Bengal | F83: Kolkata | G83: Collection & Repossession Agency | H83: J K Associate | I83: Masud Akhtar | J83: Masud Akhtar | K83: 50 A, Naba Mohajati Road, Dumdum 700028 | L83: 6296905422 | M83: 6296905422 | N83: 6296905422 | O83: jk.associate2024@gmail.com | P83: kol.collection@jkassociate.co.in | Q83: AAUFJ1133F | S83: 19AAUFJ1133F1ZA | V83: YES BANK LIMITED | X83: Partnership | Y83: Active | Z83: 45622 | AA83: 45622 | AD83: New Repossession project | AE83: 303020 | AF83: J K ASSOCIATE | AG83: 389 | AH83: 286 | AI83: 385 | AJ83: 1060 | AL83: Allocaton given by Collection & Repossession | AM83: Eligible for audit | AN83: KGAC | AO83: Biswarup Ghosh | AP83: 68/A Jessore Road, Dumdum, North 24 Parganas, 700028 | AQ83: Audited | AR83: NA | AT83: Masud Aktar | AU83: Pradeep | AV83: 8287823681 | AW83: 46132 | AX83: Kumar Gaurav Agarwal & company | AY83: Kolkata | AZ83: West Bengal | BA83: SME6781177, SDE6778568, RBE6757282, TSE6288042, DSE6782069 | BB83: Sudip ManSuman Das, Ritam Basak, Tarkeshwar Singh, Deepak Singh | BC83: Biswarup Ghosh | BD83: J K Associate | BE83: J K Associate - Kolkata - West Bengal | BF83: J K Associate_Collection Agency_Kolkata_West Bengal | BG83: J K Associate_Repo Agency_Kolkata_West Bengal
A84: 164 | B84: NA | C84: 355004 | D84: North | E84: Delhi | F84: Delhi | G84: Repossession Agency | H84: Jbms Associates | I84: Syed Saad Ali | J84: Syed Saad Ali | K84: Flat No 350/351 Pocket 1 Sector 6A, Second Floor Dda Flat , Jagriti Appartment Narela Delhi 110040 | L84: 9911639094 | M84: 9911639094 | N84: 9911639094 | O84: jbmsassociates@gmail.com | P84: NA | Q84: BHPPA4526G | S84: 07BHPPA4526G1ZG | X84: Properitoryship | Y84: Active | Z84: 45872 | AA84: 45872 | AD84: New Repossession project | AE84: 355004 | AF84: JBMS ASSOCIATES | AG84: NA | AH84: NA | AI84: NA | AJ84: NA | AK84: 3 | AL84: Allocaton given by Repo agency | AM84: Eligible for audit | AN84: KGAC | AO84: #N/A | AP84: Flat No 350/351 Pocket 1 Sector 6A, Second Floor Dda Flat , Jagriti Appartment Narela Delhi 110040 | AQ84: Audited | AR84: NA | AT84: Syad / 9911639094 | AU84: Abhinav Khurana | AV84: 9217935065 | AW84: 46136 | AX84: Kumar Gaurav Agarwal & company | AY84: Delhi | AZ84: Delhi | BA84: NA | BB84: Shyam Parkash, Gaurav Mishra, Nitesh Madhavi, Vivek Shukla, Abhinav Lal | BC84: Abhinav Lal, Sagar Pritishwar Choudhari, Sameer Dhar, Biswarup Ghosh | BD84: Jbms Associates | BE84: Jbms Associates - Delhi | BF84: Jbms Associates_Collection Agency_Delhi | BG84: Jbms Associates_Repo Agency_Delhi
A85: 127 | B85: Z21525 | C85: 26458 | D85: North | E85: Jammu | F85: Jammu | G85: Collection Agency | H85: Jk Corporate Pvt Ltd | I85: Ajay Kumar Gupta/ Shakuntla Gupta | J85: Ajay Kumar Gupta/ Shakuntla Gupta | K85: 23/2, Trikuta Nagar, Jammu-180020 | L85: 0191-2470826 | M85: 0191-2470826,8082396895,9906134244 | N85: 9419185745 | O85: ajaykgupta76@rediffmail.com;jkcs.krish@gmail.com | P85: jkcs.krish@gmail.com | Q85: AACCJ6559L | S85: DECLARATION | X85: PVT Ltd | Y85: Active | Z85: 43500 | AA85: 43395 | AE85: 26458 | AF85: JK Corporate PVT LTD | AG85: 734 | AH85: 735 | AI85: 731 | AJ85: 2200 | AK85: 1 | AL85: Allocaton given by Collection & Repossession | AM85: Eligible for audit | AN85: KGAC | AO85: Ashutosh Gupta | AP85: 23/2, Trikuta Nagar, Jammu-180020 | AQ85: Audited | AR85: NA | AT85: Ajay Gupta | AU85: Rahul Verma | AV85: 9354183359 | AW85: 46136 | AX85: Kumar Gaurav Agarwal & company | AY85: Jammu | AZ85: Jammu | BA85: VSE6762677, VKE6782576, JBE6662016, KSE6769063, RRE6766563 | BB85: Vikram Singh, Vikash Kumar, Jaspreet Bhathal, Kushpal Singh, Rishu Raghuvanshi | BC85: Sameer Dhar, Sanjeev Kumar, Ashutosh Gupta, Pawan Rana | BD85: Jk Corporate Pvt Ltd | BE85: Jk Corporate Pvt Ltd - Jammu | BF85: Jk Corporate Pvt Ltd_Collection Agency_Jammu | BG85: Jk Corporate Pvt Ltd_Repo Agency_Jammu
A86: 146 | B86: Z26085 | C86: 13052 | D86: North | E86: Uttar Pradesh | F86: Meerut | G86: Collection Agency | H86: Meerut Collection Centre | I86: Kalwa Khan Tyagi | J86: Kalwa Khan Tyagi | K86: 17/8 Shastri Nagar Meerut Uttar Pradesh- 250004 | L86: 9719020130 | M86: 9719020130,8477874056,8445350022 | N86: 9719020130 | O86: MCC.YES@REDIFFMAIL.COM;meerutcollectioncenter@rediffmail.com | P86: KKTYAGI786@REDIFFMAIL.COM | Q86: ACGPT1366G | S86: 09ACGPT1366G3ZB | X86: Properitoryship | Y86: Active | Z86: 44589 | AA86: 44588 | AE86: 13052 | AF86: Meerut Collection Centre | AG86: 58 | AH86: 53 | AI86: 61 | AJ86: 172 | AL86: Allocaton given by Collection agency | AM86: Eligible for audit | AN86: KGAC | AO86: Abhinav Lal | AP86: 17/8 Shastri Nagar Meerut Uttar Pradesh- 250004 | AQ86: Audited | AR86: NA | AT86: Ak Tyagi / 9719020130 | AU86: Abhinav Khurana | AV86: 9217935065 | AW86: 46130 | AX86: Kumar Gaurav Agarwal & company | AY86: Meerut | AZ86: Uttar Pradesh | BA86: HKE6745350, DAE6777331 | BB86: Hayat Kathayat, Devendra Asthana | BC86: Abhinav Lal, Sanjeev Kumar, Rohit Nijhawan, Sameer Dhar | BD86: Meerut Collection Centre | BE86: Meerut Collection Centre - Meerut - Uttar Pradesh | BF86: Meerut Collection Centre_Collection Agency_Meerut_Uttar Pradesh
A87: 121 | B87: NA | C87: 355991 | D87: North | E87: Delhi | F87: Delhi | G87: Collection Agency | H87: Mf Services Private Limited | I87: Mr. Somnath, Mr. Amit Mohendru And Ms, Geeta | J87: Mr. Somnath, Mr. Amit Mohendru And Ms, Geeta | K87: P.No. - 26A, Khasra No. 5/15, Block-B, Patel Garden,Uttam Nagar, Near Kakrola Road, New Delhi-110059 | L87: 7982253393 , 9555570084 , 9643940105 | M87: 7982253393 , 9555570084 , 9643940105 | N87: 7982253393 , 9555570084 , 9643940105 | O87: operations@mfplindia.in | P87: NA | Q87: AAOCM4700E | S87: 07AAOCM4700E1ZN | X87: Company | Y87: Active | Z87: 45868 | AA87: 45868 | AE87: 355991 | AF87: MF Services Private Limited | AG87: 407 | AH87: 392 | AI87: 489 | AJ87: 1288 | AL87: Allocaton given by Collection agency | AM87: Eligible for audit | AN87: KGAC | AO87: NA | AP87: P.No. - 26A, Khasra No. 5/15, Block-B, Patel Garden,Uttam Nagar, Near Kakrola Road, New Delhi-110059 | AQ87: Audited | AR87: NA | AT87: Ajay Kumar/7217827969 | AU87: Abhinav Khurana | AV87: 9217935065 | AW87: 46118 | AX87: Kumar Gaurav Agarwal & company | AY87: Delhi | AZ87: Delhi | BA87: JSE6785583, AKE6778416 | BB87: Jay Shukla, Amit Kumar | BC87: NA | BD87: Mf Services Private Limited | BE87: Mf Services Private Limited - Delhi | BF87: Mf Services Private Limited_Collection Agency_Delhi
A88: 171 | B88: Z24039 | C88: 24651 | D88: East | E88: Odisha | F88: Khurda | G88: Repossession Agency | H88: Jyotirmay Sasmal | I88: Jyotirmay Sasmal | J88: Jyotirmay Sasmal/Priti Mohapatra | K88: 119/G, Sec - A, Zone - A, Mancheswar Industrial Estate Khordha, Odisha 751010 | L88: 9861200001 9090500000 | M88: 9861200001,9090535455 | N88: 9861200001 | O88: jyotirmaysasmal@gmail.com;mpritiprakash@gmail.com | P88: NA | Q88: BCIPS7898P | S88: 21BCIPS7898P2ZG | V88: YES BANK LIMITED | X88: Properitoryship | Y88: Active | Z88: 44004 | AA88: 44004 | AE88: 24651 | AF88: Jyotirmay Sasmal | AG88: NA | AH88: NA | AI88: NA | AJ88: NA | AK88: 2 | AL88: Allocaton given by Repo agency | AM88: Eligible for audit | AN88: KGAC | AO88: #N/A | AP88: 119/G, Sec - A, Zone - A, Mancheswar Industrial Estate Khordha, Odisha 751010 | AQ88: Audited | AR88: NA | AT88: Bhupati Bhusan Maharana | AU88: Vikky Kumar | AV88: 9354241930 | AW88: 46126 | AX88: Kumar Gaurav Agarwal & company | AY88: Khurda | AZ88: Odisha | BA88: NA | BB88: Suryanarayan Nayak, Santosh Kumar Sharma, Nitesh Ramchandra Madhavi, Arindam Sarkar, Suryakanta JeManikandan G | BC88: Biswarup Ghosh, Sagar Pritishwar Choudhari, Subhasis Banerjee, Rajnish Dwivedi | BD88: Jyotirmay Sasmal | BE88: Jyotirmay Sasmal - Khurda - Odisha | BF88: Jyotirmay Sasmal_Collection Agency_Khurda_Odisha | BG88: Jyotirmay Sasmal_Repo Agency_Khurda_Odisha
A89: 4 | B89: Yblv1107 | C89: 298994 | D89: East | E89: Assam | F89: Guwahati | G89: Collection & Repossession Agency | H89: Namanshee Associates | I89: Ritupan Kalita | J89: Ritupan Kalita | K89: Bora Market Market R.G.B Road , Borah Market Complex,1 St Floor, Near Assam State Zoo, Guwahati, Assam-781005 | L89: 7002910347 | M89: 7002910347 | N89: 7002910347 | O89: ritupankalita1987@gmail.com | P89: NA | Q89: BAXPK0621B | S89: 18BAXPK0621B1ZV | V89: YES BANK LIMITED | X89: Proprietorship | Y89: Active | Z89: 45602 | AA89: 45600 | AD89: New Repossession project | AE89: 298994 | AF89: NAMANSHEE ASSOCIATES | AG89: 65 | AH89: 81 | AI89: 59 | AJ89: 205 | AL89: Allocaton given by Collection agency | AM89: Eligible for audit | AN89: KGAC | AO89: Ashutosh Gupta | AP89: Impereal Uzan Bazzar Flat No-3-B-Third Floor Commercial M.C.Road Uzan Bazar | AQ89: Audited | AR89: NA | AT89: Ritupan Kalita | AU89: Pradeep | AV89: 8287823681 | AW89: 46130 | AX89: Kumar Gaurav Agarwal & company | AY89: Guwahati | AZ89: Assam | BA89: NDE6765957, RPE6775155 | BB89: Nayanjyoti Deka, Rakesh Pathak | BC89: Ashutosh Gupta | BD89: Namanshee Associates | BE89: Namanshee Associates - Guwahati - Assam | BF89: Namanshee Associates_Collection Agency_Guwahati_Assam
A90: 43 | B90: Z21820 | C90: 26212 | D90: East | E90: Odisha | F90: Bhubaneshwar | G90: Collection & Repossession Agency | H90: Kalyani Associate - Bhubaneshwar | I90: Partha Sarthy Chatterjee | J90: Partha Sarthy Chatterjee / Satish Kumar | K90: Plot No 734, Ratha Road, Barik Sahi, Ward No 54, Khorda, Bhubhneshwar Odisha-751002 | L90: 8405900000,9204628789 | M90: 7903493400 6205830880 | N90: 7491016471 | O90: kalyaniassociates.jsr@gmail.com ; shubhankar.kalyaniassociates@gmail.com; kalyani.billing@gmail.com; kalyani.ybwoff@gmail.com; kalyaniassociates.jsr20@gmail.com; kalyani.ybmore@gmail.com; | P90: kalyaniyesbank.patna@gmail.com | Q90: ACMPC9882G | S90: 20ACMPC9882G2ZI | V90: HDFC BANK LTD | X90: Properitoryship | Y90: Active | Z90: 43489 | AA90: 43455 | AE90: 26212 | AF90: Kalyani Associate | AG90: 1392 | AH90: 1312 | AI90: 1130 | AJ90: 3834 | AK90: 2 | AL90: Allocaton given by Collection & Repossession | AM90: Eligible for audit | AN90: KGAC | AO90: Ashutosh Gupta | AP90: Plot No 734, Ratha Road, Barik Sahi, Ward No 54, Khorda, Bhubhneshwar Odisha-751002 | AQ90: Audited | AR90: NA | AT90: Tinku Sonkar | AU90: Pradeep | AV90: 8287823681 | AW90: 46134 | AX90: Kumar Gaurav Agarwal & company | AY90: Bhubaneshwar | AZ90: Odisha | BA90: AKE6777646, SDE6781658, SPE6753711, KBE6776090, ASE6778477, AME6761288, AME6777270, PKE6762328, PYE6778749, CJE6782046, KME6780756, ASE6777499, STE6769262, PME6771779, ASE5641009 | BB90: Ashit Kumar, Sujoy Das, Subhakanta Panda, Kalpataru Baishakh, Amit Singh, Md Azharuddin, Avdesh Mishra, Prabhakar Kumar, Pankaj Yadav, Choudhury JeKiran Mohapatra, Arindam Sarkar, Santosh Thakur, Priyanka Mondal | BC90: Ashutosh Gupta, Subhasis Banerjee | BD90: Kalyani Associate - Bhubaneshwar | BE90: Kalyani Associate - Bhubaneshwar - Odisha | BF90: Kalyani Associate - Bhubaneshwar_Collection Agency_Odisha | BG90: Kalyani Associate - Bhubaneshwar_Repo Agency_Odisha
A91: 70 | B91: Z18638 | C91: 25785 | D91: North | E91: Rajasthan | F91: Jaipur | G91: Collection & Repossession Agency | H91: National Consultants | I91: Kailash Singh Chouhan | J91: Kailash Singh Chouhan | K91: 139, K-5-C Scheme, Khatipura, Jaipur - 302012 | L91: 0141-2359541,9829053749,8005659049,0141-2350756 | M91: 0141-2359541,9829053749,8005659049,0141-2350756,9636323880,9694345351,9783009893 | N91: 9829053749 | O91: national.ks@gmail.com ; info.yb@nationalconsultants.co.in ; Nationalconsultants749@gmail.com | P91: nationalyesbank@gmail.com | Q91: ADPPC4913N | R91: ADPPC4913ND001 | S91: 08ADPPC4913N1Z7 | V91: YES BANK LIMITED | X91: Properitoryship | Y91: Active | Z91: 42934 | AA91: 42928 | AD91: Address chanes request recd on 2nd Jul | AE91: 25785 | AF91: National Consultants | AG91: 153 | AH91: 169 | AI91: 158 | AJ91: 480 | AL91: Allocaton given by Collection agency | AM91: Eligible for audit | AN91: KGAC | AO91: NA | AP91: 139, K-5-C Scheme, Khatipura, Jaipur - 302012 | AQ91: Audited | AR91: NA | AT91: Pradeep Kumar Yadav / 6377663047 | AU91: Akash Sharma | AV91: 7688959606 | AW91: 46125 | AX91: Kumar Gaurav Agarwal & company | AY91: Jaipur | AZ91: Rajasthan | BA91: KRE6769463 | BB91: Kuldeep Rathore | BC91: Na | BD91: National Consultants | BE91: National Consultants - Jaipur - Rajasthan | BF91: National Consultants_Collection Agency_Jaipur_Rajasthan
A92: 117 | B92: Z24042 | C92: 26232 | D92: North | E92: Delhi | F92: Delhi | G92: Collection Agency | H92: Oxford Management Services | I92: Sushant Sharma | J92: Sushant Sharma | K92: 1/50/2/71, 2Nd Floor Lalita Park Laxmi Nagar Delhi 110092 | L92: 8375826872,8375800000 | M92: 8929260290/8929259886/ 8929037581/ 8929037581/892960290 | N92: 9953472139 | O92: sushant.sharma@oxfords.co.in | P92: NA | Q92: BRFPS0765K | S92: 07BRFPS0765KIZD | X92: Properitoryship | Y92: Active | Z92: 44099 | AA92: 44097 | AD92: Contact# changed req recd in Oct21 | AE92: 26232 | AF92: Oxford Management Services | AG92: 2181 | AH92: 1859 | AI92: 2073 | AJ92: 6113 | AL92: Allocaton given by Collection agency | AM92: Eligible for audit | AN92: KGAC | AO92: Abhinav Lal | AP92: 1/50/2/71, 2Nd Floor Lalita Park Laxmi Nagar Delhi 110092 | AQ92: Audited | AR92: NA | AT92: Suhshant Sharma | AU92: Vikky Kumar | AV92: 9354241930 | AW92: 46118 | AX92: Kumar Gaurav Agarwal & company | AY92: Delhi | AZ92: Delhi | BA92: VGE6773224, GKE6784579, MFE6778570, RPE6784768, NDE6765957, PME6777882 | BB92: Vishal Gupta, Gopal Khatri, Md Faizullah, Ravi Parkashyanjyoti Deka, Pooja Mehra | BC92: Abhinav Lal, Rohit Nijhawan | BD92: Oxford Management Services | BE92: Oxford Management Services - Delhi | BF92: Oxford Management Services_Collection Agency_Delhi
A93: 153 | B93: Z15414 | C93: 26089 | D93: East | E93: Odisha | F93: Bhubaneshwar | G93: Collection/Pickup/Repo Agency | H93: P N Services | I93: Bibubuti Bhusan Mahapatra | J93: Bibubuti Bhusan Mahapatra | K93: 3774, Nageswar Tangi, Jayadev Nagar, Near Maa Club, Bhubaneshwar - 751002 | L93: 9337702267,9937887280,7064401615 | M93: 9337702267,9937887280,7064401615,7064781722,9658072509,9861560113,7978469061,7735922881,9937140705 | N93: - | O93: pnservices2@pnservices2.co.in | P93: servicespn14@gmail.com | Q93: AMPPM1056R | R93: - | S93: 21AMPPM1056R1ZM | T93: AA210417004369H | V93: BANDHAN BANK | X93: Properitoryship | Y93: Active | Z93: 42891 | AA93: 42884 | AE93: 26089 | AF93: P N Services | AG93: 669 | AH93: 503 | AI93: 481 | AJ93: 1653 | AL93: Allocaton given by Collection agency | AM93: Eligible for audit | AN93: KGAC | AO93: Ashutosh Gupta | AP93: 3774, Nageswar Tangi, Jayadev Nagar, Near Maa Club, Bhubaneshwar - 751002 | AQ93: Audited | AR93: NA | AT93: Santosh Kumar Sahoo | AU93: Vikky Kumar | AV93: 9354241930 | AW93: 46126 | AX93: Kumar Gaurav Agarwal & company | AY93: Bhubaneshwar | AZ93: Odisha | BA93: CJE6782046, SJE6757641, KBE6776090, SPE6753711, KME6780756, AME6777270 | BB93: Choudhury JeSuryakanta JeKalpataru Baishakh, Subhakanta Panda, Kiran Mohapatra, Avdesh Mishra | BC93: Ashutosh Gupta, Subhasis Banerjee, Saurabh Chaturvedi | BD93: P N Services | BE93: P N Services - Bhubaneshwar - Odisha | BF93: P N Services_Collection Agency_Bhubaneshwar_Odisha
A94: 31 | B94: Z21820 | C94: 26212 | D94: East | E94: Jharkhand | F94: Jamshedpur | G94: Collection & Repossession Agency | H94: Kalyani Associate - Jamshedpur | I94: Partha Sarthy Chatterjee | J94: Partha Sarthy Chatterjee / Satish Kumar | K94: 1St Floor Flat No-1/D, Jyoti Apartment , Road No- 2 ,Contractors Area ,Bistupur,Jamshedpur- 831001 | L94: 8405900000,9204628789 | M94: 7903493400 6205830880 | N94: 7491016471 | O94: kalyaniassociates.jsr@gmail.com ; shubhankar.kalyaniassociates@gmail.com; kalyani.billing@gmail.com; kalyani.ybwoff@gmail.com; kalyaniassociates.jsr20@gmail.com; kalyani.ybmore@gmail.com; | P94: kalyaniyesbank.patna@gmail.com | Q94: ACMPC9882G | S94: 20ACMPC9882G2ZI | V94: HDFC BANK LTD | X94: Properitoryship | Y94: Active | Z94: 43489 | AA94: 43455 | AE94: 26212 | AF94: Kalyani Associate | AG94: 1392 | AH94: 1312 | AI94: 1130 | AJ94: 3834 | AK94: 2 | AL94: Allocaton given by Collection & Repossession | AM94: Eligible for audit | AN94: KGAC | AO94: Ashutosh Gupta | AP94: 1St Floor Flat No-1/D, Jyoti Apartment , Road No- 2 ,Contractors Area ,Bistupur,Jamshedpur- 831001 | AQ94: Audited | AR94: NA | AT94: Niki Kumari | AU94: Vikky Kumar | AV94: 9354241930 | AW94: 46128 | AX94: Kumar Gaurav Agarwal & company | AY94: Jamshedpur | AZ94: Jharkhand | BA94: AKE6777646, SDE6781658, SPE6753711, KBE6776090, ASE6778477, AME6761288, AME6777270, PKE6762328, PYE6778749, CJE6782046, KME6780756, ASE6777499, STE6769262, PME6771779, ASE5641009 | BB94: Ashit Kumar, Sujoy Das, Subhakanta Panda, Kalpataru Baishakh, Amit Singh, Md Azharuddin, Avdesh Mishra, Prabhakar Kumar, Pankaj Yadav, Choudhury JeKiran Mohapatra, Arindam Sarkar, Santosh Thakur, Priyanka Mondal | BC94: Ashutosh Gupta, Subhasis Banerjee | BD94: Kalyani Associate - Jamshedpur | BE94: Kalyani Associate - Jamshedpur - Jharkhand | BF94: Kalyani Associate - Jamshedpur_Collection Agency_Jharkhand | BG94: Kalyani Associate - Jamshedpur_Repo Agency_Jharkhand
A95: 98 | B95: Z15652 | C95: 54662 | D95: North | E95: Uttarakhand | F95: Dehradun | G95: Collection & Repossession Agency | H95: Pashupati Associates | I95: Jitender Singh | J95: Jitender Singh | K95: 112/, Tagore Villa, Near Charak Pathology, Dehradun - 248001 | L95: 9897297728 | M95: 9897297728,9791391577,9927106640 | N95: 9897297728 | O95: pashupatichicky76@gmail.com | P95: NA | Q95: BAQPS7208P | R95: 75 ST PA BAS RSTDDN 09-10 | S95: 05BAQPS7208P1ZV | V95: HDFC BANK LTD | X95: Properitoryship | Y95: Active | Z95: 42921 | AA95: 42909 | AE95: 54662 | AF95: Pashupati Associates | AG95: 31 | AH95: 37 | AI95: 37 | AJ95: 105 | AL95: Allocaton given by Collection agency | AM95: Eligible for audit | AN95: KGAC | AO95: Rohit Nijhawan | AP95: 112/, Tagore Villa, Near Charak Pathology, Dehradun - 248001 | AQ95: Audited | AR95: NA | AT95: Varun / 7017433994 | AU95: Akshay Notiyal | AV95: 9149204613 | AW95: 46133 | AX95: Kumar Gaurav Agarwal & company | AY95: Dehradun | AZ95: Uttarakhand | BA95: HKE6745350 | BB95: Hayat Kathayat | BC95: Rohit Nijhawan | BD95: Pashupati Associates | BE95: Pashupati Associates - Dehradun - Uttarakhand | BF95: Pashupati Associates_Collection Agency_Dehradun_Uttarakhand
A96: 88 | B96: Z28444 | C96: 65900 | D96: North | E96: Uttar Pradesh | F96: Lucknow | G96: Collection & Repossession Agency | H96: Krishna Associates | I96: Krishna Verma | J96: Krishna Verma | K96: Ff16, Goel Palace, Indra Nagar Faizabad Road, Lucknow - 226016 | L96: 9984073156 | M96: 9984073156 | N96: 9984073156 | O96: krishnaverma156@gmail.com ; y.backend@krishnaaassociates.in | P96: NA | Q96: AHKPV7943E | S96: 09AHKPV7943E2ZP | V96: ICICI BANK LIMITED | X96: Properitoryship | Y96: Active | Z96: 45028 | AA96: 45026 | AE96: 65900 | AF96: Krishna associates | AG96: 428 | AH96: 455 | AI96: 501 | AJ96: 1384 | AK96: 5 | AL96: Allocaton given by Collection & Repossession | AM96: Eligible for audit | AN96: KGAC | AO96: Sameer Dhar | AP96: Ff16, Goel Palace, Indra Nagar Faizabad Road, Lucknow - 226016 | AQ96: Audited | AR96: NA | AT96: Prateek Asthana : 9140973378 | AU96: Hariom Sharma | AV96: 9810670823 | AW96: 46127 | AX96: Kumar Gaurav Agarwal & company | AY96: Lucknow | AZ96: Uttar Pradesh | BA96: SPE6785038, AKE6744759, DSE6786366, KKE6776767 | BB96: Shashi Pratap Singh, Aman Kesharwani, Dheerendra Singh, Kunwar Kumar Singh | BC96: Sanjeev Kumar, Sameer Dhar | BD96: Krishna Associates | BE96: Krishna Associates - Lucknow - Uttar Pradesh | BF96: Krishna Associates_Collection Agency_Lucknow_Uttar Pradesh | BG96: Krishna Associates_Repo Agency_Lucknow_Uttar Pradesh
A97: 83 | B97: NA | C97: 377996 | D97: North | E97: Haryana | F97: Gurgoan | G97: Collection & Repossession Agency | H97: Laado Associates | I97: Poonam Sehrawat , Pardeep Sehrawat | J97: Poonam Sehrawat , Pardeep Sehrawat | K97: Opp Dav Puplic School, Near Maharana Pratab Chowk, Sukharli Enclave, Gururam Haryana-122001, | L97: 9711700085 , 9911700030 | M97: 9711700085 , 9911700030 | N97: 9711700085 , 9911700030 | O97: laadoassociates@gmail.com | P97: NA | Q97: AAGFL4983M | S97: 06AAGFL4983M2ZP | X97: Partnership | Y97: Active | Z97: 45924 | AA97: 45924 | AE97: 377996 | AF97: Laado Associates | AG97: NA | AH97: NA | AI97: NA | AJ97: NA | AK97: 2 | AL97: Allocaton given by Repo agency | AM97: Eligible for audit | AN97: KGAC | AO97: #N/A | AP97: Opp Dav Puplic School, Near Maharana Pratab Chowk, Sukharli Enclave, Gururam Haryana-122001, | AQ97: Audited | AR97: NA | AT97: Kalpit Purwar / 9142810005 | AU97: Abhinav Khurana | AV97: 9217935065 | AW97: 46134 | AX97: Kumar Gaurav Agarwal & company | AY97: Gurgoan | AZ97: Haryana | BA97: NA | BB97: Abhishek Kumar, Vivek Kumar Shukla, Shyam Parkash, Rittin Arya | BC97: Abhinav Lal | BD97: Laado Associates | BE97: Laado Associates - Gurgoan - Haryana | BF97: Laado Associates_Collection Agency_Gurgoan_Haryana | BG97: Laado Associates_Repo Agency_Gurgoan_Haryana
A98: 161 | B98: Z14786 | C98: 26147 | D98: North | E98: Delhi | F98: Delhi | G98: Pick Up Agency | H98: Positive Move | I98: Sudhir Mal | J98: Sudhir Mal | K98: 53/A-7, 2Nd Floor, Rama Road,Industrial Area, Opp. Autoweb Hyundai, New Delhi - 110015 | L98: 9.81029947485888E+29 | M98: 9810299474,8588802958,8588802434,9871134345,9540602395,9873219628,8860419106,8800460361,9650753820,9716210294,9013085736,7982583518,9540483501 | N98: 9810299474,8588802958,8588802434,9711266572 | O98: posmovyb@gmail.com ; for operational work;mal.sudhir@gmail.com ; for billing; payout;escalations;etc,collectionsyb@posmov.com | P98: NA | Q98: ADGPM5433L | R98: ADGPM5433LST001 | S98: 07ADGPM5433L1ZB | T98: AA0703170018577 | U98: 034085800000237 | W98: OPENED | X98: Properitoryship | Y98: Active | Z98: 42769 | AA98: 42768 | AE98: 26147 | AF98: Positive Move | AG98: 260 | AH98: 343 | AI98: 363 | AJ98: 966 | AL98: Allocaton given by Collection agency | AM98: Eligible for audit | AN98: KGAC | AO98: NA | AP98: 53/A-7, 2Nd Floor, Rama Road,Industrial Area, Opp. Autoweb Hyundai, New Delhi - 110015 | AQ98: Audited | AR98: NA | AT98: Jai Prakash / 9871064272 | AU98: Abhinav Khurana | AV98: 9217935065 | AW98: 46133 | AX98: Kumar Gaurav Agarwal & company | AY98: Delhi | AZ98: Delhi | BA98: VGE6773224, HJE6739606, MSE6694032 | BB98: Vishal Gupta, Harish Johar, Manpreet Singh(Sbl) | BC98: Vineet Kumar | BD98: Positive Move | BE98: Positive Move - Delhi | BF98: Positive Move_Collection Agency_Delhi
A99: 89 | B99: NA | C99: 368002 | D99: North | E99: Uttar Pradesh | F99: Lucknow | G99: Collection & Repossession Agency | H99: M/S Awadh Risk Management Services Pvt Ltd | I99: Mr. Amit Kumar Singh & Mrs. Pratibha Singh & Mrs. Pinki Singh | J99: Mr. Amit Kumar Singh & Mrs. Pratibha Singh & Mrs. Pinki Singh | K99: A-42 Annapurna Complex Sector H Lda Colony Kanpur Road, Lucknow, Uttar Pradesh 226012 | L99: 7080802214, 7080802216, 7080802218 | M99: 7080802214, 7080802216, 7080802218 | N99: 7080802214, 7080802216, 7080802218 | O99: awadh.rishk@gmail.com | P99: NA | Q99: AANCA0030G | S99: 09AANCA0030G1Z1 | X99: Company | Y99: Active | Z99: 45929 | AA99: 45929 | AE99: 368002 | AF99: M/s Awadh Risk Management Services Pvt Ltd | AG99: NA | AH99: NA | AI99: NA | AJ99: NA | AK99: 12 | AL99: Allocaton given by Repo agency | AM99: Eligible for audit | AN99: KGAC | AO99: #N/A | AP99: A-42 Annapurna Complex Sector H Lda Colony Kanpur Road, Lucknow, Uttar Pradesh 226012 | AQ99: Audited | AR99: NA | AT99: Satyam Singh : 7080802261 | AU99: Hariom Sharma | AV99: 9810670823 | AW99: 46132 | AX99: Kumar Gaurav Agarwal & company | AY99: Lucknow | AZ99: Uttar Pradesh | BA99: NA | BB99: Vivek Kumar Shukla, Shyam Parkash, Rittin Arya, Sachin Chauhan, Prashant Singh, Vivek Shukla | BC99: Sameer Dhar, Sanjeev Kumar, Abhinav Lal | BD99: M/S Awadh Risk Management Services Pvt Ltd | BE99: M/S Awadh Risk Management Services Pvt Ltd - Lucknow - Uttar Pradesh | BF99: MS Awadh Risk Management Services Pvt Ltd_Collection Agency_Lucknow_Uttar Pradesh | BG99: MS Awadh Risk Management Services Pvt Ltd_Repo Agency_Lucknow_Uttar Pradesh
A100: 113 | B100: Z28509 | C100: 54359 | D100: East | E100: Bihar | F100: Patna | G100: Collection Agency | H100: Raj Management | I100: Prabhakar Kumar Mishra | J100: Prabhakar Kumar Mishra | K100: 1St Floor O.P Complex In Front Of Bandhan Bank Kurji Near Krishna Hospital Kurji Patna Bihar 800010 | L100: 8809666397 | M100: 8809666397 , 7482813023 , 7739960062 | O100: prabhakar.rajmanagement@gmail.com; prabhakar.mishra0197@gmail.com; rajmanagement06@gmail.com ; raj@rajmanagement.net.in | P100: NA | Q100: CTAPM1853Q | R100: 0 | S100: 10CTAPM1853Q2ZK | T100: 0 | U100: 0 | V100: 0 | W100: 0 | X100: Properitoryship | Y100: Active | Z100: 44867 | AA100: 44865 | AB100: 0 | AC100: There was no allocation for 3 months, Hence de-activated only for Collections, however agency Active in Credit Cards | AD100: Agency marked as active since approval recived for re-engageent of agency from BU head. | AE100: 54359 | AF100: Raj Management | AG100: 893 | AH100: 900 | AI100: 1017 | AJ100: 2810 | AL100: Allocaton given by Collection agency | AM100: Eligible for audit | AN100: KGAC | AO100: Ashutosh Gupta | AP100: 1St Floor O.P Complex In Front Of Bandhan Bank Kurji Near Krishna Hospital Kurji Patna Bihar 800010 | AQ100: Audited | AR100: NA | AT100: Prabhakar Ji | AU100: Vikky Kumar | AV100: 9354241930 | AW100: 46133 | AX100: Kumar Gaurav Agarwal & company | AY100: Patna | AZ100: Bihar | BA100: PYE6778749, RSE6776475, MME6755196, GSE6778012, STE6769262 | BB100: Pankaj Yadav, Rupesh Singh, Mritunjay MunGaurav Singh, Santosh Thakur | BC100: Ashutosh Gupta | BD100: Raj Management | BE100: Raj Management - Patna - Bihar | BF100: Raj Management_Collection Agency_Patna_Bihar
...

Sheet Audited
A1: Sr No. | B1: Vendor Code | C1: Erp Id | D1: Zone | E1: State | F1: Location | G1: Agency Type | H1: Vendor Name | I1: Owner/Partners/Director's Name | J1: Contact Person | K1: Address | L1: Audited address | M1: Status | N1: Remarks | O1: Console | P1: Manager | Q1: Auditor Name | R1: Auditor Cont. Number | S1: Audit date | T1: Vendor Name | U1: Location | V1: State | W1: CM ID | X1: CM | Y1: RCM | Z1: Vendor Name | AA1: File Name
A2: 1 | B2: 66907 | C2: 66907 | D2: East | E2: Assam | F2: Guwahati | G2: Collection & Repossession Agency | H2: Aba | I2: Junti Bania | J2: Junti Bania | K2: House No -33, Rangmili Path, M T Road, Guwahati - 780124 | L2: 3 Rd Florr House No 20 Hr Port Near Decora Marriage Hall Rgb Road Guwahati | M2: Audited | N2: NA | P2: Abdul Kayum | Q2: Pradeep | R2: 8287823681 | S2: 46130 | T2: Kumar Gaurav Agarwal & company | U2: Guwahati | V2: Assam | W2: BKE6757902, GCE6775573 | X2: Bikash Kalita, Gautam Chowdhury | Y2: Subhasis Banerjee, Md Shabbir Alam | Z2: Aba
A3: 3 | B3: Yblv1123 | C3: 306987 | D3: East | E3: Assam | F3: Guwahati | G3: Collection & Repossession Agency | H3: Gurseerat Legal Management Service | I3: Harvinder Singh Upp | J3: Harvinder Singh Upp | K3: Kachari Basti Road, House No. 1, Holding No. 246 Of Gmc Ulubari, Guwahati, Kamrup, Assam-781007. | L3: Kachari Basti Road, House No. 1, Holding No. 246 Of Gmc Ulubari, Guwahati, Kamrup, Assam-781007. | M3: Audited | N3: NA | P3: Rakesh | Q3: Pradeep | R3: 8287823681 | S3: 46129 | T3: Kumar Gaurav Agarwal & company | U3: Guwahati | V3: Assam | W3: NKE6776587, SBE6782270, VME6772902, SRE6782838, RSE6776475, NDE6765957 | X3: Nitumani Kalita, Subhajit Bhowmik, Vaibhav Mishra, Sidharth RaRupesh Singhyanjyoti Deka | Y3: Na | Z3: Gurseerat Legal Management Service
A4: 4 | B4: Yblv1107 | C4: 298994 | D4: East | E4: Assam | F4: Guwahati | G4: Collection & Repossession Agency | H4: Namanshee Associates | I4: Ritupan Kalita | J4: Ritupan Kalita | K4: Bora Market Market R.G.B Road , Borah Market Complex,1 St Floor, Near Assam State Zoo, Guwahati, Assam-781005 | L4: Impereal Uzan Bazzar Flat No-3-B-Third Floor Commercial M.C.Road Uzan Bazar | M4: Audited | N4: NA | P4: Ritupan Kalita | Q4: Pradeep | R4: 8287823681 | S4: 46130 | T4: Kumar Gaurav Agarwal & company | U4: Guwahati | V4: Assam | W4: NDE6765957, RPE6775155 | X4: Nayanjyoti Deka, Rakesh Pathak | Y4: Ashutosh Gupta | Z4: Namanshee Associates
A5: 5 | B5: NA | C5: 327999 | D5: East | E5: Assam | F5: Guwahati | G5: Collection & Repossession Agency | H5: Uttaran | I5: Bidyut Patowary | J5: Bidyut Patowary | K5: Borah Maket Rgb Road ,, Guwahati , Kamrup Metro , 781005 | L5: Borah Maket Rgb Road ,, Guwahati , Kamrup Metro , 781005 | M5: Audited | N5: NA | P5: Kuldeep Baniya | Q5: Pradeep | R5: 8287823681 | S5: 46129 | T5: Kumar Gaurav Agarwal & company | U5: Guwahati | V5: Assam | W5: RWE6776982, BKE6757902, NKE6776587, RPE6775155, NDE6765957 | X5: Roshmi Wary, Bikash Kalita, Nitumani Kalita, Rakesh Pathakyanjyoti Deka | Y5: Ashutosh Gupta, Biswarup Ghosh, Subhasis Banerjee | Z5: Uttaran
A6: 7 | B6: Z20543 | C6: 25557 | D6: East | E6: Bihar | F6: Patna | G6: Collection & Repossession Agency | H6: Aim Corporate - Patna | I6: Sanjay Gupta | J6: Sanjay Gupta/Suresh Bisoi | K6: A/56,Housing Colony Lohiyanagar,Kankarbagh Patna Bihar_800020 | L6: A/56,Housing Colony Lohiyanagar,Kankarbagh Patna Bihar_800020 | M6: Audited | N6: Audited for Collection Only, as no activity of repossession are done for the audit quarter | P6: Manoj | Q6: Vikky Kumar | R6: 9354241930 | S6: 46134 | T6: Kumar Gaurav Agarwal & company | U6: Patna | V6: Bihar | W6: KSE6767729, SME6784348, IEE6769906, PME6771779, RBE6757282, DSE6782069, SNE6610031, ASE6777499, TSE6288042, NKE6754736, RHE6158002, ABE6771337, OAE6762281, SGE6696032, MAE6785142, JME6788432 | X6: Krishnendu Sarder, Saisab Mallick, Imran Elahi, Priyanka Mondal, Ritam Basak, Deepak Singh, Suryanarayan Nayak, Arindam Sarkar, Tarkeshwar Singh, Nishant Kumar, Rajkumar Hazra, Abhisek Bose, Ossam Aditya, Soumitra Ghosh, Monawwar Alam, Jayadev Mishra | Y6: Subhasis Banerjee, Biswarup Ghosh, Md Shabbir Alam | Z6: Aim Corporate - Patna
A7: 8 | B7: NA | C7: 313004 | D7: East | E7: Chhattisgarh | F7: Raipur | G7: Collection & Repossession Agency | H7: Anurag Agency | I7: Anurag Rathi | J7: Anurag Rathi | K7: 3Rd Floor,Hanumanta Complex,Near Mansu Realty Ring Road No. 1 Agoraha Colony Raipura Raipur (492013) | L7: 3Rd Floor,Hanumanta Complex,Near Mansu Realty Ring Road No. 1 Agoraha Colony Raipura Raipur (492013) | M7: Audited | N7: Audited for collection and Repossessoin, as agency have repo of assest in the audit quarter | P7: Namarta Sharma / 8770534356 | Q7: Parteek Yadav | R7: 7460008081 | S7: 46125 | T7: Kumar Gaurav Agarwal & company | U7: Raipur | V7: Chhattisgarh | W7: VUE6755300, RQE6781542, ASE6778431, SME6345002, MKE6775854, ADE6782782 | X7: Vikram Upadhyay, Rizwan Quraishi, Avtar Singh, Sudarshan Maddu, Manoj Kumar, Anindh Dubey | Y7: Saurabh Chaturvedi, Biswarup Ghosh, Md Shabbir Alam, -, Saurabh Chaturvedi , Bikram Chakraborty | Z7: Anurag Agency
A8: 9 | B8: Z23173 | C8: 26489 | D8: East | E8: Chhattisgarh | F8: Raipur | G8: Collection & Repossession Agency | H8: Infinity Services | I8: Ayesha Begam | J8: Varsha Vani/ Imran Charania / Mohd. Israr | K8: Hig/C-21, Sector - 1, Devendra Nagar, Raipur (C.G.) 492001. | L8: Hig/C-21, Sector - 1, Devendra Nagar, Raipur (C.G.) 492001. | M8: Audited | N8: NA | P8: Mohammed Rizwan (7509634823) | Q8: Parteek Yadav | R8: 7460008081 | S8: 46126 | T8: Kumar Gaurav Agarwal & company | U8: Raipur | V8: Chhattisgarh | W8: VUE6755300, LVE6783252, ASE6778431, MKE6775854, SME6345002, RQE6781542, MKE6467020, NME6765631 | X8: Vikram Upadhyay, Lokesh Vadaskar, Avtar Singh, Manoj Kumar, Sudarshan Maddu, Rizwan Quraishi, Nikunj Mohod | Y8: Amar Gupte, Abhijeet Kashid, Subhasis Banerjee, Biswarup Ghosh, Saurabh Chaturvedi, Md Shabbir Alam, Ashutosh Gupta | Z8: Infinity Services
A9: 10 | B9: Yblv1132 | C9: 307991 | D9: North | E9: Delhi | F9: Delhi | G9: Collection & Repossession Agency | H9: Ambitious Enterprises | I9: Rameshwar Jaiswal | J9: Rameshwar Jaiswal | K9: Rz-154A , Main Najafgarh Road, Uttam Nagar Delhi | L9: Rz-154A , Main Najafgarh Road, Uttam Nagar Delhi | M9: Audited | N9: NA | P9: Akhilesh Kumar Tripahi | Q9: Rahul Verma | R9: 9354183359 | S9: 46126 | T9: Kumar Gaurav Agarwal & company | U9: Delhi | V9: Delhi | W9: NSE6771909, SKE5835012, MSE6236002, SRE6739824, NRE6746973 | X9: Narinder Singh, Sushim Kumar, Manpreet Singh(Auto), Syed Razavdeep Rastogi | Y9: Sanjeev Kumar, Sameer Dhar | Z9: Ambitious Enterprises
A10: 11 | B10: Z23039 | C10: 26323 | D10: North | E10: Delhi | F10: Delhi | G10: Collection & Repossession Agency | H10: Delta Services | I10: Anil Sharma | J10: Anil Sharma / Paramjeet Singh | K10: Wz-20, Possangipur, Janakpuri, New Delhi – 110058 | L10: Wz-20, Possangipur, Janakpuri, New Delhi – 110058 | M10: Audited | N10: NA | P10: Anil Sharma | Q10: Pawan Kumar | R10: 9582917652 | S10: 46134 | T10: Kumar Gaurav Agarwal & company | U10: Delhi | V10: Delhi | W10: RAE6783127, KSE6769063, SKE5835012, SSE6775469, RSE6763776, STE5844128, PKE6779360, MKE6780549 | X10: Rittin Arya, Kushpal Singh, Sushim Kumar, Sukhwinder Singh, Ram Shankar, Sandeep Tyagi, Pawan Kumar, Milind Kumbhar | Y10: Sanjeev Kumar, Rajnish Dwivedi | Z10: Delta Services
A11: 12 | B11: Z25246 | C11: 26364 | D11: North | E11: Delhi | F11: Delhi | G11: Collection & Repossession Agency | H11: Earth Services | I11: Subhash Chand | J11: Subhash Chand | K11: Wz-12 Kh No2882/738 1St , Floor Kailash Park, Nd-15 | L11: Wz-12 Kh No2882/738 1St , Floor Kailash Park, Nd-15 | M11: Audited | N11: NA | P11: Mithlesh Kumar | Q11: Pawan Kumar | R11: 9582917652 | S11: 46134 | T11: Kumar Gaurav Agarwal & company | U11: Delhi | V11: Delhi | W11: NKE6775741, AKE6778416, SRE6782838, RSE6776475, VKE6782576, SSE6775469, MME6755196, VGE6773224, SSE6748795 | X11: Nitin Kumar, Amit Kumar, Sidharth RaRupesh Singh, Vikash Kumar, Sukhwinder Singh, Mritunjay MunVishal Gupta, Sukhwant Singh | Y11: Ashutosh Gupta | Z11: Earth Services
A12: 13 | B12: Z22853 | C12: 26490 | D12: North | E12: Delhi | F12: Delhi | G12: Collection & Repossession Agency | H12: G.D.M. Management Services Pvt Ltd - Delhi | I12: Rajesh Kumar/Naresh Kumar | J12: Rajesh Kumar/Naresh Kumar | K12: A-1 1St Floor , Shastri Nagar , New Delhi -110034 | L12: A-1 1St Floor , Shastri Nagar , New Delhi -110034 | M12: Audited | N12: NA | P12: Rupali Singh/8539940963 | Q12: Abhinav Khurana | R12: 9217935065 | S12: 46132 | T12: Kumar Gaurav Agarwal & company | U12: Delhi | V12: Delhi | W12: NRE6746973, SRE6739824, RSE6763776, SRE6782838, RCE6775867, BRE6281007, ANE5784049, ERE6776646, PKE6779360, VME6772902, KSE6769063, MRE6786842 | X12: Navdeep Rastogi, Syed Raza, Ram Shankar, Sidharth RaRitesh Chourasia, Bhavna Rajput, Anil Kumar Nandal, Ekta Rani, Pawan Kumar, Vaibhav Mishra, Kushpal Singh, Mohit Rathore | Y12: Sameer Dhar, Kunal Malhotra, Sanjeev Kumar, Ashutosh Gupta, Upanshu Bajaj | Z12: G.D.M. Management Services Pvt Ltd - Delhi
A13: 14 | B13: NA | C13: 282016 | D13: North | E13: Delhi | F13: Delhi | G13: Collection & Repossession Agency | H13: Global Services - Delhi | I13: Sandeep Kumar Singh | J13: Sandeep Kumar Singh | K13: C-128/2, Village- Mohdpur New Delhi- 110067 | L13: C-128/2, Village- Mohdpur New Delhi- 110067 | M13: Audited | N13: NA | P13: Neha (8851441735) | Q13: Akshay Notiyal | R13: 9149204613 | S13: 46135 | T13: Kumar Gaurav Agarwal & company | U13: Delhi | V13: Delhi | W13: RSE6762728, DSE6786366, MKE6467020, VME6772902, KKE6776767 | X13: Ravi Singh, Dheerendra Singh, Manoj Kumar, Vaibhav Mishra, Kunwar Kumar Singh | Y13: Kunal Malhotra, Upanshu Bajaj | Z13: Global Services - Delhi
A14: 15 | B14: Z14974 | C14: 26166 | D14: North | E14: Delhi | F14: Delhi | G14: Collection & Repossession Agency | H14: Management Services | I14: Sunil Diwan | J14: Sunil Diwan | K14: B-138.3Rd Floor Navakar Building, Mohammad Pur New Delhi 110066 | L14: B-138.3Rd Floor Navakar Building, Mohammad Pur New Delhi 110066 | M14: Audited | N14: NA | P14: Rajesh Rohil : 9873954912 | Q14: Hariom Sharma | R14: 9810670823 | S14: 46134 | T14: Kumar Gaurav Agarwal & company | U14: Delhi | V14: Delhi | W14: GME6718001, NKE6775741, KKE6776767, SKE6779366, PGE6777921, DSE6786366, RPE6784768, RSE6776115, GKE6784579, STE5844128, MFE6778570, VGE6773224, RAE6783127, SPE6776273 | X14: Gaurav Mishra, Nitin Kumar, Kunwar Kumar Singh, Sumit Kumar, Priyanka Gupta, Dheerendra Singh, Ravi Parkash, Rahul Sharma, Gopal Khatri, Sandeep Tyagi, Md Faizullah, Vishal Gupta, Rittin Arya, Sushant Parashar | Y14: Sameer Dhar, Abhinav Lal | Z14: Management Services
... A89: 101 | B89: Z20543 | C89: 25557 | D89: East | E89: West Bengal | F89: Kolkata | G89: Collection & Repossession Agency | H89: Aim Corporate - Kolkata | I89: Sanjay Gupta | J89: Sanjay Gupta/Suresh Bisoi | K89: 17/3 Sahapur Colony New Alipore, Kolkata-700053 | L89: 17/3 Sahapur Colony New Alipore, Kolkata-700053 Office Adders-34/ | M89: Audited | N89: NA | P89: Payal | Q89: Vikky Kumar | R89: 9354241930 | S89: 46121 | T89: Kumar Gaurav Agarwal & company | U89: Kolkata | V89: West Bengal | W89: KSE6767729, SME6784348, IEE6769906, PME6771779, RBE6757282, DSE6782069, SNE6610031, ASE6777499, TSE6288042, NKE6754736, RHE6158002, ABE6771337, OAE6762281, SGE6696032, MAE6785142, JME6788432 | X89: Krishnendu Sarder, Saisab Mallick, Imran Elahi, Priyanka Mondal, Ritam Basak, Deepak Singh, Suryanarayan Nayak, Arindam Sarkar, Tarkeshwar Singh, Nishant Kumar, Rajkumar Hazra, Abhisek Bose, Ossam Aditya, Soumitra Ghosh, Monawwar Alam, Jayadev Mishra | Y89: Subhasis Banerjee, Biswarup Ghosh, Md Shabbir Alam | Z89: Aim Corporate - Kolkata
A90: 102 | B90: 83886 | C90: 83886 | D90: East | E90: West Bengal | F90: Kolkata | G90: Collection & Repossession Agency | H90: Chandan Saha | I90: Chandan Saha | J90: Chandan Saha | K90: 180/1/B, Roy Bahadur Road, Kolkata - 700034 | L90: 180/1/B, Roy Bahadur Road, Kolkata - 700034 | M90: Audited | N90: NA | P90: Tarun Kumar Kundu | Q90: Vikky Kumar | R90: 9354241930 | S90: 46120 | T90: Kumar Gaurav Agarwal & company | U90: Kolkata | V90: West Bengal | W90: SME6784348, PME6771779, AME6761288, SPE6770640, ASE6777499, IEE6769906, DSE6782069, TSE6288042, RBE6757282, MBE6782720, SGE6696032, MAE6785142, SPE6753711 | X90: Saisab Mallick, Priyanka Mondal, Md Azharuddin, Souvik Pramanik, Arindam Sarkar, Imran Elahi, Deepak Singh, Tarkeshwar Singh, Ritam Basak, Manish Bhagat, Soumitra Ghosh, Monawwar Alam, Subhakanta Panda | Y90: Subhasis Banerjee, Ashutosh Gupta, Biswarup Ghosh, Md Shabbir Alam | Z90: Chandan Saha
A91: 103 | B91: Z18015 | C91: 25877 | D91: East | E91: West Bengal | F91: Kolkata | G91: Collection & Repossession Agency | H91: Easyway Advisory | I91: Sumita Das | J91: Sumita Das | K91: 28 (264/1) Dum Dum C Road, Kolkata - 700074 | L91: 28 (264/1) Dum Dum C Road, Kolkata - 700074 | M91: Audited | N91: NA | P91: Suradip Mondal | Q91: Vikky Kumar | R91: 9354241930 | S91: 46119 | T91: Kumar Gaurav Agarwal & company | U91: Kolkata | V91: West Bengal | W91: KSE6767729, JSE6781036 | X91: Krishnendu Sarder, Joy Saha | Y91: Na | Z91: Easyway Advisory
A92: 105 | B92: Yblv1117 | C92: 303020 | D92: East | E92: West Bengal | F92: Kolkata | G92: Collection & Repossession Agency | H92: J K Associate | I92: Masud Akhtar | J92: Masud Akhtar | K92: 50 A, Naba Mohajati Road, Dumdum 700028 | L92: 68/A Jessore Road, Dumdum, North 24 Parganas, 700028 | M92: Audited | N92: NA | P92: Masud Aktar | Q92: Pradeep | R92: 8287823681 | S92: 46132 | T92: Kumar Gaurav Agarwal & company | U92: Kolkata | V92: West Bengal | W92: SME6781177, SDE6778568, RBE6757282, TSE6288042, DSE6782069 | X92: Sudip ManSuman Das, Ritam Basak, Tarkeshwar Singh, Deepak Singh | Y92: Biswarup Ghosh | Z92: J K Associate
A93: 106 | B93: Z21820 | C93: 26212 | D93: East | E93: West Bengal | F93: Kolkata | G93: Collection & Repossession Agency | H93: Kalyani Associate - Kolkata | I93: Partha Sarthy Chatterjee | J93: Partha Sarthy Chatterjee / Satish Kumar | K93: Saltee Plaza,Room No 504,1 No Jessore Road,Gol Park, Kamar Danga,North Damdam West Bengal, Kolkata 700080 | L93: Saltee Plaza,Room No 504,1 No Jessore Road,Gol Park, Kamar Danga,North Damdam West Bengal, Kolkata 700080 | M93: Audited | N93: Audited for Collection Only, as no activity of repossession are done from Kolkata branch | P93: Rajib Halder | Q93: Vikky Kumar | R93: 9354241930 | S93: 46122 | T93: Kumar Gaurav Agarwal & company | U93: Kolkata | V93: West Bengal | W93: AKE6777646, SDE6781658, SPE6753711, KBE6776090, ASE6778477, AME6761288, AME6777270, PKE6762328, PYE6778749, CJE6782046, KME6780756, ASE6777499, STE6769262, PME6771779, ASE5641009 | X93: Ashit Kumar, Sujoy Das, Subhakanta Panda, Kalpataru Baishakh, Amit Singh, Md Azharuddin, Avdesh Mishra, Prabhakar Kumar, Pankaj Yadav, Choudhury JeKiran Mohapatra, Arindam Sarkar, Santosh Thakur, Priyanka Mondal | Y93: Ashutosh Gupta, Subhasis Banerjee | Z93: Kalyani Associate - Kolkata
A94: 107 | B94: Yblv1016 | C94: 168962 | D94: East | E94: West Bengal | F94: Kolkata | G94: Collection & Repossession Agency | H94: Sunshine Credit Services | I94: Suraj Nair | J94: Suraj Nair | K94: 48/28A, Purnachandra Mitra Lane, Swiss Park, Kolkata - 700033 | L94: 48/28A, Purnachandra Mitra Lane, Swiss Park, Kolkata - 700033 | M94: Audited | N94: NA | P94: Amit Sengupta | Q94: Vikky Kumar | R94: 9354241930 | S94: 46120 | T94: Kumar Gaurav Agarwal & company | U94: Kolkata | V94: West Bengal | W94: ASE6777499, KSE6767729, PME6771779, IEE6769906, TSE6288042 | X94: Arindam Sarkar, Krishnendu Sarder, Priyanka Mondal, Imran Elahi, Tarkeshwar Singh | Y94: Subhasis Banerjee, Biswarup Ghosh | Z94: Sunshine Credit Services
A95: 108 | B95: NA | C95: 374994 | D95: East | E95: West Bengal | F95: Kolkata | G95: Collection & Repossession Agency | H95: Swastik Consultancy | I95: Pronob Karar/Raj Amitava Mitra | J95: Pronob Karar/Raj Amitava Mitra | K95: 10B Mukherjee Para Lane, 1St Floor Kolkata.Pin-700026. | L95: 10B Mukherjee Para Lane, 1St Floor Kolkata.Pin-700026. | M95: Audited | N95: NA | P95: Dalijeet Singh | Q95: Vikky Kumar | R95: 9354241930 | S95: 46124 | T95: Kumar Gaurav Agarwal & company | U95: Kolkata | V95: West Bengal | W95: SDE6778568, JSE6781036 | X95: Suman Das, Joy Saha | Y95: Na | Z95: Swastik Consultancy
A96: 109 | B96: Z14593 | C96: 26452 | D96: East | E96: West Bengal | F96: Kolkata | G96: Collection & Repossession Agency | H96: Urenus | I96: Ashok Taru Ghosh | J96: Ashok Taru Ghosh | K96: 15, Tollygunge Circular Road, New Alipore, Kolkata - 700053 | L96: 15, Tollygunge Circular Road, New Alipore, Kolkata - 700053 | M96: Audited | N96: NA | P96: Tanmoy Chandra | Q96: Pradeep | R96: 8287823681 | S96: 46123 | T96: Kumar Gaurav Agarwal & company | U96: Kolkata | V96: West Bengal | W96: SME6784348, RSE6776475, MKE6776747, IEE6769906, AKE6769375, MAE6785142, OAE6762281, ABE6771337, RHE6158002, SGE6696032, JME6788432 | X96: Saisab Mallick, Rupesh Singh, Md Kausar, Imran Elahi, Abhishek Kumar, Monawwar Alam, Ossam Aditya, Abhisek Bose, Rajkumar Hazra, Soumitra Ghosh, Jayadev Mishra | Y96: Ashutosh Gupta, Md Shabbir Alam | Z96: Urenus
A97: 110 | B97: Z28376 | C97: 53595 | D97: East | E97: West Bengal | F97: Midnapore | G97: Collection & Repossession Agency | H97: Wayout Solutions | I97: Debjit Das | J97: Debjit Das | K97: 24, Ashoke Nagar, P.O- Midnapore, Ps - Kotwali, Dist - Paschim Medinipur State - West Bengal - 721101 | L97: 24, Ashoke Nagar, P.O- Midnapore, Ps - Kotwali, Dist - Paschim Medinipur State - West Bengal - 721101 | M97: Audited | N97: NA | P97: Avijit Mallik | Q97: Pradeep | R97: 8287823681 | S97: 10-03-2026 | T97: Kumar Gaurav Agarwal & company | U97: Midnapore | V97: West Bengal | W97: ASE6777499, RBE6757282, TSE6288042, DSE6782069, PME6771779, RHE6158002, ABE6771337, MBE6782720, MAE6785142 | X97: Arindam Sarkar, Ritam Basak, Tarkeshwar Singh, Deepak Singh, Priyanka Mondal, Rajkumar Hazra, Abhisek Bose, Manish Bhagat, Monawwar Alam | Y97: Subhasis Banerjee, Biswarup Ghosh, Md Shabbir Alam | Z97: Wayout Solutions
A98: 111 | B98: NA | C98: 351036 | D98: East | E98: West Bengal | F98: Nadia | G98: Collection & Repossession Agency | H98: Boundless Grow Up Private Limited | I98: Mithun Halder/Suparna Jana | J98: Mithun Halder/Suparna Jana | K98: New Kalipur, Bhatjangla, Ps-Kotwali, Krishnanagar, Nadia, Pin-741102. | L98: New Kalipur, Bhatjangla, Ps-Kotwali, Krishnanagar, Nadia, Pin-741102. | M98: Audited | N98: NA | P98: Subir Sikdar | Q98: Pradeep | R98: 8287823681 | S98: 46120 | T98: Kumar Gaurav Agarwal & company | U98: Nadia | V98: West Bengal | W98: NA | X98: Priyanka Mondal, Sourabh Parihar | Y98: Subhasis Banerjee, Biswarup Ghosh | Z98: Boundless Grow Up Private Limited
A99: 112 | B99: Z21422 | C99: 26219 | D99: East | E99: Bihar | F99: Patna | G99: Collection Agency | H99: Global Management - Patna | I99: Rishikesh Mishra | J99: Rishikesh Mishra | K99: O. P. Complex, Opp Hdfc Bank, P & M Mall Road, Kurji, Patna 800010 | L99: O. P. Complex, Opp Hdfc Bank, P & M Mall Road, Kurji, Patna 800010 | M99: Audited | N99: NA | P99: Pankaj Kumar | Q99: Vikky Kumar | R99: 9354241930 | S99: 46133 | T99: Kumar Gaurav Agarwal & company | U99: Patna | V99: Bihar | W99: NKE6776587, AGE6739903, DNE6774673, MME6529036, MKE6768979, RSE6776475, GSE6778012, MME6755196E6771064, AKE6769375, SBE6771663, AKE6777646, SCE6766134, NDE6765957, SSE6762160, KPE6762069 | X99: Nitumani Kalita, Arjun Gudewar, Divya Nagda, Manoj Mishra, Manibhushan Kumar, Rupesh Singh, Gaurav Singh, Mritunjay Munnageshwar A, Abhishek Kumar, Swapnil Bhat, Ashit Kumar, Shailendra Chauhanyanjyoti Deka, Sushant Singh, Ketan Pol | Y99: Abhijeet Kashid, Subhasis Banerjee, Ashutosh Gupta, Kunal Malhotra | Z99: Global Management - Patna
A100: 113 | B100: Z28509 | C100: 54359 | D100: East | E100: Bihar | F100: Patna | G100: Collection Agency | H100: Raj Management | I100: Prabhakar Kumar Mishra | J100: Prabhakar Kumar Mishra | K100: 1St Floor O.P Complex In Front Of Bandhan Bank Kurji Near Krishna Hospital Kurji Patna Bihar 800010 | L100: 1St Floor O.P Complex In Front Of Bandhan Bank Kurji Near Krishna Hospital Kurji Patna Bihar 800010 | M100: Audited | N100: NA | P100: Prabhakar Ji | Q100: Vikky Kumar | R100: 9354241930 | S100: 46133 | T100: Kumar Gaurav Agarwal & company | U100: Patna | V100: Bihar | W100: PYE6778749, RSE6776475, MME6755196, GSE6778012, STE6769262 | X100: Pankaj Yadav, Rupesh Singh, Mritunjay MunGaurav Singh, Santosh Thakur | Y100: Ashutosh Gupta | Z100: Raj Management
A101: 114 | B101: Z23170 | C101: 26111 | D101: North | E101: Delhi | F101: Delhi | G101: Collection Agency | H101: Gurman Industries - Nirman Vihar | I101: Sukhpreet Singh | J101: Sukhpreet Singh / Harpreet Singh / Umesh Sharma / Naveen Dua | K101: Mb-1/E, Madhuban Road, Vikas Marg, Shakarpur, New Delhi,East Delhi, Delhi India -110092 | L101: Mb-1/E, Madhuban Road, Vikas Marg, Shakarpur, New Delhi,East Delhi, Delhi India -110092 | M101: Audited | N101: NA | P101: Gauri Shankar Sharma/7011373173 | Q101: Abhinav Khurana | R101: 9217935065 | S101: 46135 | T101: Kumar Gaurav Agarwal & company | U101: Delhi | V101: Delhi | W101: VPE6766232, CME6702019, MKE6467020 | X101: Vivek Pandey, Chander Miglani, Manoj Kumar | Y101: Rohit Nijhawan | Z101: Gurman Industries - Nirman Vihar
A102: 115 | B102: Z23170 | C102: 26111 | D102: North | E102: Delhi | F102: Delhi | G102: Collection Agency | H102: Gurman Industries - Shubhash Nagar | I102: Sukhpreet Singh | J102: Sukhpreet Singh / Harpreet Singh / Umesh Sharma / Naveen Dua | K102: Plot No.5 Top Floor Near Marry Zone Banquet , Subhash Nagar Metro Station , Gate No.2 Tilak Nagar , Industrial Area , New Delhi-110019 | L102: Plot No.5 Top Floor Near Marry Zone Banquet , Subhash Nagar Metro Station , Gate No.2 Tilak Nagar , Industrial Area , New Delhi-110019 | M102: Audited | N102: NA | P102: Arif / 8742950251 | Q102: Abhinav Khurana | R102: 9217935065 | S102: 46134 | T102: Kumar Gaurav Agarwal & company | U102: Delhi | V102: Delhi | W102: VPE6766232, CME6702019, MKE6467020 | X102: Vivek Pandey, Chander Miglani, Manoj Kumar | Y102: Rohit Nijhawan | Z102: Gurman Industries - Shubhash Nagar
A103: 116 | B103: Z24041 | C103: 26478 | D103: North | E103: Delhi | F103: Delhi | G103: Collection Agency | H103: Krishnapriya Credit Management Services (P) Ltd | I103: Arneb Debashish Nanad / Sandeep Singh Negi | J103: Sandeep Singh Negi | K103: 301,302,305,306,Guru Arjun Dev Bhawan,Ranjeet Nagar,Commerccial Complex,Shadipur-110008 | L103: 301,302,305,306,Guru Arjun Dev Bhawan,Ranjeet Nagar,Commerccial Complex,Shadipur-110008 | M103: Audited | N103: NA | P103: Rahul Arora | Q103: Rahul Verma | R103: 9354183359 | S103: 45763 | T103: Kumar Gaurav Agarwal & company | U103: Delhi | V103: Delhi | W103: HBE6784419, RSE6778024, ASE6749478, VJE6777344, NTE6776994, RPE6777552 | X103: Hemant Bajaj, Rinki Sharma, Ashvini Sharma, Vikashbhai Joshi, Neelesh Tiwari, Robin Pachchigar | Y103: Kunal Malhotra, Rajnish Dwivedi, Upanshu Bajaj | Z103: Krishnapriya Credit Management Services (P) Ltd
A104: 117 | B104: Z24042 | C104: 26232 | D104: North | E104: Delhi | F104: Delhi | G104: Collection Agency | H104: Oxford Management Services | I104: Sushant Sharma | J104: Sushant Sharma | K104: 1/50/2/71, 2Nd Floor Lalita Park Laxmi Nagar Delhi 110092 | L104: 1/50/2/71, 2Nd Floor Lalita Park Laxmi Nagar Delhi 110092 | M104: Audited | N104: NA | P104: Suhshant Sharma | Q104: Vikky Kumar | R104: 9354241930 | S104: 46118 | T104: Kumar Gaurav Agarwal & company | U104: Delhi | V104: Delhi | W104: VGE6773224, GKE6784579, MFE6778570, RPE6784768, NDE6765957, PME6777882 | X104: Vishal Gupta, Gopal Khatri, Md Faizullah, Ravi Parkashyanjyoti Deka, Pooja Mehra | Y104: Abhinav Lal, Rohit Nijhawan | Z104: Oxford Management Services
A105: 119 | B105: NA | C105: 185979 | D105: North | E105: Delhi | F105: Delhi | G105: Collection Agency | H105: Accurate Investigations | I105: Daya Nand Kaushik | J105: Daya Nand Kaushik | K105: A5- Shankar Garden Opp Metro Pillar No 618, Najafgarh Road Vikas Puri New Delhi 110018 | L105: A5- Shankar Garden Opp Metro Pillar No 618, Najafgarh Road Vikas Puri New Delhi 110018 | M105: Audited | N105: NA | P105: Pravesh (9205533109) | Q105: Parteek Yadav | R105: 7460008081 | S105: 46120 | T105: Kumar Gaurav Agarwal & company | U105: Delhi | V105: Delhi | W105: VGE6773224, SRE6782838, NKE6775741, JSE6785583, SBE6782270 | X105: Vishal Gupta, Sidharth RaNitin Kumar, Jay Shukla, Subhajit Bhowmik | Y105: Na | Z105: Accurate Investigations
A106: 120 | B106: NA | C106: 71934 | D106: North | E106: Delhi | F106: Delhi | G106: Collection Agency | H106: Jai Ambey Associates | I106: Ajay Kumar Trivedi | J106: Ajay Kumar Trivedi | K106: A30 Pillar No 538 2Nd Floor Tilak Nagar Near Janalpuri East Metro Station New Delhi 110018 | L106: A30 Pillar No 538 2Nd Floor Tilak Nagar Near Janalpuri East Metro Station New Delhi 110018 | M106: Audited | N106: NA | P106: Piyush Chouhan / 7014621268 | Q106: Abhinav Khurana | R106: 9217935065 | S106: 46119 | T106: Kumar Gaurav Agarwal & company | U106: Delhi | V106: Delhi | W106: JSE6785583 | X106: Jay Shukla | Y106: Na | Z106: Jai Ambey Associates
A107: 121 | B107: NA | C107: 355991 | D107: North | E107: Delhi | F107: Delhi | G107: Collection Agency | H107: Mf Services Private Limited | I107: Mr. Somnath, Mr. Amit Mohendru And Ms, Geeta | J107: Mr. Somnath, Mr. Amit Mohendru And Ms, Geeta | K107: P.No. - 26A, Khasra No. 5/15, Block-B, Patel Garden,Uttam Nagar, Near Kakrola Road, New Delhi-110059 | L107: P.No. - 26A, Khasra No. 5/15, Block-B, Patel Garden,Uttam Nagar, Near Kakrola Road, New Delhi-110059 | M107: Audited | N107: NA | P107: Ajay Kumar/7217827969 | Q107: Abhinav Khurana | R107: 9217935065 | S107: 46118 | T107: Kumar Gaurav Agarwal & company | U107: Delhi | V107: Delhi | W107: JSE6785583, AKE6778416 | X107: Jay Shukla, Amit Kumar | Y107: NA | Z107: Mf Services Private Limited
A108: 122 | B108: NA | C108: 317007 | D108: North | E108: Delhi | F108: Delhi | G108: Collection Agency | H108: Singh Asset Recon Services Pvt Ltd | I108: Yashpal | J108: Yashpal | K108: Plot No 36 And 36A, Third Floor Kh No-4/2 Block-C, Nishant Park Kakrola, New Delhi, South West Delhi, New Delhi 110078 | L108: Plot No 36 And 36A, Third Floor Kh No-4/2 Block-C, Nishant Park Kakrola, New Delhi, South West Delhi, New Delhi 110078 | M108: Audited | N108: NA | P108: Sanjay Kumar /9999894909 | Q108: Abhinav Khurana | R108: 9217935065 | S108: 46122 | T108: Kumar Gaurav Agarwal & company | U108: Delhi | V108: Delhi | W108: SCE6766134, JSE6775853, SSE6762160, MME6529036 | X108: Shailendra Chauhan, Jeetmani Silswal, Sushant Singh, Manoj Mishra | Y108: NA | Z108: Singh Asset Recon Services Pvt Ltd
A109: 123 | B109: Yblv0960 | C109: 118900 | D109: North | E109: Delhi | F109: Delhi | G109: Collection Agency | H109: Sss Solution | I109: Neetu Bhandari | J109: Neetu Bhandari | K109: B2 And B3 Khasra No. 2761/738 And 2762/738/1, , Second Floor, Kailash Park ,Vill. Basaidara Pur, Moti Nagar West Delhi 110015 | L109: B2 And B3 Khasra No. 2761/738 And 2762/738/1, , Second Floor, Kailash Park ,Vill. Basaidara Pur, Moti Nagar West Delhi 110015 | M109: Audited | N109: NA | P109: Vaishali / 7011037379 | Q109: Abhinav Khurana | R109: 9217935065 | S109: 46120 | T109: Kumar Gaurav Agarwal & company | U109: Delhi | V109: Haryana | W109: SKE6774754, SPE6776273, RSE6776115, SKE6779366 | X109: Satendra Kumar, Sushant Parashar, Rahul Sharma, Sumit Kumar | Y109: NA | Z109: Sss Solution
... A161: 184 | B161: Z15821 | C161: 26367 | D161: East | E161: West Bengal | F161: Kolkata | G161: Repossession Agency | H161: Relief | I161: Ranjit Singh | J161: Ranjit Singh | K161: T1-58/4, V.K.Nagar, Durgapur-10, Dist-Burdwan, West Bengal - 713210 | L161: T1-58/4, V.K.Nagar, Durgapur-10, Dist-Burdwan, West Bengal - 713210 | M161: Audited | N161: NA | P161: Saswata Chakraborty | Q161: Pradeep | R161: 8287823681 | S161: 46121 | T161: Kumar Gaurav Agarwal & company | U161: Kolkata | V161: West Bengal | W161: NA | X161: Deepak Singh, Santosh Sharma, Tarkeshwar Singh, Biswarup Ghosh , Nitesh Madhavi, Priyanka Mondal, Suryanarayan Nayak | Y161: Biswarup Ghosh, Sagar Pritishwar Choudhari, Subhasis Banerjee | Z161: Relief
A162: 185 | B162: NA | C162: NA | D162: East | E162: Assam | F162: Goalpara | G162: Stockyard | H162: Ganapati Parking Yard | I162: NA | J162: NA | K162: Vill:- Sholmari, P.S.- Agia, Dist. - Goalpara(Assam), Pin No.- 783120 | L162: Vill:- Sholmari, P.S.- Agia, Dist. - Goalpara(Assam), Pin No.- 783120 | M162: Audited | N162: NA | O162: Yes | P162: NA | Q162: Samsudin | R162: 9999934588 | S162: 46128 | T162: Kumar Gaurav Agarwal & company | U162: Goalpara | V162: Assam | W162: NA | X162: Joy Saha | Y162: NA | Z162: Ganapati Parking Yard
A163: 186 | B163: NA | C163: NA | D163: East | E163: Assam | F163: Guwahati | G163: Stockyard | H163: Rudrasagar Parking Yard | I163: NA | J163: NA | K163: Plot No 2,Betkuchi,Beltola Mouza,Dispur Circle, Dist-Kamrup Guwahati | L163: Plot No 2,Betkuchi,Beltola Mouza,Dispur Circle, Dist-Kamrup Guwahati | M163: Audited | N163: NA | O163: Yes | P163: Rahul Biswakarma | Q163: Raj Das | R163: 9999934588 | S163: 46122 | T163: Kumar Gaurav Agarwal & company | U163: Guwahati | V163: Assam | W163: NA | X163: Sudip ManBiswarup Ghosh , Pritam Khastagir, Abhishek Kumar | Y163: Biswarup Ghosh | Z163: Rudrasagar Parking Yard
A164: 187 | B164: NA | C164: NA | D164: East | E164: Assam | F164: Guwahati | G164: Stockyard | H164: S S Parking Yard - Guwahati | I164: NA | J164: NA | K164: Lalumgaon, Kotokypara Road, Lakhara, Pin - 781034 | L164: Lalumgaon, Kotokypara Road, Lakhara, Pin - 781034 | M164: Audited | N164: NA | O164: Yes | P164: Utpal Chaudhary | Q164: Raj Das | R164: 9999934588 | S164: 46122 | T164: Kumar Gaurav Agarwal & company | U164: Guwahati | V164: Assam | W164: NA | X164: Nayan Jyoti Deka, Sudip ManPritam Khastagir, Abhishek Kumar, Pritam Khatsagir | Y164: Biswarup Ghosh | Z164: S S Parking Yard - Guwahati
A165: 188 | B165: NA | C165: NA | D165: East | E165: Assam | F165: Nagaon | G165: Stockyard | H165: Luit Associates | I165: NA | J165: NA | K165: Vill- Morikolong Borghat. P.O.- Nagaon, P.S-Sadar,Dist-Nagaon(Assam),Pin-782001 | L165: Vill- Morikolong Borghat. P.O.- Nagaon, P.S-Sadar,Dist-Nagaon(Assam),Pin-782001 | M165: Audited | N165: NA | O165: Yes | P165: Piyush | Q165: Raja Khan | R165: 9999934588 | S165: 46129 | T165: Kumar Gaurav Agarwal & company | U165: Nagaon | V165: Assam | W165: NA | X165: Priyanka Mondal, Pritam Khastagir | Y165: Subhasis Banerjee, Biswarup Ghosh | Z165: Luit Associates
A166: 189 | B166: NA | C166: NA | D166: East | E166: Bihar | F166: Bihta | G166: Stockyard | H166: Raju Kumar-Janki Ventures Stock Yard | I166: NA | J166: NA | K166: Vill Korhar P.S- Bihta Po- Anandpur Camp Dist Patna Pin-801103 Beside Of Bharat Petrolium Korhar | L166: Vill Korhar P.S- Bihta Po- Anandpur Camp Dist Patna Pin-801103 Beside Of Bharat Petrolium Korhar | M166: Audited | N166: NA | O166: Yes | P166: Kundan Kumar Singh | Q166: Vishal | R166: 9999934588 | S166: 46126 | T166: Kumar Gaurav Agarwal & company | U166: Bihta | V166: Bihar | W166: NA | X166: Manibhushan Kumar, Nishant Kumar, Abhishek Kumar | Y166: Subhasis Banerjee, Biswarup Ghosh | Z166: Raju Kumar-Janki Ventures Stock Yard
A167: 190 | B167: NA | C167: NA | D167: North | E167: Chandigarh | F167: Chandigarh | G167: Stockyard | H167: Dashmesh Pitta Parking Yard | I167: NA | J167: NA | K167: V.P.O Wazidpur,Moga Road, Opposite Gurudwara Jamnni Sahib, Ferozepur, Punjab - 152004 | L167: V.P.O Wazidpur,Moga Road, Opposite Gurudwara Jamnni Sahib, Ferozepur, Punjab - 152004 | M167: Audited | N167: NA | O167: Yes | P167: Ravinder Kartaiya | Q167: Anmol Sharma | R167: 9999934588 | S167: 46130 | T167: Kumar Gaurav Agarwal & company | U167: Chandigarh | V167: Chandigarh | W167: NA | X167: Shyam Parkash | Y167: NA | Z167: Dashmesh Pitta Parking Yard
A168: 191 | B168: NA | C168: NA | D168: North | E168: Chandigarh | F168: Chandigarh | G168: Stockyard | H168: Radha Rani Parking Yard | I168: NA | J168: NA | K168: Vill Rangilpur Near Govt. School Chandigarh Road Ropar Punjab Pin 140108 | L168: Vill Rangilpur Near Govt. School Chandigarh Road Ropar Punjab Pin 140108 | M168: Audited | N168: NA | O168: Yes | P168: Dushyant | Q168: Mohit Kumar | R168: 9999934588 | S168: 46121 | T168: Kumar Gaurav Agarwal & company | U168: Chandigarh | V168: Chandigarh | W168: NA | X168: Vikram Singhrinder Pal Singh, Sachin Chauhan, Parveen Kumar, Pravin Yashwant Pawar, Sukhwinder Singh, Neeraj Kumar | Y168: Sanjeev Kumar, Rajnish Dwivedi, Chetram Chahal | Z168: Radha Rani Parking Yard
A169: 192 | B169: NA | C169: NA | D169: North | E169: Chandigarh | F169: Chandigarh | G169: Stockyard | H169: Sukhpinder Singh | I169: NA | J169: NA | K169: Kala Tibba ,Abohar 152116 | L169: Kala Tibba ,Abohar 152116 | M169: Audited | N169: NA | O169: Yes | P169: Hanuman | Q169: Suraj Kumar | R169: 9999934588 | S169: 46122 | T169: Kumar Gaurav Agarwal & company | U169: Chandigarh | V169: Chandigarh | W169: NA | X169: Gourav Bagga | Y169: Jasvendra Singh | Z169: Sukhpinder Singh
A170: 193 | B170: NA | C170: NA | D170: East | E170: Chhattisgarh | F170: Bilaspur | G170: Stockyard | H170: Jain Campus | I170: NA | J170: NA | K170: Village-Sambalpuri,Behind New High Court -Bilaspur | L170: Village-Sambalpuri,Behind New High Court -Bilaspur | M170: Audited | N170: NA | O170: Yes | P170: Ramesh Ji | Q170: Gaurav | R170: 9999934588 | S170: 46121 | T170: Kumar Gaurav Agarwal & company | U170: Bilaspur | V170: Chhattisgarh | W170: NA | X170: Mahendra Patel | Y170: NA | Z170: Jain Campus
A171: 194 | B171: NA | C171: NA | D171: East | E171: Chhattisgarh | F171: Bilaspur | G171: Stockyard | H171: Lanjewar Brother Yard | I171: NA | J171: NA | K171: Yard Address: Beside New High Court, Village Chatauna, Chkabhata, Billaspur Dist, Chattisgarhoffice Address: Shop No 19, Shahed Bhagat Singh Complex, Vyapar Vihar Road, Billaspur, Chattishgarh | L171: Yard Address: Beside New High Court, Village Chatauna, Chkabhata, Billaspur Dist, Chattisgarhoffice Address: Shop No 19, Shahed Bhagat Singh Complex, Vyapar Vihar Road, Billaspur, Chattishgarh | M171: Audited | N171: NA | O171: Yes | P171: Yash | Q171: Vishal | R171: 9999934588 | S171: 46121 | T171: Kumar Gaurav Agarwal & company | U171: Bilaspur | V171: Chhattisgarh | W171: NA | X171: Abhishek Kumar, Nitesh Madhavi | Y171: Biswarup Ghosh | Z171: Lanjewar Brother Yard
A172: 195 | B172: NA | C172: NA | D172: East | E172: Chhattisgarh | F172: Durg | G172: Stockyard | H172: Shriram Automall Raipur | I172: NA | J172: NA | K172: Shriram Automall India Limited, Survey No ; 296/1/4/15/9/7/3-5/6/7/4/6/9 And 297/1/8/3/5 Ph No : 49 At R.N.M. Ahiwara,Village Jangiri The,Dhamda,Dist Durg,Raipur,Chattisgarh. | L172: Shriram Automall India Limited, Survey No ; 296/1/4/15/9/7/3-5/6/7/4/6/9 And 297/1/8/3/5 Ph No : 49 At R.N.M. Ahiwara,Village Jangiri The,Dhamda,Dist Durg,Raipur,Chattisgarh. | M172: Audited | N172: NA | O172: Yes | P172: Laxmikant Umariya | Q172: Bhumika | R172: 9999934588 | S172: 46123 | T172: Kumar Gaurav Agarwal & company | U172: Durg | V172: Chhattisgarh | W172: NA | X172: Nitesh Ramchandra Madhavi - NME6744676 | Y172: Biswarup Ghosh | Z172: Shriram Automall Raipur
A173: 196 | B173: NA | C173: NA | D173: East | E173: Chhattisgarh | F173: Raipur | G173: Stockyard | H173: High Tech Parking | I173: NA | J173: NA | K173: Opp Durga Darmkata Dixit Door Ring Road 02 Bhanpuri Nr Best Price Shop No 01 Raipur Chattsigarh - 492001 | L173: Opp Durga Darmkata Dixit Door Ring Road 02 Bhanpuri Nr Best Price Shop No 01 Raipur Chattsigarh - 492001 | M173: Audited | N173: NA | O173: Yes | P173: Rajendra Mishra | Q173: Domesh | R173: 9999934588 | S173: 13-04-2026 & 14-04-2026 | T173: Kumar Gaurav Agarwal & company | U173: Raipur | V173: Chhattisgarh | W173: NA | X173: Nitesh Ramchandra Madhavi, Nitesh Madhavi, Rizwan Quraishi, Sourabh Parihar, K Ravi Kumar, Sudip ManAbhishek Kumar | Y173: Biswarup Ghosh, Sagar Choudhari, Subhasis Banerjee | Z173: High Tech Parking
A174: 197 | B174: NA | C174: NA | D174: East | E174: Chhattisgarh | F174: Raipur | G174: Stockyard | H174: Komal Chhatri | I174: NA | J174: NA | K174: Komal Chhattri Yard, Bhatagao,Raipur (C.G.),Pin Code - 492013 | L174: Komal Chhattri Yard, Bhatagao,Raipur (C.G.),Pin Code - 492013 | M174: Audited | N174: NA | O174: Yes | P174: Sushil | Q174: Abhijeet Swain | R174: 9999934588 | S174: 46128 | T174: Kumar Gaurav Agarwal & company | U174: Raipur | V174: Chhattisgarh | W174: NA | X174: Bineet Kumar Tiwari | Y174: NA | Z174: Komal Chhatri
A175: 198 | B175: NA | C175: NA | D175: North | E175: Delhi | F175: Delhi | G175: Stockyard | H175: Prithvi Parking Yard | I175: NA | J175: NA | K175: Village Jagat Pur, Gali No. 9A. Post Office Burari, Delhi-110084 | L175: Village Jagat Pur, Gali No. 9A. Post Office Burari, Delhi-110084 | M175: Audited | N175: NA | O175: Yes | P175: Ravindra | Q175: Aman Monga | R175: 9999934588 | S175: 46130 | T175: Kumar Gaurav Agarwal & company | U175: Delhi | V175: Delhi | W175: NA | X175: Abhinav Lal, Gopal Khatri | Y175: Abhinav Lal | Z175: Prithvi Parking Yard
A176: 199 | B176: NA | C176: NA | D176: North | E176: Delhi | F176: Delhi | G176: Stockyard | H176: Sharma Farm | I176: NA | J176: NA | K176: Gopal Nagar Najafgarh | L176: Gopal Nagar Najafgarh | M176: Audited | N176: NA | O176: Yes | P176: Anil | Q176: Aman Monga | R176: 9999934588 | S176: 46129 | T176: Kumar Gaurav Agarwal & company | U176: Delhi | V176: Delhi | W176: NA | X176: Sushim Kumarrinder Pal Singh, Rittin Arya, Manpreet singhrinder singhvdeep Rastogi, Rittin Arya | Y176: Sanjeev Kumar, Sameer Dhar, Subhasis Banerjee | Z176: Sharma Farm
A177: 200 | B177: NA | C177: NA | D177: North | E177: Delhi | F177: Delhi | G177: Stockyard | H177: Shree Mahalaxmi Enterprises | I177: NA | J177: NA | K177: Khasra No. 60-1 And 61-26. Village Bakoli , Alipur, Delhi-110034. | L177: Khasra No. 60-1 And 61-26. Village Bakoli , Alipur, Delhi-110034. | M177: Audited | N177: NA | O177: Yes | P177: Laxman | Q177: Raunak | R177: 9999934588 | S177: 46125 | T177: Kumar Gaurav Agarwal & company | U177: Delhi | V177: Delhi | W177: NA | X177: Shyam Parkash | Y177: Abhinav Lal | Z177: Shree Mahalaxmi Enterprises
A178: 201 | B178: NA | C178: NA | D178: North | E178: Delhi | F178: Delhi | G178: Stockyard | H178: Sharma Farm-Najafgarh | I178: NA | J178: NA | K178: Bakkargarh Main Dhansa Road, Najafgarh Opp. Laxmi Narayan Mandir New Delhi, Pin 110040 | L178: Bakkargarh Main Dhansa Road, Najafgarh Opp. Laxmi Narayan Mandir New Delhi, Pin 110040 | M178: Audited | N178: NA | O178: Yes | P178: Dhanraj | Q178: Raunak | R178: 9999934588 | S178: 46123 | T178: Kumar Gaurav Agarwal & company | U178: Delhi | V178: Delhi | W178: NA | X178: Sushim Kumarrinder Pal Singh, Rittin Arya, Manpreet Singhrinder Singhvdeep Rastogi, Rittin Arya | Y178: Sanjeev Kumar, Sameer Dhar, Subhasis Banerjee | Z178: Sharma Farm-Najafgarh
A179: 202 | B179: NA | C179: NA | D179: North | E179: Delhi | F179: Delhi | G179: Stockyard | H179: Gurmukh Dass And Sons Yard | I179: NA | J179: NA | K179: Gurmukh Dass And Sonskhasra, No.24-19/1,19/2,Nangloi Najafgarh Rd,Ranholla(Risal Garden) Nangloi, New Delhi-110041 | L179: Gurmukh Dass And Sonskhasra, No.24-19/1,19/2,Nangloi Najafgarh Rd,Ranholla(Risal Garden) Nangloi, New Delhi-110041 | M179: Audited | N179: NA | O179: Yes | P179: Raju Kumar | Q179: Raunak | R179: 9999934588 | S179: 46122 | T179: Kumar Gaurav Agarwal & company | U179: Delhi | V179: Delhi | W179: NA | X179: Nilesh Pednekar | Y179: NA | Z179: Gurmukh Dass And Sons Yard
A180: 203 | B180: NA | C180: NA | D180: North | E180: Delhi | F180: Delhi | G180: Stockyard | H180: S R Yard-Delhi | I180: NA | J180: NA | K180: Mamupur Pyau Manihari Road Narela Delhi 110040 | L180: Mamupur Pyau Manihari Road Narela Delhi 110040 | M180: Audited | N180: NA | O180: Yes | P180: Kundan Kumar | Q180: Raunak | R180: 9999934588 | S180: 46125 | T180: Kumar Gaurav Agarwal & company | U180: Delhi | V180: Delhi | W180: NA | X180: Ravi Parkash, Shyam Parkash | Y180: Abhinav Lal | Z180: S R Yard-Delhi
A181: 204 | B181: NA | C181: NA | D181: North | E181: Haryana | F181: Ambala | G181: Stockyard | H181: Maharishi Markanda Bank Parking Yard | I181: NA | J181: NA | K181: Warehouse Link Road,Near Guru Ravidass Mandir,Saha Panchkula Road,Saha,Distt.Ambala,Haryana,133104 | L181: Warehouse Link Road,Near Guru Ravidass Mandir,Saha Panchkula Road,Saha,Distt.Ambala,Haryana,133104 | M181: Audited | N181: NA | O181: Yes | P181: Mohit Sharma | Q181: Satendra Singh | R181: 9999934588 | S181: 46122 | T181: Kumar Gaurav Agarwal & company | U181: Ambala | V181: Haryana | W181: NA | X181: Shyam Parkash, Maninder Kumar | Y181: Abhinav Lal, Sanjeev Kumar, Sameer Dhar | Z181: Maharishi Markanda Bank Parking Yard
A182: 205 | B182: NA | C182: NA | D182: North | E182: Haryana | F182: Faridabad | G182: Stockyard | H182: S R Yard | I182: NA | J182: NA | K182: D.P Chaudhary Sports Complex, Pali Sohna Road, Village Mohtabad, Faridabad,Haryana -121004 | L182: D.P Chaudhary Sports Complex, Pali Sohna Road, Village Mohtabad, Faridabad,Haryana -121004 | M182: Audited | N182: NA | O182: Yes | P182: Mr. Sumit | Q182: Amit | R182: 9999934588 | S182: 46129 | T182: Kumar Gaurav Agarwal & company | U182: Faridabad | V182: Haryana | W182: NA | X182: Ravi Parkash, Shyam Parkash | Y182: Abhinav Lal | Z182: S R Yard
A183: 206 | B183: NA | C183: NA | D183: North | E183: Haryana | F183: Jhajjar | G183: Stockyard | H183: Baba Group Associate | I183: NA | J183: NA | K183: Vill.Khungai,Tehsil.Badli,Dist.Jhajjar,Haryana,124103 | L183: Vill.Khungai,Tehsil.Badli,Dist.Jhajjar,Haryana,124103 | M183: Audited | N183: NA | O183: Yes | P183: Sarvan | Q183: Sumit | R183: 9999934588 | S183: 46126 | T183: Kumar Gaurav Agarwal & company | U183: Jhajjar | V183: Haryana | W183: NA | X183: Shyam Parkash, Rittin Aryarinder Pal Singh | Y183: Abhinav Lal, Sanjeev Kumar | Z183: Baba Group Associate
A184: 207 | B184: NA | C184: NA | D184: North | E184: Haryana | F184: Jind | G184: Stockyard | H184: Aditya Automobiles Yard | I184: NA | J184: NA | K184: Village Biroli,On Ring Road, Near Hp Petrol Pump Jind Haryana 126102 | L184: Village Biroli,On Ring Road, Near Hp Petrol Pump Jind Haryana 126102 | M184: Audited | N184: NA | O184: A+ | P184: Anil Kumar | Q184: Mohit Kumar | R184: 9999934588 | S184: 46121 | T184: Kumar Gaurav Agarwal & company | U184: Jind | V184: Haryana | W184: NA | X184: Shyam Parkash, Surender Kumar | Y184: Jasvendra Singh | Z184: Aditya Automobiles Yard
A185: 208 | B185: NA | C185: NA | D185: North | E185: Haryana | F185: Jind | G185: Stockyard | H185: Yash Enterprises | I185: NA | J185: NA | K185: Near Satsang Nirankari Bhawan Harial Chowk Narwana- 126116 | L185: Near Satsang Nirankari Bhawan Harial Chowk Narwana- 126116 | M185: Audited | N185: NA | O185: Yes | P185: Raju | Q185: Manish Kandu | R185: 9999934588 | S185: 46122 | T185: Kumar Gaurav Agarwal & company | U185: Jind | V185: Haryana | W185: NA | X185: Nitesh Ramchandra Madhavi, Kushpal Singh | Y185: Rajnish Dwivedi | Z185: Yash Enterprises
... A295: 318 | B295: NA | C295: NA | D295: East | E295: West Bengal | F295: Usti | G295: Stockyard | H295: Jk Parking | I295: NA | J295: NA | K295: Jk Parking Vill-Po-Usti South 24 Paraganas West Bengal Pin No.743375 | L295: Jk Parking Vill-Po-Usti South 24 Paraganas West Bengal Pin No.743375 | M295: Audited | N295: NA | O295: Yes | P295: Msk | Q295: Nidhi | R295: 9999934588 | S295: 46132 | T295: Kumar Gaurav Agarwal & company | U295: Usti | V295: West Bengal | W295: NA | X295: Imran Elahi | Y295: NA | Z295: Jk Parking

Sheet Mail Mapping
A1: Sr No. | B1: Vendor Code | C1: Erp Id | D1: Zone | E1: State | F1: Location | G1: Agency Type | H1: Report Count | I1: Laado Associates | J1: Eligible Reason | K1: Audited Email | L1: EMail ID | M1: CM | N1: RCM | O1: ZCM | P1: Help | Q1: TO - | R1: CC - | S1: Subject | T1: Mail Body | U1: FPR | V1: Status
A2: 1 | B2: 66907 | C2: 66907 | D2: East | E2: Assam | F2: Guwahati | G2: Collection & Repossession Agency | H2: 1 | I2: Aba | J2: Allocaton given by Collection agency | K2: northeast@abaguwahati.co.in | L2: aba.guwahati002@gmail.com, northeast@abaguwahati.Co.in | M2: gautam.chowdhury@yes.bank.in | N2: subhasis.banerjee@yes.bank.in,mdshabbir.alam@yes.bank.in | P2: =VLOOKUP(I2,Schedule!H:AR,37,FALSE) -> NA | Q2: aba.guwahati002@gmail.com, northeast@abaguwahati.Co.in,northeast@abaguwahati.co.in | R2: =_xlfn.TEXTJOIN(",",TRUE,O2,N2,M2,"lonika.kotekar@yes.bank.in,shirajahmed.habib@yes.bank.in,Gaurav@kgac.in,AmanM@kgac.in,hariom@kgac.in") -> subhasis.banerjee@yes.bank.in,mdshabbir.alam@yes.bank.in,gautam.chowdhury@yes.bank.in,lonika.kotekar@yes.bank.in,shirajahmed.habib@yes.bank.in,Gaurav@kgac.in,AmanM@kgac.in,hariom@kgac.in | S2: =_xlfn.CONCAT("Draft audit report of ",I2,"_Collection_",F2,"_April '26_ (Audit Period Jan'26 to Mar'26)") -> Draft audit report of Aba_Collection_Guwahati_April '26_ (Audit Period Jan'26 to Mar'26) | T2: Collection & Repossession | U2: Akash Sharma
A3: 3 | B3: Yblv1123 | C3: 306987 | D3: East | E3: Assam | F3: Guwahati | G3: Collection & Repossession Agency | H3: 1 | I3: Gurseerat Legal Management Service | J3: Allocaton given by Collection agency | K3: gurseerat.yesbank@gmail.com | L3: Gurseerat.yesbank@gmail.com | M3: nitumani.kalita@yes.bank.in,subhajit.bhowmik@yes.bank.in,vaibhav.mishra2@yes.bank.in,sidharth.rana@yes.bank.in,rupesh.singh1@yes.bank.in,nayanjyoti.deka@yes.bank.in | N3: sekhar.mukharjee@yes.bank.in,mukesh.rawat2@yes.bank.in,sukhwant.singh2@yes.bank.in | P3: =VLOOKUP(I3,Schedule!H:AR,37,FALSE) -> NA | Q3: Gurseerat.yesbank@gmail.com,gurseerat.yesbank@gmail.com | R3: =_xlfn.TEXTJOIN(",",TRUE,O3,N3,M3,"lonika.kotekar@yes.bank.in,shirajahmed.habib@yes.bank.in,Gaurav@kgac.in,AmanM@kgac.in,hariom@kgac.in") -> sekhar.mukharjee@yes.bank.in,mukesh.rawat2@yes.bank.in,sukhwant.singh2@yes.bank.in,nitumani.kalita@yes.bank.in,subhajit.bhowmik@yes.bank.in,vaibhav.mishra2@yes.bank.in,sidharth.rana@yes.bank.in,rupesh.singh1@yes.bank.in,nayanjyoti.deka@yes.bank.in,lonika.kotekar@yes.bank.in,shirajahmed.habib@yes.bank.in,Gaurav@kgac.in,AmanM@kgac.in,hariom@kgac.in | S3: =_xlfn.CONCAT("Draft audit report of ",I3,"_Collection_",F3,"_April '26_ (Audit Period Jan'26 to Mar'26)") -> Draft audit report of Gurseerat Legal Management Service_Collection_Guwahati_April '26_ (Audit Period Jan'26 to Mar'26) | T3: =_xlfn.CONCAT("Please find the attached ",S3) -> Please find the attached Draft audit report of Gurseerat Legal Management Service_Collection_Guwahati_April '26_ (Audit Period Jan'26 to Mar'26) | U3: Akash Sharma
A4: 4 | B4: Yblv1107 | C4: 298994 | D4: East | E4: Assam | F4: Guwahati | G4: Collection & Repossession Agency | H4: 1 | I4: Namanshee Associates | J4: Allocaton given by Collection agency | L4: ritupankalita1987@gmail.com | M4: nayanjyoti.deka@yes.bank.in,rakesh.pathak@yes.bank.in | N4: sekhar.mukharjee@yes.bank.in,ashutosh.gupta3@yes.bank.in | P4: =VLOOKUP(I4,Schedule!H:AR,37,FALSE) -> NA | Q4: ritupankalita1987@gmail.com | R4: =_xlfn.TEXTJOIN(",",TRUE,O4,N4,M4,"lonika.kotekar@yes.bank.in,shirajahmed.habib@yes.bank.in,Gaurav@kgac.in,AmanM@kgac.in,hariom@kgac.in") -> sekhar.mukharjee@yes.bank.in,ashutosh.gupta3@yes.bank.in,nayanjyoti.deka@yes.bank.in,rakesh.pathak@yes.bank.in,lonika.kotekar@yes.bank.in,shirajahmed.habib@yes.bank.in,Gaurav@kgac.in,AmanM@kgac.in,hariom@kgac.in | S4: =_xlfn.CONCAT("Draft audit report of ",I4,"_Collection_",F4,"_April '26_ (Audit Period Jan'26 to Mar'26)") -> Draft audit report of Namanshee Associates_Collection_Guwahati_April '26_ (Audit Period Jan'26 to Mar'26) | T4: =_xlfn.CONCAT("Please find the attached ",S4) -> Please find the attached Draft audit report of Namanshee Associates_Collection_Guwahati_April '26_ (Audit Period Jan'26 to Mar'26) | U4: Akash Sharma
A5: 5 | B5: NA | C5: 327999 | D5: East | E5: Assam | F5: Guwahati | G5: Collection & Repossession Agency | H5: 1 | I5: Uttaran | J5: Allocaton given by Collection & Repossession | K5: uttaran.ne0325@gmail.com | L5: uttaran7@yahoo.in | M5: roshmi.wary@yes.bank.in,nitumani.kalita@yes.bank.in,rakesh.pathak@yes.bank.in,nayanjyoti.deka@yes.bank.in | N5: ashutosh.gupta3@yes.bank.in,biswarup.ghosh@yes.bank.in,sekhar.mukharjee@yes.bank.in,subhasis.banerjee@yes.bank.in,gitartha.sarma@yes.bank.in | O5: ashutosh.gupta3@yes.bank.in | P5: =VLOOKUP(I5,Schedule!H:AR,37,FALSE) -> NA | Q5: uttaran7@yahoo.in,uttaran.ne0325@gmail.com | R5: =_xlfn.TEXTJOIN(",",TRUE,O5,N5,M5,"lonika.kotekar@yes.bank.in,shirajahmed.habib@yes.bank.in,Gaurav@kgac.in,AmanM@kgac.in,hariom@kgac.in") -> ashutosh.gupta3@yes.bank.in,ashutosh.gupta3@yes.bank.in,biswarup.ghosh@yes.bank.in,sekhar.mukharjee@yes.bank.in,subhasis.banerjee@yes.bank.in,gitartha.sarma@yes.bank.in,roshmi.wary@yes.bank.in,nitumani.kalita@yes.bank.in,rakesh.pathak@yes.bank.in,nayanjyoti.deka@yes.bank.in,lonika.kotekar@yes.bank.in,shirajahmed.habib@yes.bank.in,Gaurav@kgac.in,AmanM@kgac.in,hariom@kgac.in | S5: =_xlfn.CONCAT("Draft audit report of ",I5,"_Collection & Repossession_",F5,"_April '26_ (Audit Period Jan'26 to Mar'26)") -> Draft audit report of Uttaran_Collection & Repossession_Guwahati_April '26_ (Audit Period Jan'26 to Mar'26) | T5: =_xlfn.CONCAT("Please find the attached ",S5) -> Please find the attached Draft audit report of Uttaran_Collection & Repossession_Guwahati_April '26_ (Audit Period Jan'26 to Mar'26) | U5: Hariom Sharma | V5: Done
A6: 7 | B6: Z20543 | C6: 25557 | D6: East | E6: Bihar | F6: Patna | G6: Collection & Repossession Agency | H6: 2 | I6: Aim Corporate - Patna | J6: Allocaton given by Collection agency | K6: collections5@aimcorporte.co | L6: collections5@aimcorporate.co | M6: krishnendu.sarder@yes.bank.in,saisab.mallick@yes.bank.in,imran.elahi@yes.bank.in,priyanka.mondal@yes.bank.in,ritam.basak@yes.bank.in,deepak.singh39@yes.bank.in,suryanarayan.nayak@yes.bank.in,arindam.sarkar2@yes.bank.in,tarkeshwar.singh@yes.bank.in,nishant.kumar16@yes.bank.in,rajkumar.hazra@yes.bank.in,abhisek.bose@yes.bank.in,ossam.aditya@yes.bank.in,soumitra.ghosh1@yes.bank.in,monawwar.alam1@yes.bank.in | N6: sekhar.mukharjee@yes.bank.in,manikandan.g4@yes.bank.in,subhasis.banerjee@yes.bank.in,biswarup.ghosh@yes.bank.in,mdshabbir.alam@yes.bank.in | O6: manikandan.g4@yes.bank.in | P6: =VLOOKUP(I6,Schedule!H:AR,37,FALSE) -> Audited for Collection Only, as no activity of repossession are done for the audit quarter | Q6: collections5@aimcorporate.co,collections5@aimcorporte.co | R6: =_xlfn.TEXTJOIN(",",TRUE,O6,N6,M6,"lonika.kotekar@yes.bank.in,shirajahmed.habib@yes.bank.in,Gaurav@kgac.in,AmanM@kgac.in,hariom@kgac.in") -> manikandan.g4@yes.bank.in,sekhar.mukharjee@yes.bank.in,manikandan.g4@yes.bank.in,subhasis.banerjee@yes.bank.in,biswarup.ghosh@yes.bank.in,mdshabbir.alam@yes.bank.in,krishnendu.sarder@yes.bank.in,saisab.mallick@yes.bank.in,imran.elahi@yes.bank.in,priyanka.mondal@yes.bank.in,ritam.basak@yes.bank.in,deepak.singh39@yes.bank.in,suryanarayan.nayak@yes.bank.in,arindam.sarkar2@yes.bank.in,tarkeshwar.singh@yes.bank.in,nishant.kumar16@yes.bank.in,rajkumar.hazra@yes.bank.in,abhisek.bose@yes.bank.in,ossam.aditya@yes.bank.in,soumitra.ghosh1@yes.bank.in,monawwar.alam1@yes.bank.in,lonika.kotekar@yes.bank.in,shirajahmed.habib@yes.bank.in,Gaurav@kgac.in,AmanM@kgac.in,hariom@kgac.in | S6: =_xlfn.CONCAT("Draft audit report of ","Aim Corporate","_Collection_","Patna, Kolkata","_April '26_ (Audit Period Jan'26 to Mar'26)") -> Draft audit report of Aim Corporate_Collection_Patna, Kolkata_April '26_ (Audit Period Jan'26 to Mar'26) | T6: =_xlfn.CONCAT("Please find the attached ",S6) -> Please find the attached Draft audit report of Aim Corporate_Collection_Patna, Kolkata_April '26_ (Audit Period Jan'26 to Mar'26) | U6: Hariom Sharma | V6: Done
